Workbook

Sheet DEC 2026
A1: 44895 | C1: RECETTE | G1: CAISSE | M1: MOUVEMENT CAISSE | P1: CAISSE MOIS PREC | Q1: PAYEMENT FOURNISSEUR CAISSE | R1: MONTANT | S1: TOTAL | T1: DATE SORTIE | Y1: FOURNISSEUR | Z1: DATE | AA1: REFERENCE | AB1: COMPTE | AC1: HTVA | AD1: TVA | AE1: MONTANT | AF1: PAIEMENT | AG1: CAISSE | AH1: DATE | AI1: ECHEANCE
A2: DATE | B2: FACTURE | C2: 6 | D2: 12 | E2: 21 | F2: TOTAL | G2: CHIFF | H2: carte | I2: cadeau0 | J2: bque | K2: liquide | L2: TOT CAIS | M2: SORTIE | N2: vers ban | O2: solde cai | P2: ='NOV 2026'!P33 -> 268.9 | AB2: 44895
A3: 44895 | F3: =SUM(B3:E3) -> 0 | G3: =F3 -> 0 | K3: =SUM(F3-H3-J3-I3) -> 0 | L3: =SUM(F3-H3-J3-I3) -> 0 | O3: =SUM(L3-M3-N3+P2) -> 268.9 | X3: 1 | AE3: =SUM(AC3:AD3) -> 0 | AJ3: 0
A4: 44896 | F4: =SUM(B4:E4) -> 0 | G4: =F4 -> 0 | K4: =SUM(F4-H4-J4-I4) -> 0 | L4: =SUM(F4-H4-J4-I4) -> 0 | O4: =SUM(L4-M4-N4+O3+P4) -> 268.9 | X4: 2 | AE4: =SUM(AC4:AD4) -> 0 | AJ4: =AE4 -> 0
A5: 44897 | F5: =SUM(B5:E5) -> 0 | G5: =F5 -> 0 | K5: =SUM(F5-H5-J5-I5) -> 0 | L5: =SUM(F5-H5-J5-I5) -> 0 | O5: =SUM(L5-M5-N5+O4+P5) -> 268.9 | X5: 3 | AE5: =SUM(AC5:AD5) -> 0 | AJ5: 0
A6: 44898 | F6: =SUM(B6:E6) -> 0 | G6: =F6 -> 0 | K6: =SUM(F6-H6-J6-I6) -> 0 | L6: =SUM(F6-H6-J6-I6) -> 0 | O6: =SUM(L6-M6-N6+O5+P6) -> 268.9 | X6: 4 | AE6: =SUM(AC6:AD6) -> 0 | AJ6: 0
A7: 44899 | F7: =SUM(B7:E7) -> 0 | G7: =F7 -> 0 | K7: =SUM(F7-H7-J7-I7) -> 0 | L7: =SUM(F7-H7-J7-I7) -> 0 | O7: =SUM(L7-M7-N7+O6+P7) -> 268.9 | X7: 5 | AE7: =SUM(AC7:AD7) -> 0 | AJ7: 0
A8: 44900 | F8: =SUM(B8:E8) -> 0 | G8: =F8 -> 0 | K8: =SUM(F8-H8-J8-I8) -> 0 | L8: =SUM(F8-H8-J8-I8) -> 0 | O8: =SUM(L8-M8-N8+O7+P8) -> 268.9 | X8: 6 | AE8: =SUM(AC8:AD8) -> 0 | AJ8: 0
A9: 44901 | F9: =SUM(B9:E9) -> 0 | G9: =F9 -> 0 | K9: =SUM(F9-H9-J9-I9) -> 0 | L9: =SUM(F9-H9-J9-I9) -> 0 | O9: =SUM(L9-M9-N9+O8) -> 268.9 | X9: 7 | AE9: =SUM(AC9:AD9) -> 0 | AJ9: =AE9 -> 0
A10: 44902 | F10: =SUM(B10:E10) -> 0 | G10: =F10 -> 0 | K10: =SUM(F10-H10-J10-I10) -> 0 | L10: =SUM(F10-H10-J10-I10) -> 0 | O10: =SUM(L10-M10-N10+O9) -> 268.9 | X10: 8 | AE10: =SUM(AC10:AD10) -> 0 | AJ10: =AE10 -> 0
A11: 44903 | F11: =SUM(B11:E11) -> 0 | G11: =F11 -> 0 | K11: =SUM(F11-H11-J11-I11) -> 0 | L11: =SUM(F11-H11-J11-I11) -> 0 | O11: =SUM(L11-M11-N11+O10) -> 268.9 | X11: 9 | AE11: =SUM(AC11:AD11) -> 0 | AJ11: =AE11 -> 0
A12: 44904 | F12: =SUM(B12:E12) -> 0 | G12: =F12 -> 0 | K12: =SUM(F12-H12-J12-I12) -> 0 | L12: =SUM(F12-H12-J12-I12) -> 0 | O12: =SUM(L12-M12-N12+O11) -> 268.9 | X12: 10 | AE12: =SUM(AC12:AD12) -> 0 | AJ12: =AE12 -> 0
A13: 44905 | F13: =SUM(B13:E13) -> 0 | G13: =F13 -> 0 | K13: =SUM(F13-H13-J13-I13) -> 0 | L13: =SUM(F13-H13-J13-I13) -> 0 | O13: =SUM(L13-M13-N13+O12) -> 268.9 | X13: 11 | AE13: =SUM(AC13:AD13) -> 0 | AJ13: =AE13 -> 0
A14: 44906 | F14: =SUM(B14:E14) -> 0 | G14: =F14 -> 0 | K14: =SUM(F14-H14-J14-I14) -> 0 | L14: =SUM(F14-H14-J14-I14) -> 0 | O14: =SUM(L14-M14-N14+O13) -> 268.9 | X14: 12 | AE14: =SUM(AC14:AD14) -> 0 | AJ14: =AE14 -> 0
A15: 44907 | F15: =SUM(B15:E15) -> 0 | G15: =F15 -> 0 | K15: =SUM(F15-H15-J15-I15) -> 0 | L15: =SUM(F15-H15-J15-I15) -> 0 | O15: =SUM(L15-M15-N15+O14) -> 268.9 | X15: 13 | AE15: =SUM(AC15:AD15) -> 0 | AJ15: =AE15 -> 0
A16: 44908 | F16: =SUM(B16:E16) -> 0 | G16: =F16 -> 0 | K16: =SUM(F16-H16-J16-I16) -> 0 | L16: =SUM(F16-H16-J16-I16) -> 0 | O16: =SUM(L16-M16-N16+O15) -> 268.9 | X16: 14 | AE16: =SUM(AC16:AD16) -> 0 | AJ16: =AE16 -> 0
A17: 44909 | F17: =SUM(B17:E17) -> 0 | G17: =F17 -> 0 | K17: =SUM(F17-H17-J17-I17) -> 0 | L17: =SUM(F17-H17-J17-I17) -> 0 | O17: =SUM(L17-M17-N17+O16+P17) -> 268.9 | X17: 15 | AE17: =SUM(AC17:AD17) -> 0 | AJ17: =AE17 -> 0
A18: 44910 | F18: =SUM(B18:E18) -> 0 | G18: =F18 -> 0 | K18: =SUM(F18-H18-J18-I18) -> 0 | L18: =SUM(F18-H18-J18-I18) -> 0 | O18: =SUM(L18-M18-N18+O17+P18) -> 268.9 | X18: 16 | AE18: =SUM(AC18:AD18) -> 0 | AJ18: =AE18 -> 0
A19: 44911 | F19: =SUM(B19:E19) -> 0 | G19: =F19 -> 0 | K19: =SUM(F19-H19-J19-I19) -> 0 | L19: =SUM(F19-H19-J19-I19) -> 0 | O19: =SUM(L19-M19-N19+O18+P19) -> 268.9 | X19: 17 | AE19: =SUM(AC19:AD19) -> 0 | AJ19: =AE19 -> 0
A20: 44912 | F20: =SUM(B20:E20) -> 0 | G20: =F20 -> 0 | K20: =SUM(F20-H20-J20-I20) -> 0 | L20: =SUM(F20-H20-J20-I20) -> 0 | O20: =SUM(L20-M20-N20+O19+P20) -> 268.9 | X20: 18 | AE20: =SUM(AC20:AD20) -> 0 | AJ20: =AE20 -> 0
A21: 44913 | F21: =SUM(B21:E21) -> 0 | G21: =F21 -> 0 | K21: =SUM(F21-H21-J21-I21) -> 0 | L21: =SUM(F21-H21-J21-I21) -> 0 | O21: =SUM(L21-M21-N21+O20) -> 268.9 | X21: 19 | AE21: =SUM(AC21:AD21) -> 0 | AJ21: =AE21 -> 0
A22: 44914 | F22: =SUM(B22:E22) -> 0 | G22: =F22 -> 0 | K22: =SUM(F22-H22-J22-I22) -> 0 | L22: =SUM(F22-H22-J22-I22) -> 0 | O22: =SUM(L22-M22-N22+O21) -> 268.9 | X22: 20 | AE22: =SUM(AC22:AD22) -> 0 | AJ22: =AE22 -> 0
A23: 44915 | F23: =SUM(B23:E23) -> 0 | G23: =F23 -> 0 | K23: =SUM(F23-H23-J23-I23) -> 0 | L23: =SUM(F23-H23-J23-I23) -> 0 | O23: =SUM(L23-M23-N23+O22) -> 268.9 | X23: 21 | AE23: =SUM(AC23:AD23) -> 0 | AJ23: =AE23 -> 0
A24: 44916 | F24: =SUM(B24:E24) -> 0 | G24: =F24 -> 0 | K24: =SUM(F24-H24-J24-I24) -> 0 | L24: =SUM(F24-H24-J24-I24) -> 0 | O24: =SUM(L24-M24-N24+O23+P24) -> 268.9 | X24: 22 | AE24: =SUM(AC24:AD24) -> 0 | AJ24: =AE24 -> 0
A25: 44917 | F25: =SUM(B25:E25) -> 0 | G25: =F25 -> 0 | K25: =SUM(F25-H25-J25-I25) -> 0 | L25: =SUM(F25-H25-J25-I25) -> 0 | O25: =SUM(L25-M25-N25+O24) -> 268.9 | X25: 26 | AE25: =SUM(AC25:AD25) -> 0 | AJ25: =AE25 -> 0
A26: 44918 | F26: =SUM(B26:E26) -> 0 | G26: =F26 -> 0 | K26: =SUM(F26-H26-J26-I26) -> 0 | L26: =SUM(F26-H26-J26-I26) -> 0 | O26: =SUM(L26-M26-N26+O25) -> 268.9 | X26: 27 | AE26: =SUM(AC26:AD26) -> 0 | AJ26: =AE26 -> 0
A27: 44919 | F27: =SUM(B27:E27) -> 0 | G27: =F27 -> 0 | K27: =SUM(F27-H27-J27-I27) -> 0 | L27: =SUM(F27-H27-J27-I27) -> 0 | O27: =SUM(L27-M27-N27+O26) -> 268.9 | X27: 28 | AE27: =SUM(AC27:AD27) -> 0 | AJ27: =AE27 -> 0
A28: 44920 | F28: =SUM(B28:E28) -> 0 | G28: =F28 -> 0 | K28: =SUM(F28-H28-J28-I28) -> 0 | L28: =SUM(F28-H28-J28-I28) -> 0 | O28: =SUM(L28-M28-N28+O27+P28) -> 268.9 | X28: 29 | AE28: =SUM(AC28:AD28) -> 0 | AJ28: =AE28 -> 0
A29: 44921 | F29: =SUM(B29:E29) -> 0 | G29: =F29 -> 0 | K29: =SUM(F29-H29-J29-I29) -> 0 | L29: =SUM(F29-H29-J29-I29) -> 0 | O29: =SUM(L29-M29-N29+O28) -> 268.9 | X29: 30 | AE29: =SUM(AC29:AD29) -> 0 | AJ29: =AE29 -> 0
A30: 44922 | F30: =SUM(B30:E30) -> 0 | G30: =F30 -> 0 | K30: =SUM(F30-H30-J30-I30) -> 0 | L30: =SUM(F30-H30-J30-I30) -> 0 | O30: =SUM(L30-M30-N30+O29+P30) -> 268.9 | AC30: TVA | AD30: =SUM(AD3:AD29) -> 0
A31: 44923 | F31: =SUM(B31:E31) -> 0 | G31: =F31 -> 0 | K31: =SUM(F31-H31-J31-I31) -> 0 | L31: =SUM(F31-H31-J31-I31) -> 0 | O31: =SUM(L31-M31-N31+O30) -> 268.9 | P31: SOLDE CAISSE
A32: 44924 | F32: =SUM(B32:E32) -> 0 | G32: =F32 -> 0 | K32: =SUM(F32-H32-J32-I32) -> 0 | L32: =SUM(F32-H32-J32-I32) -> 0 | O32: =SUM(L32-M32-N32+O31) -> 268.9 | P32: DU MOIS | AA32: MARGE | AL32: calcul de marge
A33: 44925 | F33: =SUM(B33:E33) -> 0 | G33: =F33 -> 0 | K33: =SUM(F33-H33-J33-I33) -> 0 | L33: =SUM(F33-H33-J33-I33) -> 0 | O33: =SUM(L33-M33-N33+O32) -> 268.9 | P33: =SUM(O33) -> 268.9 | X33: 1 | AE33: =SUM(AC33:AD33) -> 0 | AJ33: 0 | AL33: =AC33 -> 0 | AM33: 1
B34: =SUM(B5:B33) -> 0 | C34: =SUM(C3:C33) -> 0 | D34: =SUM(D3:D33) -> 0 | E34: =SUM(E3:E33) -> 0 | F34: =SUM(F3:F33) -> 0 | H34: =SUM(H3:H33) -> 0 | J34: =SUM(J3:J33) -> 0 | K34: =SUM(K3:K33) -> 0 | L34: =SUM(L3:L33) -> 0 | M34: =SUM(M3:M33) -> 0 | N34: =SUM(N3:N33) -> 0 | X34: 2 | AE34: =SUM(AC34:AD34) -> 0 | AJ34: =AE34 -> 0 | AL34: =AC34 -> 0 | AM34: 2
A35: HTVA | B35: =SUM(B3:B33) -> 0 | C35: =SUM(C34/1.06) -> 0 | D35: =SUM(D34/1.12) -> 0 | E35: =SUM(E34/1.21) -> 0 | F35: =SUM(B35:E35) -> 0 | G35: =SUM(G34:G34) -> 0 | L35: TOTAL SORTIE | N35: =SUM(M34:N34) -> 0 | X35: 3 | AE35: =SUM(AC35:AD35) -> 0 | AJ35: =AE35 -> 0 | AL35: =AC35 -> 0 | AM35: 3
A36: TVA | C36: =SUM(C34-C35) -> 0 | D36: =SUM(D34-D35) -> 0 | E36: =SUM(E34-E35) -> 0 | F36: =SUM(C36:E36) -> 0 | X36: 4 | AE36: =SUM(AC36:AD36) -> 0 | AJ36: 0 | AL36: =AC36 -> 0 | AM36: 4
X37: 5 | AE37: =SUM(AC37:AD37) -> 0 | AJ37: =AE37 -> 0 | AL37: =AC37 -> 0 | AM37: 5
X38: 6 | AE38: =SUM(AC38:AD38) -> 0 | AJ38: 0 | AL38: =AC38 -> 0 | AM38: 6
X39: 7 | AE39: =SUM(AC39:AD39) -> 0 | AJ39: =AE39 -> 0 | AL39: =AC39 -> 0 | AM39: 7
X40: 8 | AE40: =SUM(AC40:AD40) -> 0 | AJ40: =AE40 -> 0 | AL40: =AC40 -> 0 | AM40: 8
X41: 9 | AE41: =SUM(AC41:AD41) -> 0 | AJ41: =AE41 -> 0 | AL41: =AC41 -> 0 | AM41: 9
X42: 10 | AE42: =SUM(AC42:AD42) -> 0 | AJ42: =AE42 -> 0 | AL42: =AC42 -> 0 | AM42: 10
X43: 11 | AE43: =SUM(AC43:AD43) -> 0 | AJ43: =AE43 -> 0 | AL43: =AC43 -> 0 | AM43: 11
X44: 12 | AE44: =SUM(AC44:AD44) -> 0 | AJ44: =AE44 -> 0 | AL44: =AC44 -> 0 | AM44: 12
X45: 13 | AE45: =SUM(AC45:AD45) -> 0 | AJ45: =AE45 -> 0 | AL45: =AC45 -> 0 | AM45: 13
X46: 14 | AE46: =SUM(AC46:AD46) -> 0 | AJ46: =AE46 -> 0 | AL46: =AC46 -> 0 | AM46: 14
X47: 15 | AE47: =SUM(AC47:AD47) -> 0 | AJ47: =AE47 -> 0 | AL47: =AC47 -> 0 | AM47: 15
X48: 16 | AE48: =SUM(AC48:AD48) -> 0 | AJ48: =AE48 -> 0 | AL48: =AC48 -> 0 | AM48: 16
X49: 17 | AE49: =SUM(AC49:AD49) -> 0 | AJ49: =AE49 -> 0 | AL49: =AC49 -> 0 | AM49: 17
X50: 18 | AE50: =SUM(AC50:AD50) -> 0 | AJ50: =AE50 -> 0 | AL50: =AC50 -> 0 | AM50: 18
... X62: 30 | AE62: =SUM(AC62:AD62) -> 0 | AJ62: =AE62 -> 0 | AL62: =AC62 -> 0 | AM62: 30
AC63: =SUM(AC33:AC62) -> 0 | AH63: TOTAL GENE FEUILLE | AJ63: =SUM(AJ3:AJ62) -> 0 | AL63: =AC63 -> 0
AC64: TVA | AD64: =SUM(AD33:AD63) -> 0
AI66: A PÄYER
AC67: TVA | AD67: =AD30 -> 0 | AJ67: =AJ63 -> 0
AC68: TVA | AD68: =AD64 -> 0 | AI68: mois précèdent | AJ68: ='JANV 2026'!AJ69 -> 0
AC69: TVA RECUP | AD69: =SUM(AD67:AD68) -> 0 | AI69: total a payer | AJ69: =SUM(AJ67:AJ68) -> 0

Sheet NOV 2026
A1: 44865 | C1: RECETTE | G1: CAISSE | M1: MOUVEMENT CAISSE | P1: CAISSE MOIS PREC | Q1: PAYEMENT FOURNISSEUR CAISSE | R1: MONTANT | S1: TOTAL | T1: DATE SORTIE | Y1: FOURNISSEUR | Z1: DATE | AA1: REFERENCE | AB1: COMPTE | AC1: HTVA | AD1: TVA | AE1: MONTANT | AF1: PAIEMENT | AG1: CAISSE | AH1: DATE | AI1: ECHEANCE
A2: DATE | B2: FACTURE | C2: 6 | D2: 12 | E2: 21 | F2: TOTAL | G2: CHIFF | H2: carte | I2: cadeau0 | J2: bque | K2: liquide | L2: TOT CAIS | M2: SORTIE | N2: vers ban | O2: solde cai | P2: ='OCT 2026'!P33 -> 268.9 | AB2: 44865
A3: 44865 | F3: =SUM(B3:E3) -> 0 | G3: =F3 -> 0 | K3: =SUM(F3-H3-J3-I3) -> 0 | L3: =SUM(F3-H3-J3-I3) -> 0 | O3: =SUM(L3-M3-N3+P2) -> 268.9 | X3: 1 | AE3: =SUM(AC3:AD3) -> 0 | AJ3: 0
A4: 44866 | F4: =SUM(B4:E4) -> 0 | G4: =F4 -> 0 | K4: =SUM(F4-H4-J4-I4) -> 0 | L4: =SUM(F4-H4-J4-I4) -> 0 | O4: =SUM(L4-M4-N4+O3+P4) -> 268.9 | X4: 2 | AE4: =SUM(AC4:AD4) -> 0 | AJ4: =AE4 -> 0
A5: 44867 | F5: =SUM(B5:E5) -> 0 | G5: =F5 -> 0 | K5: =SUM(F5-H5-J5-I5) -> 0 | L5: =SUM(F5-H5-J5-I5) -> 0 | O5: =SUM(L5-M5-N5+O4+P5) -> 268.9 | X5: 3 | AE5: =SUM(AC5:AD5) -> 0 | AJ5: 0
A6: 44868 | F6: =SUM(B6:E6) -> 0 | G6: =F6 -> 0 | K6: =SUM(F6-H6-J6-I6) -> 0 | L6: =SUM(F6-H6-J6-I6) -> 0 | O6: =SUM(L6-M6-N6+O5+P6) -> 268.9 | X6: 4 | AE6: =SUM(AC6:AD6) -> 0 | AJ6: 0
A7: 44869 | F7: =SUM(B7:E7) -> 0 | G7: =F7 -> 0 | K7: =SUM(F7-H7-J7-I7) -> 0 | L7: =SUM(F7-H7-J7-I7) -> 0 | O7: =SUM(L7-M7-N7+O6+P7) -> 268.9 | X7: 5 | AE7: =SUM(AC7:AD7) -> 0 | AJ7: 0
A8: 44870 | F8: =SUM(B8:E8) -> 0 | G8: =F8 -> 0 | K8: =SUM(F8-H8-J8-I8) -> 0 | L8: =SUM(F8-H8-J8-I8) -> 0 | O8: =SUM(L8-M8-N8+O7+P8) -> 268.9 | X8: 6 | AE8: =SUM(AC8:AD8) -> 0 | AJ8: 0
A9: 44871 | F9: =SUM(B9:E9) -> 0 | G9: =F9 -> 0 | K9: =SUM(F9-H9-J9-I9) -> 0 | L9: =SUM(F9-H9-J9-I9) -> 0 | O9: =SUM(L9-M9-N9+O8) -> 268.9 | X9: 7 | AE9: =SUM(AC9:AD9) -> 0 | AJ9: =AE9 -> 0
A10: 44872 | F10: =SUM(B10:E10) -> 0 | G10: =F10 -> 0 | K10: =SUM(F10-H10-J10-I10) -> 0 | L10: =SUM(F10-H10-J10-I10) -> 0 | O10: =SUM(L10-M10-N10+O9) -> 268.9 | X10: 8 | AE10: =SUM(AC10:AD10) -> 0 | AJ10: =AE10 -> 0
A11: 44873 | F11: =SUM(B11:E11) -> 0 | G11: =F11 -> 0 | K11: =SUM(F11-H11-J11-I11) -> 0 | L11: =SUM(F11-H11-J11-I11) -> 0 | O11: =SUM(L11-M11-N11+O10) -> 268.9 | X11: 9 | AE11: =SUM(AC11:AD11) -> 0 | AJ11: =AE11 -> 0
A12: 44874 | F12: =SUM(B12:E12) -> 0 | G12: =F12 -> 0 | K12: =SUM(F12-H12-J12-I12) -> 0 | L12: =SUM(F12-H12-J12-I12) -> 0 | O12: =SUM(L12-M12-N12+O11) -> 268.9 | X12: 10 | AE12: =SUM(AC12:AD12) -> 0 | AJ12: =AE12 -> 0
A13: 44875 | F13: =SUM(B13:E13) -> 0 | G13: =F13 -> 0 | K13: =SUM(F13-H13-J13-I13) -> 0 | L13: =SUM(F13-H13-J13-I13) -> 0 | O13: =SUM(L13-M13-N13+O12) -> 268.9 | X13: 11 | AE13: =SUM(AC13:AD13) -> 0 | AJ13: =AE13 -> 0
A14: 44876 | F14: =SUM(B14:E14) -> 0 | G14: =F14 -> 0 | K14: =SUM(F14-H14-J14-I14) -> 0 | L14: =SUM(F14-H14-J14-I14) -> 0 | O14: =SUM(L14-M14-N14+O13) -> 268.9 | X14: 12 | AE14: =SUM(AC14:AD14) -> 0 | AJ14: =AE14 -> 0
A15: 44877 | F15: =SUM(B15:E15) -> 0 | G15: =F15 -> 0 | K15: =SUM(F15-H15-J15-I15) -> 0 | L15: =SUM(F15-H15-J15-I15) -> 0 | O15: =SUM(L15-M15-N15+O14) -> 268.9 | X15: 13 | AE15: =SUM(AC15:AD15) -> 0 | AJ15: =AE15 -> 0
A16: 44878 | F16: =SUM(B16:E16) -> 0 | G16: =F16 -> 0 | K16: =SUM(F16-H16-J16-I16) -> 0 | L16: =SUM(F16-H16-J16-I16) -> 0 | O16: =SUM(L16-M16-N16+O15) -> 268.9 | X16: 14 | AE16: =SUM(AC16:AD16) -> 0 | AJ16: =AE16 -> 0
A17: 44879 | F17: =SUM(B17:E17) -> 0 | G17: =F17 -> 0 | K17: =SUM(F17-H17-J17-I17) -> 0 | L17: =SUM(F17-H17-J17-I17) -> 0 | O17: =SUM(L17-M17-N17+O16+P17) -> 268.9 | X17: 15 | AE17: =SUM(AC17:AD17) -> 0 | AJ17: =AE17 -> 0
A18: 44880 | F18: =SUM(B18:E18) -> 0 | G18: =F18 -> 0 | K18: =SUM(F18-H18-J18-I18) -> 0 | L18: =SUM(F18-H18-J18-I18) -> 0 | O18: =SUM(L18-M18-N18+O17+P18) -> 268.9 | X18: 16 | AE18: =SUM(AC18:AD18) -> 0 | AJ18: =AE18 -> 0
A19: 44881 | F19: =SUM(B19:E19) -> 0 | G19: =F19 -> 0 | K19: =SUM(F19-H19-J19-I19) -> 0 | L19: =SUM(F19-H19-J19-I19) -> 0 | O19: =SUM(L19-M19-N19+O18+P19) -> 268.9 | X19: 17 | AE19: =SUM(AC19:AD19) -> 0 | AJ19: =AE19 -> 0
A20: 44882 | F20: =SUM(B20:E20) -> 0 | G20: =F20 -> 0 | K20: =SUM(F20-H20-J20-I20) -> 0 | L20: =SUM(F20-H20-J20-I20) -> 0 | O20: =SUM(L20-M20-N20+O19+P20) -> 268.9 | X20: 18 | AE20: =SUM(AC20:AD20) -> 0 | AJ20: =AE20 -> 0
A21: 44883 | F21: =SUM(B21:E21) -> 0 | G21: =F21 -> 0 | K21: =SUM(F21-H21-J21-I21) -> 0 | L21: =SUM(F21-H21-J21-I21) -> 0 | O21: =SUM(L21-M21-N21+O20) -> 268.9 | X21: 19 | AE21: =SUM(AC21:AD21) -> 0 | AJ21: =AE21 -> 0
A22: 44884 | F22: =SUM(B22:E22) -> 0 | G22: =F22 -> 0 | K22: =SUM(F22-H22-J22-I22) -> 0 | L22: =SUM(F22-H22-J22-I22) -> 0 | O22: =SUM(L22-M22-N22+O21) -> 268.9 | X22: 20 | AE22: =SUM(AC22:AD22) -> 0 | AJ22: =AE22 -> 0
A23: 44885 | F23: =SUM(B23:E23) -> 0 | G23: =F23 -> 0 | K23: =SUM(F23-H23-J23-I23) -> 0 | L23: =SUM(F23-H23-J23-I23) -> 0 | O23: =SUM(L23-M23-N23+O22) -> 268.9 | X23: 21 | AE23: =SUM(AC23:AD23) -> 0 | AJ23: =AE23 -> 0
A24: 44886 | F24: =SUM(B24:E24) -> 0 | G24: =F24 -> 0 | K24: =SUM(F24-H24-J24-I24) -> 0 | L24: =SUM(F24-H24-J24-I24) -> 0 | O24: =SUM(L24-M24-N24+O23+P24) -> 268.9 | X24: 22 | AE24: =SUM(AC24:AD24) -> 0 | AJ24: =AE24 -> 0
A25: 44887 | F25: =SUM(B25:E25) -> 0 | G25: =F25 -> 0 | K25: =SUM(F25-H25-J25-I25) -> 0 | L25: =SUM(F25-H25-J25-I25) -> 0 | O25: =SUM(L25-M25-N25+O24) -> 268.9 | X25: 26 | AE25: =SUM(AC25:AD25) -> 0 | AJ25: =AE25 -> 0
A26: 44888 | F26: =SUM(B26:E26) -> 0 | G26: =F26 -> 0 | K26: =SUM(F26-H26-J26-I26) -> 0 | L26: =SUM(F26-H26-J26-I26) -> 0 | O26: =SUM(L26-M26-N26+O25) -> 268.9 | X26: 27 | AE26: =SUM(AC26:AD26) -> 0 | AJ26: =AE26 -> 0
A27: 44889 | F27: =SUM(B27:E27) -> 0 | G27: =F27 -> 0 | K27: =SUM(F27-H27-J27-I27) -> 0 | L27: =SUM(F27-H27-J27-I27) -> 0 | O27: =SUM(L27-M27-N27+O26) -> 268.9 | X27: 28 | AE27: =SUM(AC27:AD27) -> 0 | AJ27: =AE27 -> 0
A28: 44890 | F28: =SUM(B28:E28) -> 0 | G28: =F28 -> 0 | K28: =SUM(F28-H28-J28-I28) -> 0 | L28: =SUM(F28-H28-J28-I28) -> 0 | O28: =SUM(L28-M28-N28+O27+P28) -> 268.9 | X28: 29 | AE28: =SUM(AC28:AD28) -> 0 | AJ28: =AE28 -> 0
A29: 44891 | F29: =SUM(B29:E29) -> 0 | G29: =F29 -> 0 | K29: =SUM(F29-H29-J29-I29) -> 0 | L29: =SUM(F29-H29-J29-I29) -> 0 | O29: =SUM(L29-M29-N29+O28) -> 268.9 | X29: 30 | AE29: =SUM(AC29:AD29) -> 0 | AJ29: =AE29 -> 0
A30: 44892 | F30: =SUM(B30:E30) -> 0 | G30: =F30 -> 0 | K30: =SUM(F30-H30-J30-I30) -> 0 | L30: =SUM(F30-H30-J30-I30) -> 0 | O30: =SUM(L30-M30-N30+O29+P30) -> 268.9 | AC30: TVA | AD30: =SUM(AD3:AD29) -> 0
A31: 44893 | F31: =SUM(B31:E31) -> 0 | G31: =F31 -> 0 | K31: =SUM(F31-H31-J31-I31) -> 0 | L31: =SUM(F31-H31-J31-I31) -> 0 | O31: =SUM(L31-M31-N31+O30) -> 268.9 | P31: SOLDE CAISSE
A32: 44894 | F32: =SUM(B32:E32) -> 0 | G32: =F32 -> 0 | K32: =SUM(F32-H32-J32-I32) -> 0 | L32: =SUM(F32-H32-J32-I32) -> 0 | O32: =SUM(L32-M32-N32+O31) -> 268.9 | P32: DU MOIS | AA32: MARGE | AL32: calcul de marge
A33: 44895 | F33: =SUM(B33:E33) -> 0 | G33: =F33 -> 0 | K33: =SUM(F33-H33-J33-I33) -> 0 | L33: =SUM(F33-H33-J33-I33) -> 0 | O33: =SUM(L33-M33-N33+O32) -> 268.9 | P33: =SUM(O33) -> 268.9 | X33: 1 | AE33: =SUM(AC33:AD33) -> 0 | AJ33: 0 | AL33: =AC33 -> 0 | AM33: 1
B34: =SUM(B5:B33) -> 0 | C34: =SUM(C3:C33) -> 0 | D34: =SUM(D3:D33) -> 0 | E34: =SUM(E3:E33) -> 0 | F34: =SUM(F3:F33) -> 0 | H34: =SUM(H3:H33) -> 0 | J34: =SUM(J3:J33) -> 0 | K34: =SUM(K3:K33) -> 0 | L34: =SUM(L3:L33) -> 0 | M34: =SUM(M3:M33) -> 0 | N34: =SUM(N3:N33) -> 0 | X34: 2 | AE34: =SUM(AC34:AD34) -> 0 | AJ34: =AE34 -> 0 | AL34: =AC34 -> 0 | AM34: 2
A35: HTVA | B35: =SUM(B3:B33) -> 0 | C35: =SUM(C34/1.06) -> 0 | D35: =SUM(D34/1.12) -> 0 | E35: =SUM(E34/1.21) -> 0 | F35: =SUM(B35:E35) -> 0 | G35: =SUM(G34:G34) -> 0 | L35: TOTAL SORTIE | N35: =SUM(M34:N34) -> 0 | X35: 3 | AE35: =SUM(AC35:AD35) -> 0 | AJ35: =AE35 -> 0 | AL35: =AC35 -> 0 | AM35: 3
A36: TVA | C36: =SUM(C34-C35) -> 0 | D36: =SUM(D34-D35) -> 0 | E36: =SUM(E34-E35) -> 0 | F36: =SUM(C36:E36) -> 0 | X36: 4 | AE36: =SUM(AC36:AD36) -> 0 | AJ36: 0 | AL36: =AC36 -> 0 | AM36: 4
X37: 5 | AE37: =SUM(AC37:AD37) -> 0 | AJ37: =AE37 -> 0 | AL37: =AC37 -> 0 | AM37: 5
X38: 6 | AE38: =SUM(AC38:AD38) -> 0 | AJ38: 0 | AL38: =AC38 -> 0 | AM38: 6
X39: 7 | AE39: =SUM(AC39:AD39) -> 0 | AJ39: =AE39 -> 0 | AL39: =AC39 -> 0 | AM39: 7
X40: 8 | AE40: =SUM(AC40:AD40) -> 0 | AJ40: =AE40 -> 0 | AL40: =AC40 -> 0 | AM40: 8
X41: 9 | AE41: =SUM(AC41:AD41) -> 0 | AJ41: =AE41 -> 0 | AL41: =AC41 -> 0 | AM41: 9
X42: 10 | AE42: =SUM(AC42:AD42) -> 0 | AJ42: =AE42 -> 0 | AL42: =AC42 -> 0 | AM42: 10
X43: 11 | AE43: =SUM(AC43:AD43) -> 0 | AJ43: =AE43 -> 0 | AL43: =AC43 -> 0 | AM43: 11
X44: 12 | AE44: =SUM(AC44:AD44) -> 0 | AJ44: =AE44 -> 0 | AL44: =AC44 -> 0 | AM44: 12
X45: 13 | AE45: =SUM(AC45:AD45) -> 0 | AJ45: =AE45 -> 0 | AL45: =AC45 -> 0 | AM45: 13
X46: 14 | AE46: =SUM(AC46:AD46) -> 0 | AJ46: =AE46 -> 0 | AL46: =AC46 -> 0 | AM46: 14
X47: 15 | AE47: =SUM(AC47:AD47) -> 0 | AJ47: =AE47 -> 0 | AL47: =AC47 -> 0 | AM47: 15
X48: 16 | AE48: =SUM(AC48:AD48) -> 0 | AJ48: =AE48 -> 0 | AL48: =AC48 -> 0 | AM48: 16
X49: 17 | AE49: =SUM(AC49:AD49) -> 0 | AJ49: =AE49 -> 0 | AL49: =AC49 -> 0 | AM49: 17
X50: 18 | AE50: =SUM(AC50:AD50) -> 0 | AJ50: =AE50 -> 0 | AL50: =AC50 -> 0 | AM50: 18
... X62: 30 | AE62: =SUM(AC62:AD62) -> 0 | AJ62: =AE62 -> 0 | AL62: =AC62 -> 0 | AM62: 30
AC63: =SUM(AC33:AC62) -> 0 | AH63: TOTAL GENE FEUILLE | AJ63: =SUM(AJ3:AJ62) -> 0 | AL63: =AC63 -> 0
AC64: TVA | AD64: =SUM(AD33:AD63) -> 0
AI66: A PÄYER
AC67: TVA | AD67: =AD30 -> 0 | AJ67: =AJ63 -> 0
AC68: TVA | AD68: =AD64 -> 0 | AI68: mois précèdent | AJ68: ='JANV 2026'!AJ69 -> 0
AC69: TVA RECUP | AD69: =SUM(AD67:AD68) -> 0 | AI69: total a payer | AJ69: =SUM(AJ67:AJ68) -> 0

Sheet OCT 2026
A1: 44834 | C1: RECETTE | G1: CAISSE | M1: MOUVEMENT CAISSE | P1: CAISSE MOIS PREC | Q1: PAYEMENT FOURNISSEUR CAISSE | R1: MONTANT | S1: TOTAL | T1: DATE SORTIE | Y1: FOURNISSEUR | Z1: DATE | AA1: REFERENCE | AB1: COMPTE | AC1: HTVA | AD1: TVA | AE1: MONTANT | AF1: PAIEMENT | AG1: CAISSE | AH1: DATE | AI1: ECHEANCE
A2: DATE | B2: FACTURE | C2: 6 | D2: 12 | E2: 21 | F2: TOTAL | G2: CHIFF | H2: carte | I2: cadeau0 | J2: bque | K2: liquide | L2: TOT CAIS | M2: SORTIE | N2: vers ban | O2: solde cai | P2: ='SEPT 2026'!P33 -> 268.9 | AB2: 44834
A3: 44834 | F3: =SUM(B3:E3) -> 0 | G3: =F3 -> 0 | K3: =SUM(F3-H3-J3-I3) -> 0 | L3: =SUM(F3-H3-J3-I3) -> 0 | O3: =SUM(L3-M3-N3+P2) -> 268.9 | X3: 1 | AE3: =SUM(AC3:AD3) -> 0 | AJ3: 0
A4: 44835 | F4: =SUM(B4:E4) -> 0 | G4: =F4 -> 0 | K4: =SUM(F4-H4-J4-I4) -> 0 | L4: =SUM(F4-H4-J4-I4) -> 0 | O4: =SUM(L4-M4-N4+O3+P4) -> 268.9 | X4: 2 | AE4: =SUM(AC4:AD4) -> 0 | AJ4: =AE4 -> 0
A5: 44836 | F5: =SUM(B5:E5) -> 0 | G5: =F5 -> 0 | K5: =SUM(F5-H5-J5-I5) -> 0 | L5: =SUM(F5-H5-J5-I5) -> 0 | O5: =SUM(L5-M5-N5+O4+P5) -> 268.9 | X5: 3 | AE5: =SUM(AC5:AD5) -> 0 | AJ5: 0
A6: 44837 | F6: =SUM(B6:E6) -> 0 | G6: =F6 -> 0 | K6: =SUM(F6-H6-J6-I6) -> 0 | L6: =SUM(F6-H6-J6-I6) -> 0 | O6: =SUM(L6-M6-N6+O5+P6) -> 268.9 | X6: 4 | AE6: =SUM(AC6:AD6) -> 0 | AJ6: 0
A7: 44838 | F7: =SUM(B7:E7) -> 0 | G7: =F7 -> 0 | K7: =SUM(F7-H7-J7-I7) -> 0 | L7: =SUM(F7-H7-J7-I7) -> 0 | O7: =SUM(L7-M7-N7+O6+P7) -> 268.9 | X7: 5 | AE7: =SUM(AC7:AD7) -> 0 | AJ7: 0
A8: 44839 | F8: =SUM(B8:E8) -> 0 | G8: =F8 -> 0 | K8: =SUM(F8-H8-J8-I8) -> 0 | L8: =SUM(F8-H8-J8-I8) -> 0 | O8: =SUM(L8-M8-N8+O7+P8) -> 268.9 | X8: 6 | AE8: =SUM(AC8:AD8) -> 0 | AJ8: 0
A9: 44840 | F9: =SUM(B9:E9) -> 0 | G9: =F9 -> 0 | K9: =SUM(F9-H9-J9-I9) -> 0 | L9: =SUM(F9-H9-J9-I9) -> 0 | O9: =SUM(L9-M9-N9+O8) -> 268.9 | X9: 7 | AE9: =SUM(AC9:AD9) -> 0 | AJ9: =AE9 -> 0
A10: 44841 | F10: =SUM(B10:E10) -> 0 | G10: =F10 -> 0 | K10: =SUM(F10-H10-J10-I10) -> 0 | L10: =SUM(F10-H10-J10-I10) -> 0 | O10: =SUM(L10-M10-N10+O9) -> 268.9 | X10: 8 | AE10: =SUM(AC10:AD10) -> 0 | AJ10: =AE10 -> 0
A11: 44842 | F11: =SUM(B11:E11) -> 0 | G11: =F11 -> 0 | K11: =SUM(F11-H11-J11-I11) -> 0 | L11: =SUM(F11-H11-J11-I11) -> 0 | O11: =SUM(L11-M11-N11+O10) -> 268.9 | X11: 9 | AE11: =SUM(AC11:AD11) -> 0 | AJ11: =AE11 -> 0
A12: 44843 | F12: =SUM(B12:E12) -> 0 | G12: =F12 -> 0 | K12: =SUM(F12-H12-J12-I12) -> 0 | L12: =SUM(F12-H12-J12-I12) -> 0 | O12: =SUM(L12-M12-N12+O11) -> 268.9 | X12: 10 | AE12: =SUM(AC12:AD12) -> 0 | AJ12: =AE12 -> 0
A13: 44844 | F13: =SUM(B13:E13) -> 0 | G13: =F13 -> 0 | K13: =SUM(F13-H13-J13-I13) -> 0 | L13: =SUM(F13-H13-J13-I13) -> 0 | O13: =SUM(L13-M13-N13+O12) -> 268.9 | X13: 11 | AE13: =SUM(AC13:AD13) -> 0 | AJ13: =AE13 -> 0
A14: 44845 | F14: =SUM(B14:E14) -> 0 | G14: =F14 -> 0 | K14: =SUM(F14-H14-J14-I14) -> 0 | L14: =SUM(F14-H14-J14-I14) -> 0 | O14: =SUM(L14-M14-N14+O13) -> 268.9 | X14: 12 | AE14: =SUM(AC14:AD14) -> 0 | AJ14: =AE14 -> 0
A15: 44846 | F15: =SUM(B15:E15) -> 0 | G15: =F15 -> 0 | K15: =SUM(F15-H15-J15-I15) -> 0 | L15: =SUM(F15-H15-J15-I15) -> 0 | O15: =SUM(L15-M15-N15+O14) -> 268.9 | X15: 13 | AE15: =SUM(AC15:AD15) -> 0 | AJ15: =AE15 -> 0
A16: 44847 | F16: =SUM(B16:E16) -> 0 | G16: =F16 -> 0 | K16: =SUM(F16-H16-J16-I16) -> 0 | L16: =SUM(F16-H16-J16-I16) -> 0 | O16: =SUM(L16-M16-N16+O15) -> 268.9 | X16: 14 | AE16: =SUM(AC16:AD16) -> 0 | AJ16: =AE16 -> 0
A17: 44848 | F17: =SUM(B17:E17) -> 0 | G17: =F17 -> 0 | K17: =SUM(F17-H17-J17-I17) -> 0 | L17: =SUM(F17-H17-J17-I17) -> 0 | O17: =SUM(L17-M17-N17+O16+P17) -> 268.9 | X17: 15 | AE17: =SUM(AC17:AD17) -> 0 | AJ17: =AE17 -> 0
A18: 44849 | F18: =SUM(B18:E18) -> 0 | G18: =F18 -> 0 | K18: =SUM(F18-H18-J18-I18) -> 0 | L18: =SUM(F18-H18-J18-I18) -> 0 | O18: =SUM(L18-M18-N18+O17+P18) -> 268.9 | X18: 16 | AE18: =SUM(AC18:AD18) -> 0 | AJ18: =AE18 -> 0
A19: 44850 | F19: =SUM(B19:E19) -> 0 | G19: =F19 -> 0 | K19: =SUM(F19-H19-J19-I19) -> 0 | L19: =SUM(F19-H19-J19-I19) -> 0 | O19: =SUM(L19-M19-N19+O18+P19) -> 268.9 | X19: 17 | AE19: =SUM(AC19:AD19) -> 0 | AJ19: =AE19 -> 0
A20: 44851 | F20: =SUM(B20:E20) -> 0 | G20: =F20 -> 0 | K20: =SUM(F20-H20-J20-I20) -> 0 | L20: =SUM(F20-H20-J20-I20) -> 0 | O20: =SUM(L20-M20-N20+O19+P20) -> 268.9 | X20: 18 | AE20: =SUM(AC20:AD20) -> 0 | AJ20: =AE20 -> 0
A21: 44852 | F21: =SUM(B21:E21) -> 0 | G21: =F21 -> 0 | K21: =SUM(F21-H21-J21-I21) -> 0 | L21: =SUM(F21-H21-J21-I21) -> 0 | O21: =SUM(L21-M21-N21+O20) -> 268.9 | X21: 19 | AE21: =SUM(AC21:AD21) -> 0 | AJ21: =AE21 -> 0
A22: 44853 | F22: =SUM(B22:E22) -> 0 | G22: =F22 -> 0 | K22: =SUM(F22-H22-J22-I22) -> 0 | L22: =SUM(F22-H22-J22-I22) -> 0 | O22: =SUM(L22-M22-N22+O21) -> 268.9 | X22: 20 | AE22: =SUM(AC22:AD22) -> 0 | AJ22: =AE22 -> 0
A23: 44854 | F23: =SUM(B23:E23) -> 0 | G23: =F23 -> 0 | K23: =SUM(F23-H23-J23-I23) -> 0 | L23: =SUM(F23-H23-J23-I23) -> 0 | O23: =SUM(L23-M23-N23+O22) -> 268.9 | X23: 21 | AE23: =SUM(AC23:AD23) -> 0 | AJ23: =AE23 -> 0
A24: 44855 | F24: =SUM(B24:E24) -> 0 | G24: =F24 -> 0 | K24: =SUM(F24-H24-J24-I24) -> 0 | L24: =SUM(F24-H24-J24-I24) -> 0 | O24: =SUM(L24-M24-N24+O23+P24) -> 268.9 | X24: 22 | AE24: =SUM(AC24:AD24) -> 0 | AJ24: =AE24 -> 0
A25: 44856 | F25: =SUM(B25:E25) -> 0 | G25: =F25 -> 0 | K25: =SUM(F25-H25-J25-I25) -> 0 | L25: =SUM(F25-H25-J25-I25) -> 0 | O25: =SUM(L25-M25-N25+O24) -> 268.9 | X25: 26 | AE25: =SUM(AC25:AD25) -> 0 | AJ25: =AE25 -> 0
A26: 44857 | F26: =SUM(B26:E26) -> 0 | G26: =F26 -> 0 | K26: =SUM(F26-H26-J26-I26) -> 0 | L26: =SUM(F26-H26-J26-I26) -> 0 | O26: =SUM(L26-M26-N26+O25) -> 268.9 | X26: 27 | AE26: =SUM(AC26:AD26) -> 0 | AJ26: =AE26 -> 0
A27: 44858 | F27: =SUM(B27:E27) -> 0 | G27: =F27 -> 0 | K27: =SUM(F27-H27-J27-I27) -> 0 | L27: =SUM(F27-H27-J27-I27) -> 0 | O27: =SUM(L27-M27-N27+O26) -> 268.9 | X27: 28 | AE27: =SUM(AC27:AD27) -> 0 | AJ27: =AE27 -> 0
A28: 44859 | F28: =SUM(B28:E28) -> 0 | G28: =F28 -> 0 | K28: =SUM(F28-H28-J28-I28) -> 0 | L28: =SUM(F28-H28-J28-I28) -> 0 | O28: =SUM(L28-M28-N28+O27+P28) -> 268.9 | X28: 29 | AE28: =SUM(AC28:AD28) -> 0 | AJ28: =AE28 -> 0
A29: 44860 | F29: =SUM(B29:E29) -> 0 | G29: =F29 -> 0 | K29: =SUM(F29-H29-J29-I29) -> 0 | L29: =SUM(F29-H29-J29-I29) -> 0 | O29: =SUM(L29-M29-N29+O28) -> 268.9 | X29: 30 | AE29: =SUM(AC29:AD29) -> 0 | AJ29: =AE29 -> 0
A30: 44861 | F30: =SUM(B30:E30) -> 0 | G30: =F30 -> 0 | K30: =SUM(F30-H30-J30-I30) -> 0 | L30: =SUM(F30-H30-J30-I30) -> 0 | O30: =SUM(L30-M30-N30+O29+P30) -> 268.9 | AC30: TVA | AD30: =SUM(AD3:AD29) -> 0
A31: 44862 | F31: =SUM(B31:E31) -> 0 | G31: =F31 -> 0 | K31: =SUM(F31-H31-J31-I31) -> 0 | L31: =SUM(F31-H31-J31-I31) -> 0 | O31: =SUM(L31-M31-N31+O30) -> 268.9 | P31: SOLDE CAISSE
A32: 44863 | F32: =SUM(B32:E32) -> 0 | G32: =F32 -> 0 | K32: =SUM(F32-H32-J32-I32) -> 0 | L32: =SUM(F32-H32-J32-I32) -> 0 | O32: =SUM(L32-M32-N32+O31) -> 268.9 | P32: DU MOIS | AA32: MARGE | AL32: calcul de marge
A33: 44864 | F33: =SUM(B33:E33) -> 0 | G33: =F33 -> 0 | K33: =SUM(F33-H33-J33-I33) -> 0 | L33: =SUM(F33-H33-J33-I33) -> 0 | O33: =SUM(L33-M33-N33+O32) -> 268.9 | P33: =SUM(O33) -> 268.9 | X33: 1 | AE33: =SUM(AC33:AD33) -> 0 | AJ33: 0 | AL33: =AC33 -> 0 | AM33: 1
B34: =SUM(B5:B33) -> 0 | C34: =SUM(C3:C33) -> 0 | D34: =SUM(D3:D33) -> 0 | E34: =SUM(E3:E33) -> 0 | F34: =SUM(F3:F33) -> 0 | H34: =SUM(H3:H33) -> 0 | J34: =SUM(J3:J33) -> 0 | K34: =SUM(K3:K33) -> 0 | L34: =SUM(L3:L33) -> 0 | M34: =SUM(M3:M33) -> 0 | N34: =SUM(N3:N33) -> 0 | X34: 2 | AE34: =SUM(AC34:AD34) -> 0 | AJ34: =AE34 -> 0 | AL34: =AC34 -> 0 | AM34: 2
A35: HTVA | B35: =SUM(B3:B33) -> 0 | C35: =SUM(C34/1.06) -> 0 | D35: =SUM(D34/1.12) -> 0 | E35: =SUM(E34/1.21) -> 0 | F35: =SUM(B35:E35) -> 0 | G35: =SUM(G34:G34) -> 0 | L35: TOTAL SORTIE | N35: =SUM(M34:N34) -> 0 | X35: 3 | AE35: =SUM(AC35:AD35) -> 0 | AJ35: =AE35 -> 0 | AL35: =AC35 -> 0 | AM35: 3
A36: TVA | C36: =SUM(C34-C35) -> 0 | D36: =SUM(D34-D35) -> 0 | E36: =SUM(E34-E35) -> 0 | F36: =SUM(C36:E36) -> 0 | X36: 4 | AE36: =SUM(AC36:AD36) -> 0 | AJ36: 0 | AL36: =AC36 -> 0 | AM36: 4
X37: 5 | AE37: =SUM(AC37:AD37) -> 0 | AJ37: =AE37 -> 0 | AL37: =AC37 -> 0 | AM37: 5
X38: 6 | AE38: =SUM(AC38:AD38) -> 0 | AJ38: 0 | AL38: =AC38 -> 0 | AM38: 6
X39: 7 | AE39: =SUM(AC39:AD39) -> 0 | AJ39: =AE39 -> 0 | AL39: =AC39 -> 0 | AM39: 7
X40: 8 | AE40: =SUM(AC40:AD40) -> 0 | AJ40: =AE40 -> 0 | AL40: =AC40 -> 0 | AM40: 8
X41: 9 | AE41: =SUM(AC41:AD41) -> 0 | AJ41: =AE41 -> 0 | AL41: =AC41 -> 0 | AM41: 9
X42: 10 | AE42: =SUM(AC42:AD42) -> 0 | AJ42: =AE42 -> 0 | AL42: =AC42 -> 0 | AM42: 10
X43: 11 | AE43: =SUM(AC43:AD43) -> 0 | AJ43: =AE43 -> 0 | AL43: =AC43 -> 0 | AM43: 11
X44: 12 | AE44: =SUM(AC44:AD44) -> 0 | AJ44: =AE44 -> 0 | AL44: =AC44 -> 0 | AM44: 12
X45: 13 | AE45: =SUM(AC45:AD45) -> 0 | AJ45: =AE45 -> 0 | AL45: =AC45 -> 0 | AM45: 13
X46: 14 | AE46: =SUM(AC46:AD46) -> 0 | AJ46: =AE46 -> 0 | AL46: =AC46 -> 0 | AM46: 14
X47: 15 | AE47: =SUM(AC47:AD47) -> 0 | AJ47: =AE47 -> 0 | AL47: =AC47 -> 0 | AM47: 15
X48: 16 | AE48: =SUM(AC48:AD48) -> 0 | AJ48: =AE48 -> 0 | AL48: =AC48 -> 0 | AM48: 16
X49: 17 | AE49: =SUM(AC49:AD49) -> 0 | AJ49: =AE49 -> 0 | AL49: =AC49 -> 0 | AM49: 17
X50: 18 | AE50: =SUM(AC50:AD50) -> 0 | AJ50: =AE50 -> 0 | AL50: =AC50 -> 0 | AM50: 18
... X62: 30 | AE62: =SUM(AC62:AD62) -> 0 | AJ62: =AE62 -> 0 | AL62: =AC62 -> 0 | AM62: 30
AC63: =SUM(AC33:AC62) -> 0 | AH63: TOTAL GENE FEUILLE | AJ63: =SUM(AJ3:AJ62) -> 0 | AL63: =AC63 -> 0
AC64: TVA | AD64: =SUM(AD33:AD63) -> 0
AI66: A PÄYER
AC67: TVA | AD67: =AD30 -> 0 | AJ67: =AJ63 -> 0
AC68: TVA | AD68: =AD64 -> 0 | AI68: mois précèdent | AJ68: ='JANV 2026'!AJ69 -> 0
AC69: TVA RECUP | AD69: =SUM(AD67:AD68) -> 0 | AI69: total a payer | AJ69: =SUM(AJ67:AJ68) -> 0

Sheet SEPT 2026
A1: 44804 | C1: RECETTE | G1: CAISSE | M1: MOUVEMENT CAISSE | P1: CAISSE MOIS PREC | Q1: PAYEMENT FOURNISSEUR CAISSE | R1: MONTANT | S1: TOTAL | T1: DATE SORTIE | Y1: FOURNISSEUR | Z1: DATE | AA1: REFERENCE | AB1: COMPTE | AC1: HTVA | AD1: TVA | AE1: MONTANT | AF1: PAIEMENT | AG1: CAISSE | AH1: DATE | AI1: ECHEANCE
A2: DATE | B2: FACTURE | C2: 6 | D2: 12 | E2: 21 | F2: TOTAL | G2: CHIFF | H2: carte | I2: cadeau0 | J2: bque | K2: liquide | L2: TOT CAIS | M2: SORTIE | N2: vers ban | O2: solde cai | P2: ='AOUT 2026'!P33 -> 268.9 | AB2: 44804
A3: 44804 | F3: =SUM(B3:E3) -> 0 | G3: =F3 -> 0 | K3: =SUM(F3-H3-J3-I3) -> 0 | L3: =SUM(F3-H3-J3-I3) -> 0 | O3: =SUM(L3-M3-N3+P2) -> 268.9 | X3: 1 | AE3: =SUM(AC3:AD3) -> 0 | AJ3: 0
A4: 44805 | F4: =SUM(B4:E4) -> 0 | G4: =F4 -> 0 | K4: =SUM(F4-H4-J4-I4) -> 0 | L4: =SUM(F4-H4-J4-I4) -> 0 | O4: =SUM(L4-M4-N4+O3+P4) -> 268.9 | X4: 2 | AE4: =SUM(AC4:AD4) -> 0 | AJ4: =AE4 -> 0
A5: 44806 | F5: =SUM(B5:E5) -> 0 | G5: =F5 -> 0 | K5: =SUM(F5-H5-J5-I5) -> 0 | L5: =SUM(F5-H5-J5-I5) -> 0 | O5: =SUM(L5-M5-N5+O4+P5) -> 268.9 | X5: 3 | AE5: =SUM(AC5:AD5) -> 0 | AJ5: 0
A6: 44807 | F6: =SUM(B6:E6) -> 0 | G6: =F6 -> 0 | K6: =SUM(F6-H6-J6-I6) -> 0 | L6: =SUM(F6-H6-J6-I6) -> 0 | O6: =SUM(L6-M6-N6+O5+P6) -> 268.9 | X6: 4 | AE6: =SUM(AC6:AD6) -> 0 | AJ6: 0
A7: 44808 | F7: =SUM(B7:E7) -> 0 | G7: =F7 -> 0 | K7: =SUM(F7-H7-J7-I7) -> 0 | L7: =SUM(F7-H7-J7-I7) -> 0 | O7: =SUM(L7-M7-N7+O6+P7) -> 268.9 | X7: 5 | AE7: =SUM(AC7:AD7) -> 0 | AJ7: 0
A8: 44809 | F8: =SUM(B8:E8) -> 0 | G8: =F8 -> 0 | K8: =SUM(F8-H8-J8-I8) -> 0 | L8: =SUM(F8-H8-J8-I8) -> 0 | O8: =SUM(L8-M8-N8+O7+P8) -> 268.9 | X8: 6 | AE8: =SUM(AC8:AD8) -> 0 | AJ8: 0
A9: 44810 | F9: =SUM(B9:E9) -> 0 | G9: =F9 -> 0 | K9: =SUM(F9-H9-J9-I9) -> 0 | L9: =SUM(F9-H9-J9-I9) -> 0 | O9: =SUM(L9-M9-N9+O8) -> 268.9 | X9: 7 | AE9: =SUM(AC9:AD9) -> 0 | AJ9: =AE9 -> 0
A10: 44811 | F10: =SUM(B10:E10) -> 0 | G10: =F10 -> 0 | K10: =SUM(F10-H10-J10-I10) -> 0 | L10: =SUM(F10-H10-J10-I10) -> 0 | O10: =SUM(L10-M10-N10+O9) -> 268.9 | X10: 8 | AE10: =SUM(AC10:AD10) -> 0 | AJ10: =AE10 -> 0
A11: 44812 | F11: =SUM(B11:E11) -> 0 | G11: =F11 -> 0 | K11: =SUM(F11-H11-J11-I11) -> 0 | L11: =SUM(F11-H11-J11-I11) -> 0 | O11: =SUM(L11-M11-N11+O10) -> 268.9 | X11: 9 | AE11: =SUM(AC11:AD11) -> 0 | AJ11: =AE11 -> 0
A12: 44813 | F12: =SUM(B12:E12) -> 0 | G12: =F12 -> 0 | K12: =SUM(F12-H12-J12-I12) -> 0 | L12: =SUM(F12-H12-J12-I12) -> 0 | O12: =SUM(L12-M12-N12+O11) -> 268.9 | X12: 10 | AE12: =SUM(AC12:AD12) -> 0 | AJ12: =AE12 -> 0
A13: 44814 | F13: =SUM(B13:E13) -> 0 | G13: =F13 -> 0 | K13: =SUM(F13-H13-J13-I13) -> 0 | L13: =SUM(F13-H13-J13-I13) -> 0 | O13: =SUM(L13-M13-N13+O12) -> 268.9 | X13: 11 | AE13: =SUM(AC13:AD13) -> 0 | AJ13: =AE13 -> 0
A14: 44815 | F14: =SUM(B14:E14) -> 0 | G14: =F14 -> 0 | K14: =SUM(F14-H14-J14-I14) -> 0 | L14: =SUM(F14-H14-J14-I14) -> 0 | O14: =SUM(L14-M14-N14+O13) -> 268.9 | X14: 12 | AE14: =SUM(AC14:AD14) -> 0 | AJ14: =AE14 -> 0
A15: 44816 | F15: =SUM(B15:E15) -> 0 | G15: =F15 -> 0 | K15: =SUM(F15-H15-J15-I15) -> 0 | L15: =SUM(F15-H15-J15-I15) -> 0 | O15: =SUM(L15-M15-N15+O14) -> 268.9 | X15: 13 | AE15: =SUM(AC15:AD15) -> 0 | AJ15: =AE15 -> 0
A16: 44817 | F16: =SUM(B16:E16) -> 0 | G16: =F16 -> 0 | K16: =SUM(F16-H16-J16-I16) -> 0 | L16: =SUM(F16-H16-J16-I16) -> 0 | O16: =SUM(L16-M16-N16+O15) -> 268.9 | X16: 14 | AE16: =SUM(AC16:AD16) -> 0 | AJ16: =AE16 -> 0
A17: 44818 | F17: =SUM(B17:E17) -> 0 | G17: =F17 -> 0 | K17: =SUM(F17-H17-J17-I17) -> 0 | L17: =SUM(F17-H17-J17-I17) -> 0 | O17: =SUM(L17-M17-N17+O16+P17) -> 268.9 | X17: 15 | AE17: =SUM(AC17:AD17) -> 0 | AJ17: =AE17 -> 0
A18: 44819 | F18: =SUM(B18:E18) -> 0 | G18: =F18 -> 0 | K18: =SUM(F18-H18-J18-I18) -> 0 | L18: =SUM(F18-H18-J18-I18) -> 0 | O18: =SUM(L18-M18-N18+O17+P18) -> 268.9 | X18: 16 | AE18: =SUM(AC18:AD18) -> 0 | AJ18: =AE18 -> 0
A19: 44820 | F19: =SUM(B19:E19) -> 0 | G19: =F19 -> 0 | K19: =SUM(F19-H19-J19-I19) -> 0 | L19: =SUM(F19-H19-J19-I19) -> 0 | O19: =SUM(L19-M19-N19+O18+P19) -> 268.9 | X19: 17 | AE19: =SUM(AC19:AD19) -> 0 | AJ19: =AE19 -> 0
A20: 44821 | F20: =SUM(B20:E20) -> 0 | G20: =F20 -> 0 | K20: =SUM(F20-H20-J20-I20) -> 0 | L20: =SUM(F20-H20-J20-I20) -> 0 | O20: =SUM(L20-M20-N20+O19+P20) -> 268.9 | X20: 18 | AE20: =SUM(AC20:AD20) -> 0 | AJ20: =AE20 -> 0
A21: 44822 | F21: =SUM(B21:E21) -> 0 | G21: =F21 -> 0 | K21: =SUM(F21-H21-J21-I21) -> 0 | L21: =SUM(F21-H21-J21-I21) -> 0 | O21: =SUM(L21-M21-N21+O20) -> 268.9 | X21: 19 | AE21: =SUM(AC21:AD21) -> 0 | AJ21: =AE21 -> 0
A22: 44823 | F22: =SUM(B22:E22) -> 0 | G22: =F22 -> 0 | K22: =SUM(F22-H22-J22-I22) -> 0 | L22: =SUM(F22-H22-J22-I22) -> 0 | O22: =SUM(L22-M22-N22+O21) -> 268.9 | X22: 20 | AE22: =SUM(AC22:AD22) -> 0 | AJ22: =AE22 -> 0
A23: 44824 | F23: =SUM(B23:E23) -> 0 | G23: =F23 -> 0 | K23: =SUM(F23-H23-J23-I23) -> 0 | L23: =SUM(F23-H23-J23-I23) -> 0 | O23: =SUM(L23-M23-N23+O22) -> 268.9 | X23: 21 | AE23: =SUM(AC23:AD23) -> 0 | AJ23: =AE23 -> 0
A24: 44825 | F24: =SUM(B24:E24) -> 0 | G24: =F24 -> 0 | K24: =SUM(F24-H24-J24-I24) -> 0 | L24: =SUM(F24-H24-J24-I24) -> 0 | O24: =SUM(L24-M24-N24+O23+P24) -> 268.9 | X24: 22 | AE24: =SUM(AC24:AD24) -> 0 | AJ24: =AE24 -> 0
A25: 44826 | F25: =SUM(B25:E25) -> 0 | G25: =F25 -> 0 | K25: =SUM(F25-H25-J25-I25) -> 0 | L25: =SUM(F25-H25-J25-I25) -> 0 | O25: =SUM(L25-M25-N25+O24) -> 268.9 | X25: 26 | AE25: =SUM(AC25:AD25) -> 0 | AJ25: =AE25 -> 0
A26: 44827 | F26: =SUM(B26:E26) -> 0 | G26: =F26 -> 0 | K26: =SUM(F26-H26-J26-I26) -> 0 | L26: =SUM(F26-H26-J26-I26) -> 0 | O26: =SUM(L26-M26-N26+O25) -> 268.9 | X26: 27 | AE26: =SUM(AC26:AD26) -> 0 | AJ26: =AE26 -> 0
A27: 44828 | F27: =SUM(B27:E27) -> 0 | G27: =F27 -> 0 | K27: =SUM(F27-H27-J27-I27) -> 0 | L27: =SUM(F27-H27-J27-I27) -> 0 | O27: =SUM(L27-M27-N27+O26) -> 268.9 | X27: 28 | AE27: =SUM(AC27:AD27) -> 0 | AJ27: =AE27 -> 0
A28: 44829 | F28: =SUM(B28:E28) -> 0 | G28: =F28 -> 0 | K28: =SUM(F28-H28-J28-I28) -> 0 | L28: =SUM(F28-H28-J28-I28) -> 0 | O28: =SUM(L28-M28-N28+O27+P28) -> 268.9 | X28: 29 | AE28: =SUM(AC28:AD28) -> 0 | AJ28: =AE28 -> 0
A29: 44830 | F29: =SUM(B29:E29) -> 0 | G29: =F29 -> 0 | K29: =SUM(F29-H29-J29-I29) -> 0 | L29: =SUM(F29-H29-J29-I29) -> 0 | O29: =SUM(L29-M29-N29+O28) -> 268.9 | X29: 30 | AE29: =SUM(AC29:AD29) -> 0 | AJ29: =AE29 -> 0
A30: 44831 | F30: =SUM(B30:E30) -> 0 | G30: =F30 -> 0 | K30: =SUM(F30-H30-J30-I30) -> 0 | L30: =SUM(F30-H30-J30-I30) -> 0 | O30: =SUM(L30-M30-N30+O29+P30) -> 268.9 | AC30: TVA | AD30: =SUM(AD3:AD29) -> 0
A31: 44832 | F31: =SUM(B31:E31) -> 0 | G31: =F31 -> 0 | K31: =SUM(F31-H31-J31-I31) -> 0 | L31: =SUM(F31-H31-J31-I31) -> 0 | O31: =SUM(L31-M31-N31+O30) -> 268.9 | P31: SOLDE CAISSE
A32: 44833 | F32: =SUM(B32:E32) -> 0 | G32: =F32 -> 0 | K32: =SUM(F32-H32-J32-I32) -> 0 | L32: =SUM(F32-H32-J32-I32) -> 0 | O32: =SUM(L32-M32-N32+O31) -> 268.9 | P32: DU MOIS | AA32: MARGE | AL32: calcul de marge
F33: =SUM(B33:E33) -> 0 | G33: =F33 -> 0 | K33: =SUM(F33-H33-J33-I33) -> 0 | L33: =SUM(F33-H33-J33-I33) -> 0 | O33: =SUM(L33-M33-N33+O32) -> 268.9 | P33: =SUM(O33) -> 268.9 | X33: 1 | AE33: =SUM(AC33:AD33) -> 0 | AJ33: 0 | AL33: =AC33 -> 0 | AM33: 1
B34: =SUM(B5:B33) -> 0 | C34: =SUM(C3:C33) -> 0 | D34: =SUM(D3:D33) -> 0 | E34: =SUM(E3:E33) -> 0 | F34: =SUM(F3:F33) -> 0 | H34: =SUM(H3:H33) -> 0 | J34: =SUM(J3:J33) -> 0 | K34: =SUM(K3:K33) -> 0 | L34: =SUM(L3:L33) -> 0 | M34: =SUM(M3:M33) -> 0 | N34: =SUM(N3:N33) -> 0 | X34: 2 | AE34: =SUM(AC34:AD34) -> 0 | AJ34: =AE34 -> 0 | AL34: =AC34 -> 0 | AM34: 2
A35: HTVA | B35: =SUM(B3:B33) -> 0 | C35: =SUM(C34/1.06) -> 0 | D35: =SUM(D34/1.12) -> 0 | E35: =SUM(E34/1.21) -> 0 | F35: =SUM(B35:E35) -> 0 | G35: =SUM(G34:G34) -> 0 | L35: TOTAL SORTIE | N35: =SUM(M34:N34) -> 0 | X35: 3 | AE35: =SUM(AC35:AD35) -> 0 | AJ35: =AE35 -> 0 | AL35: =AC35 -> 0 | AM35: 3
A36: TVA | C36: =SUM(C34-C35) -> 0 | D36: =SUM(D34-D35) -> 0 | E36: =SUM(E34-E35) -> 0 | F36: =SUM(C36:E36) -> 0 | X36: 4 | AE36: =SUM(AC36:AD36) -> 0 | AJ36: 0 | AL36: =AC36 -> 0 | AM36: 4
X37: 5 | AE37: =SUM(AC37:AD37) -> 0 | AJ37: =AE37 -> 0 | AL37: =AC37 -> 0 | AM37: 5
X38: 6 | AE38: =SUM(AC38:AD38) -> 0 | AJ38: 0 | AL38: =AC38 -> 0 | AM38: 6
X39: 7 | AE39: =SUM(AC39:AD39) -> 0 | AJ39: =AE39 -> 0 | AL39: =AC39 -> 0 | AM39: 7
X40: 8 | AE40: =SUM(AC40:AD40) -> 0 | AJ40: =AE40 -> 0 | AL40: =AC40 -> 0 | AM40: 8
X41: 9 | AE41: =SUM(AC41:AD41) -> 0 | AJ41: =AE41 -> 0 | AL41: =AC41 -> 0 | AM41: 9
X42: 10 | AE42: =SUM(AC42:AD42) -> 0 | AJ42: =AE42 -> 0 | AL42: =AC42 -> 0 | AM42: 10
X43: 11 | AE43: =SUM(AC43:AD43) -> 0 | AJ43: =AE43 -> 0 | AL43: =AC43 -> 0 | AM43: 11
X44: 12 | AE44: =SUM(AC44:AD44) -> 0 | AJ44: =AE44 -> 0 | AL44: =AC44 -> 0 | AM44: 12
X45: 13 | AE45: =SUM(AC45:AD45) -> 0 | AJ45: =AE45 -> 0 | AL45: =AC45 -> 0 | AM45: 13
X46: 14 | AE46: =SUM(AC46:AD46) -> 0 | AJ46: =AE46 -> 0 | AL46: =AC46 -> 0 | AM46: 14
X47: 15 | AE47: =SUM(AC47:AD47) -> 0 | AJ47: =AE47 -> 0 | AL47: =AC47 -> 0 | AM47: 15
X48: 16 | AE48: =SUM(AC48:AD48) -> 0 | AJ48: =AE48 -> 0 | AL48: =AC48 -> 0 | AM48: 16
X49: 17 | AE49: =SUM(AC49:AD49) -> 0 | AJ49: =AE49 -> 0 | AL49: =AC49 -> 0 | AM49: 17
X50: 18 | AE50: =SUM(AC50:AD50) -> 0 | AJ50: =AE50 -> 0 | AL50: =AC50 -> 0 | AM50: 18
... X62: 30 | AE62: =SUM(AC62:AD62) -> 0 | AJ62: =AE62 -> 0 | AL62: =AC62 -> 0 | AM62: 30
AC63: =SUM(AC33:AC62) -> 0 | AH63: TOTAL GENE FEUILLE | AJ63: =SUM(AJ3:AJ62) -> 0 | AL63: =AC63 -> 0
AC64: TVA | AD64: =SUM(AD33:AD63) -> 0
AI66: A PÄYER
AC67: TVA | AD67: =AD30 -> 0 | AJ67: =AJ63 -> 0
AC68: TVA | AD68: =AD64 -> 0 | AI68: mois précèdent | AJ68: ='JANV 2026'!AJ69 -> 0
AC69: TVA RECUP | AD69: =SUM(AD67:AD68) -> 0 | AI69: total a payer | AJ69: =SUM(AJ67:AJ68) -> 0

Sheet AOUT 2026
A1: 44773 | C1: RECETTE | G1: CAISSE | M1: MOUVEMENT CAISSE | P1: CAISSE MOIS PREC | Q1: PAYEMENT FOURNISSEUR CAISSE | R1: MONTANT | S1: TOTAL | T1: DATE SORTIE | Y1: FOURNISSEUR | Z1: DATE | AA1: REFERENCE | AB1: COMPTE | AC1: HTVA | AD1: TVA | AE1: MONTANT | AF1: PAIEMENT | AG1: CAISSE | AH1: DATE | AI1: ECHEANCE
A2: DATE | B2: FACTURE | C2: 6 | D2: 12 | E2: 21 | F2: TOTAL | G2: CHIFF | H2: carte | I2: cadeau0 | J2: bque | K2: liquide | L2: TOT CAIS | M2: SORTIE | N2: vers ban | O2: solde cai | P2: ='JUILLET 2026'!P33 -> 268.9 | AB2: 44773
A3: 44773 | F3: =SUM(B3:E3) -> 0 | G3: =F3 -> 0 | K3: =SUM(F3-H3-J3-I3) -> 0 | L3: =SUM(F3-H3-J3-I3) -> 0 | O3: =SUM(L3-M3-N3+P2) -> 268.9 | X3: 1 | AE3: =SUM(AC3:AD3) -> 0 | AJ3: 0
A4: 44774 | F4: =SUM(B4:E4) -> 0 | G4: =F4 -> 0 | K4: =SUM(F4-H4-J4-I4) -> 0 | L4: =SUM(F4-H4-J4-I4) -> 0 | O4: =SUM(L4-M4-N4+O3+P4) -> 268.9 | X4: 2 | AE4: =SUM(AC4:AD4) -> 0 | AJ4: =AE4 -> 0
A5: 44775 | F5: =SUM(B5:E5) -> 0 | G5: =F5 -> 0 | K5: =SUM(F5-H5-J5-I5) -> 0 | L5: =SUM(F5-H5-J5-I5) -> 0 | O5: =SUM(L5-M5-N5+O4+P5) -> 268.9 | X5: 3 | AE5: =SUM(AC5:AD5) -> 0 | AJ5: 0
A6: 44776 | F6: =SUM(B6:E6) -> 0 | G6: =F6 -> 0 | K6: =SUM(F6-H6-J6-I6) -> 0 | L6: =SUM(F6-H6-J6-I6) -> 0 | O6: =SUM(L6-M6-N6+O5+P6) -> 268.9 | X6: 4 | AE6: =SUM(AC6:AD6) -> 0 | AJ6: 0
A7: 44777 | F7: =SUM(B7:E7) -> 0 | G7: =F7 -> 0 | K7: =SUM(F7-H7-J7-I7) -> 0 | L7: =SUM(F7-H7-J7-I7) -> 0 | O7: =SUM(L7-M7-N7+O6+P7) -> 268.9 | X7: 5 | AE7: =SUM(AC7:AD7) -> 0 | AJ7: 0
A8: 44778 | F8: =SUM(B8:E8) -> 0 | G8: =F8 -> 0 | K8: =SUM(F8-H8-J8-I8) -> 0 | L8: =SUM(F8-H8-J8-I8) -> 0 | O8: =SUM(L8-M8-N8+O7+P8) -> 268.9 | X8: 6 | AE8: =SUM(AC8:AD8) -> 0 | AJ8: 0
A9: 44779 | F9: =SUM(B9:E9) -> 0 | G9: =F9 -> 0 | K9: =SUM(F9-H9-J9-I9) -> 0 | L9: =SUM(F9-H9-J9-I9) -> 0 | O9: =SUM(L9-M9-N9+O8) -> 268.9 | X9: 7 | AE9: =SUM(AC9:AD9) -> 0 | AJ9: =AE9 -> 0
A10: 44780 | F10: =SUM(B10:E10) -> 0 | G10: =F10 -> 0 | K10: =SUM(F10-H10-J10-I10) -> 0 | L10: =SUM(F10-H10-J10-I10) -> 0 | O10: =SUM(L10-M10-N10+O9) -> 268.9 | X10: 8 | AE10: =SUM(AC10:AD10) -> 0 | AJ10: =AE10 -> 0
A11: 44781 | F11: =SUM(B11:E11) -> 0 | G11: =F11 -> 0 | K11: =SUM(F11-H11-J11-I11) -> 0 | L11: =SUM(F11-H11-J11-I11) -> 0 | O11: =SUM(L11-M11-N11+O10) -> 268.9 | X11: 9 | AE11: =SUM(AC11:AD11) -> 0 | AJ11: =AE11 -> 0
A12: 44782 | F12: =SUM(B12:E12) -> 0 | G12: =F12 -> 0 | K12: =SUM(F12-H12-J12-I12) -> 0 | L12: =SUM(F12-H12-J12-I12) -> 0 | O12: =SUM(L12-M12-N12+O11) -> 268.9 | X12: 10 | AE12: =SUM(AC12:AD12) -> 0 | AJ12: =AE12 -> 0
A13: 44783 | F13: =SUM(B13:E13) -> 0 | G13: =F13 -> 0 | K13: =SUM(F13-H13-J13-I13) -> 0 | L13: =SUM(F13-H13-J13-I13) -> 0 | O13: =SUM(L13-M13-N13+O12) -> 268.9 | X13: 11 | AE13: =SUM(AC13:AD13) -> 0 | AJ13: =AE13 -> 0
A14: 44784 | F14: =SUM(B14:E14) -> 0 | G14: =F14 -> 0 | K14: =SUM(F14-H14-J14-I14) -> 0 | L14: =SUM(F14-H14-J14-I14) -> 0 | O14: =SUM(L14-M14-N14+O13) -> 268.9 | X14: 12 | AE14: =SUM(AC14:AD14) -> 0 | AJ14: =AE14 -> 0
A15: 44785 | F15: =SUM(B15:E15) -> 0 | G15: =F15 -> 0 | K15: =SUM(F15-H15-J15-I15) -> 0 | L15: =SUM(F15-H15-J15-I15) -> 0 | O15: =SUM(L15-M15-N15+O14) -> 268.9 | X15: 13 | AE15: =SUM(AC15:AD15) -> 0 | AJ15: =AE15 -> 0
A16: 44786 | F16: =SUM(B16:E16) -> 0 | G16: =F16 -> 0 | K16: =SUM(F16-H16-J16-I16) -> 0 | L16: =SUM(F16-H16-J16-I16) -> 0 | O16: =SUM(L16-M16-N16+O15) -> 268.9 | X16: 14 | AE16: =SUM(AC16:AD16) -> 0 | AJ16: =AE16 -> 0
A17: 44787 | F17: =SUM(B17:E17) -> 0 | G17: =F17 -> 0 | K17: =SUM(F17-H17-J17-I17) -> 0 | L17: =SUM(F17-H17-J17-I17) -> 0 | O17: =SUM(L17-M17-N17+O16+P17) -> 268.9 | X17: 15 | AE17: =SUM(AC17:AD17) -> 0 | AJ17: =AE17 -> 0
A18: 44788 | F18: =SUM(B18:E18) -> 0 | G18: =F18 -> 0 | K18: =SUM(F18-H18-J18-I18) -> 0 | L18: =SUM(F18-H18-J18-I18) -> 0 | O18: =SUM(L18-M18-N18+O17+P18) -> 268.9 | X18: 16 | AE18: =SUM(AC18:AD18) -> 0 | AJ18: =AE18 -> 0
A19: 44789 | F19: =SUM(B19:E19) -> 0 | G19: =F19 -> 0 | K19: =SUM(F19-H19-J19-I19) -> 0 | L19: =SUM(F19-H19-J19-I19) -> 0 | O19: =SUM(L19-M19-N19+O18+P19) -> 268.9 | X19: 17 | AE19: =SUM(AC19:AD19) -> 0 | AJ19: =AE19 -> 0
A20: 44790 | F20: =SUM(B20:E20) -> 0 | G20: =F20 -> 0 | K20: =SUM(F20-H20-J20-I20) -> 0 | L20: =SUM(F20-H20-J20-I20) -> 0 | O20: =SUM(L20-M20-N20+O19+P20) -> 268.9 | X20: 18 | AE20: =SUM(AC20:AD20) -> 0 | AJ20: =AE20 -> 0
A21: 44791 | F21: =SUM(B21:E21) -> 0 | G21: =F21 -> 0 | K21: =SUM(F21-H21-J21-I21) -> 0 | L21: =SUM(F21-H21-J21-I21) -> 0 | O21: =SUM(L21-M21-N21+O20) -> 268.9 | X21: 19 | AE21: =SUM(AC21:AD21) -> 0 | AJ21: =AE21 -> 0
A22: 44792 | F22: =SUM(B22:E22) -> 0 | G22: =F22 -> 0 | K22: =SUM(F22-H22-J22-I22) -> 0 | L22: =SUM(F22-H22-J22-I22) -> 0 | O22: =SUM(L22-M22-N22+O21) -> 268.9 | X22: 20 | AE22: =SUM(AC22:AD22) -> 0 | AJ22: =AE22 -> 0
A23: 44793 | F23: =SUM(B23:E23) -> 0 | G23: =F23 -> 0 | K23: =SUM(F23-H23-J23-I23) -> 0 | L23: =SUM(F23-H23-J23-I23) -> 0 | O23: =SUM(L23-M23-N23+O22) -> 268.9 | X23: 21 | AE23: =SUM(AC23:AD23) -> 0 | AJ23: =AE23 -> 0
A24: 44794 | F24: =SUM(B24:E24) -> 0 | G24: =F24 -> 0 | K24: =SUM(F24-H24-J24-I24) -> 0 | L24: =SUM(F24-H24-J24-I24) -> 0 | O24: =SUM(L24-M24-N24+O23+P24) -> 268.9 | X24: 22 | AE24: =SUM(AC24:AD24) -> 0 | AJ24: =AE24 -> 0
A25: 44795 | F25: =SUM(B25:E25) -> 0 | G25: =F25 -> 0 | K25: =SUM(F25-H25-J25-I25) -> 0 | L25: =SUM(F25-H25-J25-I25) -> 0 | O25: =SUM(L25-M25-N25+O24) -> 268.9 | X25: 26 | AE25: =SUM(AC25:AD25) -> 0 | AJ25: =AE25 -> 0
A26: 44796 | F26: =SUM(B26:E26) -> 0 | G26: =F26 -> 0 | K26: =SUM(F26-H26-J26-I26) -> 0 | L26: =SUM(F26-H26-J26-I26) -> 0 | O26: =SUM(L26-M26-N26+O25) -> 268.9 | X26: 27 | AE26: =SUM(AC26:AD26) -> 0 | AJ26: =AE26 -> 0
A27: 44797 | F27: =SUM(B27:E27) -> 0 | G27: =F27 -> 0 | K27: =SUM(F27-H27-J27-I27) -> 0 | L27: =SUM(F27-H27-J27-I27) -> 0 | O27: =SUM(L27-M27-N27+O26) -> 268.9 | X27: 28 | AE27: =SUM(AC27:AD27) -> 0 | AJ27: =AE27 -> 0
A28: 44798 | F28: =SUM(B28:E28) -> 0 | G28: =F28 -> 0 | K28: =SUM(F28-H28-J28-I28) -> 0 | L28: =SUM(F28-H28-J28-I28) -> 0 | O28: =SUM(L28-M28-N28+O27+P28) -> 268.9 | X28: 29 | AE28: =SUM(AC28:AD28) -> 0 | AJ28: =AE28 -> 0
A29: 44799 | F29: =SUM(B29:E29) -> 0 | G29: =F29 -> 0 | K29: =SUM(F29-H29-J29-I29) -> 0 | L29: =SUM(F29-H29-J29-I29) -> 0 | O29: =SUM(L29-M29-N29+O28) -> 268.9 | X29: 30 | AE29: =SUM(AC29:AD29) -> 0 | AJ29: =AE29 -> 0
A30: 44800 | F30: =SUM(B30:E30) -> 0 | G30: =F30 -> 0 | K30: =SUM(F30-H30-J30-I30) -> 0 | L30: =SUM(F30-H30-J30-I30) -> 0 | O30: =SUM(L30-M30-N30+O29+P30) -> 268.9 | AC30: TVA | AD30: =SUM(AD3:AD29) -> 0
A31: 44801 | F31: =SUM(B31:E31) -> 0 | G31: =F31 -> 0 | K31: =SUM(F31-H31-J31-I31) -> 0 | L31: =SUM(F31-H31-J31-I31) -> 0 | O31: =SUM(L31-M31-N31+O30) -> 268.9 | P31: SOLDE CAISSE
A32: 44802 | F32: =SUM(B32:E32) -> 0 | G32: =F32 -> 0 | K32: =SUM(F32-H32-J32-I32) -> 0 | L32: =SUM(F32-H32-J32-I32) -> 0 | O32: =SUM(L32-M32-N32+O31) -> 268.9 | P32: DU MOIS | AA32: MARGE | AL32: calcul de marge
A33: 44803 | F33: =SUM(B33:E33) -> 0 | G33: =F33 -> 0 | K33: =SUM(F33-H33-J33-I33) -> 0 | L33: =SUM(F33-H33-J33-I33) -> 0 | O33: =SUM(L33-M33-N33+O32) -> 268.9 | P33: =SUM(O33) -> 268.9 | X33: 1 | AE33: =SUM(AC33:AD33) -> 0 | AJ33: 0 | AL33: =AC33 -> 0 | AM33: 1
B34: =SUM(B5:B33) -> 0 | C34: =SUM(C3:C33) -> 0 | D34: =SUM(D3:D33) -> 0 | E34: =SUM(E3:E33) -> 0 | F34: =SUM(F3:F33) -> 0 | H34: =SUM(H3:H33) -> 0 | J34: =SUM(J3:J33) -> 0 | K34: =SUM(K3:K33) -> 0 | L34: =SUM(L3:L33) -> 0 | M34: =SUM(M3:M33) -> 0 | N34: =SUM(N3:N33) -> 0 | X34: 2 | AE34: =SUM(AC34:AD34) -> 0 | AJ34: =AE34 -> 0 | AL34: =AC34 -> 0 | AM34: 2
A35: HTVA | B35: =SUM(B3:B33) -> 0 | C35: =SUM(C34/1.06) -> 0 | D35: =SUM(D34/1.12) -> 0 | E35: =SUM(E34/1.21) -> 0 | F35: =SUM(B35:E35) -> 0 | G35: =SUM(G34:G34) -> 0 | L35: TOTAL SORTIE | N35: =SUM(M34:N34) -> 0 | X35: 3 | AE35: =SUM(AC35:AD35) -> 0 | AJ35: =AE35 -> 0 | AL35: =AC35 -> 0 | AM35: 3
A36: TVA | C36: =SUM(C34-C35) -> 0 | D36: =SUM(D34-D35) -> 0 | E36: =SUM(E34-E35) -> 0 | F36: =SUM(C36:E36) -> 0 | X36: 4 | AE36: =SUM(AC36:AD36) -> 0 | AJ36: 0 | AL36: =AC36 -> 0 | AM36: 4
X37: 5 | AE37: =SUM(AC37:AD37) -> 0 | AJ37: =AE37 -> 0 | AL37: =AC37 -> 0 | AM37: 5
X38: 6 | AE38: =SUM(AC38:AD38) -> 0 | AJ38: 0 | AL38: =AC38 -> 0 | AM38: 6
X39: 7 | AE39: =SUM(AC39:AD39) -> 0 | AJ39: =AE39 -> 0 | AL39: =AC39 -> 0 | AM39: 7
X40: 8 | AE40: =SUM(AC40:AD40) -> 0 | AJ40: =AE40 -> 0 | AL40: =AC40 -> 0 | AM40: 8
X41: 9 | AE41: =SUM(AC41:AD41) -> 0 | AJ41: =AE41 -> 0 | AL41: =AC41 -> 0 | AM41: 9
X42: 10 | AE42: =SUM(AC42:AD42) -> 0 | AJ42: =AE42 -> 0 | AL42: =AC42 -> 0 | AM42: 10
X43: 11 | AE43: =SUM(AC43:AD43) -> 0 | AJ43: =AE43 -> 0 | AL43: =AC43 -> 0 | AM43: 11
X44: 12 | AE44: =SUM(AC44:AD44) -> 0 | AJ44: =AE44 -> 0 | AL44: =AC44 -> 0 | AM44: 12
X45: 13 | AE45: =SUM(AC45:AD45) -> 0 | AJ45: =AE45 -> 0 | AL45: =AC45 -> 0 | AM45: 13
X46: 14 | AE46: =SUM(AC46:AD46) -> 0 | AJ46: =AE46 -> 0 | AL46: =AC46 -> 0 | AM46: 14
X47: 15 | AE47: =SUM(AC47:AD47) -> 0 | AJ47: =AE47 -> 0 | AL47: =AC47 -> 0 | AM47: 15
X48: 16 | AE48: =SUM(AC48:AD48) -> 0 | AJ48: =AE48 -> 0 | AL48: =AC48 -> 0 | AM48: 16
X49: 17 | AE49: =SUM(AC49:AD49) -> 0 | AJ49: =AE49 -> 0 | AL49: =AC49 -> 0 | AM49: 17
X50: 18 | AE50: =SUM(AC50:AD50) -> 0 | AJ50: =AE50 -> 0 | AL50: =AC50 -> 0 | AM50: 18
... X62: 30 | AE62: =SUM(AC62:AD62) -> 0 | AJ62: =AE62 -> 0 | AL62: =AC62 -> 0 | AM62: 30
AC63: =SUM(AC33:AC62) -> 0 | AH63: TOTAL GENE FEUILLE | AJ63: =SUM(AJ3:AJ62) -> 0 | AL63: =AC63 -> 0
AC64: TVA | AD64: =SUM(AD33:AD63) -> 0
AI66: A PÄYER
AC67: TVA | AD67: =AD30 -> 0 | AJ67: =AJ63 -> 0
AC68: TVA | AD68: =AD64 -> 0 | AI68: mois précèdent | AJ68: ='JANV 2026'!AJ69 -> 0
AC69: TVA RECUP | AD69: =SUM(AD67:AD68) -> 0 | AI69: total a payer | AJ69: =SUM(AJ67:AJ68) -> 0

Sheet JUILLET 2026
A1: 44742 | C1: RECETTE | G1: CAISSE | M1: MOUVEMENT CAISSE | P1: CAISSE MOIS PREC | Q1: PAYEMENT FOURNISSEUR CAISSE | R1: MONTANT | S1: TOTAL | T1: DATE SORTIE | Y1: FOURNISSEUR | Z1: DATE | AA1: REFERENCE | AB1: COMPTE | AC1: HTVA | AD1: TVA | AE1: MONTANT | AF1: PAIEMENT | AG1: CAISSE | AH1: DATE | AI1: ECHEANCE
A2: DATE | B2: FACTURE | C2: 6 | D2: 12 | E2: 21 | F2: TOTAL | G2: CHIFF | H2: carte | I2: cadeau0 | J2: bque | K2: liquide | L2: TOT CAIS | M2: SORTIE | N2: vers ban | O2: solde cai | P2: ='JUIN 2026'!P33 -> 268.9 | AB2: 44742
A3: 44742 | F3: =SUM(B3:E3) -> 0 | G3: =F3 -> 0 | K3: =SUM(F3-H3-J3-I3) -> 0 | L3: =SUM(F3-H3-J3-I3) -> 0 | O3: =SUM(L3-M3-N3+P2) -> 268.9 | X3: 1 | AE3: =SUM(AC3:AD3) -> 0 | AJ3: 0
A4: 44743 | F4: =SUM(B4:E4) -> 0 | G4: =F4 -> 0 | K4: =SUM(F4-H4-J4-I4) -> 0 | L4: =SUM(F4-H4-J4-I4) -> 0 | O4: =SUM(L4-M4-N4+O3+P4) -> 268.9 | X4: 2 | AE4: =SUM(AC4:AD4) -> 0 | AJ4: =AE4 -> 0
A5: 44744 | F5: =SUM(B5:E5) -> 0 | G5: =F5 -> 0 | K5: =SUM(F5-H5-J5-I5) -> 0 | L5: =SUM(F5-H5-J5-I5) -> 0 | O5: =SUM(L5-M5-N5+O4+P5) -> 268.9 | X5: 3 | AE5: =SUM(AC5:AD5) -> 0 | AJ5: 0
A6: 44745 | F6: =SUM(B6:E6) -> 0 | G6: =F6 -> 0 | K6: =SUM(F6-H6-J6-I6) -> 0 | L6: =SUM(F6-H6-J6-I6) -> 0 | O6: =SUM(L6-M6-N6+O5+P6) -> 268.9 | X6: 4 | AE6: =SUM(AC6:AD6) -> 0 | AJ6: 0
A7: 44746 | F7: =SUM(B7:E7) -> 0 | G7: =F7 -> 0 | K7: =SUM(F7-H7-J7-I7) -> 0 | L7: =SUM(F7-H7-J7-I7) -> 0 | O7: =SUM(L7-M7-N7+O6+P7) -> 268.9 | X7: 5 | AE7: =SUM(AC7:AD7) -> 0 | AJ7: 0
A8: 44747 | F8: =SUM(B8:E8) -> 0 | G8: =F8 -> 0 | K8: =SUM(F8-H8-J8-I8) -> 0 | L8: =SUM(F8-H8-J8-I8) -> 0 | O8: =SUM(L8-M8-N8+O7+P8) -> 268.9 | X8: 6 | AE8: =SUM(AC8:AD8) -> 0 | AJ8: 0
A9: 44748 | F9: =SUM(B9:E9) -> 0 | G9: =F9 -> 0 | K9: =SUM(F9-H9-J9-I9) -> 0 | L9: =SUM(F9-H9-J9-I9) -> 0 | O9: =SUM(L9-M9-N9+O8) -> 268.9 | X9: 7 | AE9: =SUM(AC9:AD9) -> 0 | AJ9: =AE9 -> 0
A10: 44749 | F10: =SUM(B10:E10) -> 0 | G10: =F10 -> 0 | K10: =SUM(F10-H10-J10-I10) -> 0 | L10: =SUM(F10-H10-J10-I10) -> 0 | O10: =SUM(L10-M10-N10+O9) -> 268.9 | X10: 8 | AE10: =SUM(AC10:AD10) -> 0 | AJ10: =AE10 -> 0
A11: 44750 | F11: =SUM(B11:E11) -> 0 | G11: =F11 -> 0 | K11: =SUM(F11-H11-J11-I11) -> 0 | L11: =SUM(F11-H11-J11-I11) -> 0 | O11: =SUM(L11-M11-N11+O10) -> 268.9 | X11: 9 | AE11: =SUM(AC11:AD11) -> 0 | AJ11: =AE11 -> 0
A12: 44751 | F12: =SUM(B12:E12) -> 0 | G12: =F12 -> 0 | K12: =SUM(F12-H12-J12-I12) -> 0 | L12: =SUM(F12-H12-J12-I12) -> 0 | O12: =SUM(L12-M12-N12+O11) -> 268.9 | X12: 10 | AE12: =SUM(AC12:AD12) -> 0 | AJ12: =AE12 -> 0
A13: 44752 | F13: =SUM(B13:E13) -> 0 | G13: =F13 -> 0 | K13: =SUM(F13-H13-J13-I13) -> 0 | L13: =SUM(F13-H13-J13-I13) -> 0 | O13: =SUM(L13-M13-N13+O12) -> 268.9 | X13: 11 | AE13: =SUM(AC13:AD13) -> 0 | AJ13: =AE13 -> 0
A14: 44753 | F14: =SUM(B14:E14) -> 0 | G14: =F14 -> 0 | K14: =SUM(F14-H14-J14-I14) -> 0 | L14: =SUM(F14-H14-J14-I14) -> 0 | O14: =SUM(L14-M14-N14+O13) -> 268.9 | X14: 12 | AE14: =SUM(AC14:AD14) -> 0 | AJ14: =AE14 -> 0
A15: 44754 | F15: =SUM(B15:E15) -> 0 | G15: =F15 -> 0 | K15: =SUM(F15-H15-J15-I15) -> 0 | L15: =SUM(F15-H15-J15-I15) -> 0 | O15: =SUM(L15-M15-N15+O14) -> 268.9 | X15: 13 | AE15: =SUM(AC15:AD15) -> 0 | AJ15: =AE15 -> 0
A16: 44755 | F16: =SUM(B16:E16) -> 0 | G16: =F16 -> 0 | K16: =SUM(F16-H16-J16-I16) -> 0 | L16: =SUM(F16-H16-J16-I16) -> 0 | O16: =SUM(L16-M16-N16+O15) -> 268.9 | X16: 14 | AE16: =SUM(AC16:AD16) -> 0 | AJ16: =AE16 -> 0
A17: 44756 | F17: =SUM(B17:E17) -> 0 | G17: =F17 -> 0 | K17: =SUM(F17-H17-J17-I17) -> 0 | L17: =SUM(F17-H17-J17-I17) -> 0 | O17: =SUM(L17-M17-N17+O16+P17) -> 268.9 | X17: 15 | AE17: =SUM(AC17:AD17) -> 0 | AJ17: =AE17 -> 0
A18: 44757 | F18: =SUM(B18:E18) -> 0 | G18: =F18 -> 0 | K18: =SUM(F18-H18-J18-I18) -> 0 | L18: =SUM(F18-H18-J18-I18) -> 0 | O18: =SUM(L18-M18-N18+O17+P18) -> 268.9 | X18: 16 | AE18: =SUM(AC18:AD18) -> 0 | AJ18: =AE18 -> 0
A19: 44758 | F19: =SUM(B19:E19) -> 0 | G19: =F19 -> 0 | K19: =SUM(F19-H19-J19-I19) -> 0 | L19: =SUM(F19-H19-J19-I19) -> 0 | O19: =SUM(L19-M19-N19+O18+P19) -> 268.9 | X19: 17 | AE19: =SUM(AC19:AD19) -> 0 | AJ19: =AE19 -> 0
A20: 44759 | F20: =SUM(B20:E20) -> 0 | G20: =F20 -> 0 | K20: =SUM(F20-H20-J20-I20) -> 0 | L20: =SUM(F20-H20-J20-I20) -> 0 | O20: =SUM(L20-M20-N20+O19+P20) -> 268.9 | X20: 18 | AE20: =SUM(AC20:AD20) -> 0 | AJ20: =AE20 -> 0
A21: 44760 | F21: =SUM(B21:E21) -> 0 | G21: =F21 -> 0 | K21: =SUM(F21-H21-J21-I21) -> 0 | L21: =SUM(F21-H21-J21-I21) -> 0 | O21: =SUM(L21-M21-N21+O20) -> 268.9 | X21: 19 | AE21: =SUM(AC21:AD21) -> 0 | AJ21: =AE21 -> 0
A22: 44761 | F22: =SUM(B22:E22) -> 0 | G22: =F22 -> 0 | K22: =SUM(F22-H22-J22-I22) -> 0 | L22: =SUM(F22-H22-J22-I22) -> 0 | O22: =SUM(L22-M22-N22+O21) -> 268.9 | X22: 20 | AE22: =SUM(AC22:AD22) -> 0 | AJ22: =AE22 -> 0
A23: 44762 | F23: =SUM(B23:E23) -> 0 | G23: =F23 -> 0 | K23: =SUM(F23-H23-J23-I23) -> 0 | L23: =SUM(F23-H23-J23-I23) -> 0 | O23: =SUM(L23-M23-N23+O22) -> 268.9 | X23: 21 | AE23: =SUM(AC23:AD23) -> 0 | AJ23: =AE23 -> 0
A24: 44763 | F24: =SUM(B24:E24) -> 0 | G24: =F24 -> 0 | K24: =SUM(F24-H24-J24-I24) -> 0 | L24: =SUM(F24-H24-J24-I24) -> 0 | O24: =SUM(L24-M24-N24+O23+P24) -> 268.9 | X24: 22 | AE24: =SUM(AC24:AD24) -> 0 | AJ24: =AE24 -> 0
A25: 44764 | F25: =SUM(B25:E25) -> 0 | G25: =F25 -> 0 | K25: =SUM(F25-H25-J25-I25) -> 0 | L25: =SUM(F25-H25-J25-I25) -> 0 | O25: =SUM(L25-M25-N25+O24) -> 268.9 | X25: 26 | AE25: =SUM(AC25:AD25) -> 0 | AJ25: =AE25 -> 0
A26: 44765 | F26: =SUM(B26:E26) -> 0 | G26: =F26 -> 0 | K26: =SUM(F26-H26-J26-I26) -> 0 | L26: =SUM(F26-H26-J26-I26) -> 0 | O26: =SUM(L26-M26-N26+O25) -> 268.9 | X26: 27 | AE26: =SUM(AC26:AD26) -> 0 | AJ26: =AE26 -> 0
A27: 44766 | F27: =SUM(B27:E27) -> 0 | G27: =F27 -> 0 | K27: =SUM(F27-H27-J27-I27) -> 0 | L27: =SUM(F27-H27-J27-I27) -> 0 | O27: =SUM(L27-M27-N27+O26) -> 268.9 | X27: 28 | AE27: =SUM(AC27:AD27) -> 0 | AJ27: =AE27 -> 0
A28: 44767 | F28: =SUM(B28:E28) -> 0 | G28: =F28 -> 0 | K28: =SUM(F28-H28-J28-I28) -> 0 | L28: =SUM(F28-H28-J28-I28) -> 0 | O28: =SUM(L28-M28-N28+O27+P28) -> 268.9 | X28: 29 | AE28: =SUM(AC28:AD28) -> 0 | AJ28: =AE28 -> 0
A29: 44768 | F29: =SUM(B29:E29) -> 0 | G29: =F29 -> 0 | K29: =SUM(F29-H29-J29-I29) -> 0 | L29: =SUM(F29-H29-J29-I29) -> 0 | O29: =SUM(L29-M29-N29+O28) -> 268.9 | X29: 30 | AE29: =SUM(AC29:AD29) -> 0 | AJ29: =AE29 -> 0
A30: 44769 | F30: =SUM(B30:E30) -> 0 | G30: =F30 -> 0 | K30: =SUM(F30-H30-J30-I30) -> 0 | L30: =SUM(F30-H30-J30-I30) -> 0 | O30: =SUM(L30-M30-N30+O29+P30) -> 268.9 | AC30: TVA | AD30: =SUM(AD3:AD29) -> 0
A31: 44770 | F31: =SUM(B31:E31) -> 0 | G31: =F31 -> 0 | K31: =SUM(F31-H31-J31-I31) -> 0 | L31: =SUM(F31-H31-J31-I31) -> 0 | O31: =SUM(L31-M31-N31+O30) -> 268.9 | P31: SOLDE CAISSE
A32: 44771 | F32: =SUM(B32:E32) -> 0 | G32: =F32 -> 0 | K32: =SUM(F32-H32-J32-I32) -> 0 | L32: =SUM(F32-H32-J32-I32) -> 0 | O32: =SUM(L32-M32-N32+O31) -> 268.9 | P32: DU MOIS | AA32: MARGE | AL32: calcul de marge
A33: 44772 | F33: =SUM(B33:E33) -> 0 | G33: =F33 -> 0 | K33: =SUM(F33-H33-J33-I33) -> 0 | L33: =SUM(F33-H33-J33-I33) -> 0 | O33: =SUM(L33-M33-N33+O32) -> 268.9 | P33: =SUM(O33) -> 268.9 | X33: 1 | AE33: =SUM(AC33:AD33) -> 0 | AJ33: 0 | AL33: =AC33 -> 0 | AM33: 1
B34: =SUM(B5:B33) -> 0 | C34: =SUM(C3:C33) -> 0 | D34: =SUM(D3:D33) -> 0 | E34: =SUM(E3:E33) -> 0 | F34: =SUM(F3:F33) -> 0 | H34: =SUM(H3:H33) -> 0 | J34: =SUM(J3:J33) -> 0 | K34: =SUM(K3:K33) -> 0 | L34: =SUM(L3:L33) -> 0 | M34: =SUM(M3:M33) -> 0 | N34: =SUM(N3:N33) -> 0 | X34: 2 | AE34: =SUM(AC34:AD34) -> 0 | AJ34: =AE34 -> 0 | AL34: =AC34 -> 0 | AM34: 2
A35: HTVA | B35: =SUM(B3:B33) -> 0 | C35: =SUM(C34/1.06) -> 0 | D35: =SUM(D34/1.12) -> 0 | E35: =SUM(E34/1.21) -> 0 | F35: =SUM(B35:E35) -> 0 | G35: =SUM(G34:G34) -> 0 | L35: TOTAL SORTIE | N35: =SUM(M34:N34) -> 0 | X35: 3 | AE35: =SUM(AC35:AD35) -> 0 | AJ35: =AE35 -> 0 | AL35: =AC35 -> 0 | AM35: 3
A36: TVA | C36: =SUM(C34-C35) -> 0 | D36: =SUM(D34-D35) -> 0 | E36: =SUM(E34-E35) -> 0 | F36: =SUM(C36:E36) -> 0 | X36: 4 | AE36: =SUM(AC36:AD36) -> 0 | AJ36: 0 | AL36: =AC36 -> 0 | AM36: 4
X37: 5 | AE37: =SUM(AC37:AD37) -> 0 | AJ37: =AE37 -> 0 | AL37: =AC37 -> 0 | AM37: 5
X38: 6 | AE38: =SUM(AC38:AD38) -> 0 | AJ38: 0 | AL38: =AC38 -> 0 | AM38: 6
X39: 7 | AE39: =SUM(AC39:AD39) -> 0 | AJ39: =AE39 -> 0 | AL39: =AC39 -> 0 | AM39: 7
X40: 8 | AE40: =SUM(AC40:AD40) -> 0 | AJ40: =AE40 -> 0 | AL40: =AC40 -> 0 | AM40: 8
X41: 9 | AE41: =SUM(AC41:AD41) -> 0 | AJ41: =AE41 -> 0 | AL41: =AC41 -> 0 | AM41: 9
X42: 10 | AE42: =SUM(AC42:AD42) -> 0 | AJ42: =AE42 -> 0 | AL42: =AC42 -> 0 | AM42: 10
X43: 11 | AE43: =SUM(AC43:AD43) -> 0 | AJ43: =AE43 -> 0 | AL43: =AC43 -> 0 | AM43: 11
X44: 12 | AE44: =SUM(AC44:AD44) -> 0 | AJ44: =AE44 -> 0 | AL44: =AC44 -> 0 | AM44: 12
X45: 13 | AE45: =SUM(AC45:AD45) -> 0 | AJ45: =AE45 -> 0 | AL45: =AC45 -> 0 | AM45: 13
X46: 14 | AE46: =SUM(AC46:AD46) -> 0 | AJ46: =AE46 -> 0 | AL46: =AC46 -> 0 | AM46: 14
X47: 15 | AE47: =SUM(AC47:AD47) -> 0 | AJ47: =AE47 -> 0 | AL47: =AC47 -> 0 | AM47: 15
X48: 16 | AE48: =SUM(AC48:AD48) -> 0 | AJ48: =AE48 -> 0 | AL48: =AC48 -> 0 | AM48: 16
X49: 17 | AE49: =SUM(AC49:AD49) -> 0 | AJ49: =AE49 -> 0 | AL49: =AC49 -> 0 | AM49: 17
X50: 18 | AE50: =SUM(AC50:AD50) -> 0 | AJ50: =AE50 -> 0 | AL50: =AC50 -> 0 | AM50: 18
... X62: 30 | AE62: =SUM(AC62:AD62) -> 0 | AJ62: =AE62 -> 0 | AL62: =AC62 -> 0 | AM62: 30
AC63: =SUM(AC33:AC62) -> 0 | AH63: TOTAL GENE FEUILLE | AJ63: =SUM(AJ3:AJ62) -> 0 | AL63: =AC63 -> 0
AC64: TVA | AD64: =SUM(AD33:AD63) -> 0
AI66: A PÄYER
AC67: TVA | AD67: =AD30 -> 0 | AJ67: =AJ63 -> 0
AC68: TVA | AD68: =AD64 -> 0 | AI68: mois précèdent | AJ68: ='JANV 2026'!AJ69 -> 0
AC69: TVA RECUP | AD69: =SUM(AD67:AD68) -> 0 | AI69: total a payer | AJ69: =SUM(AJ67:AJ68) -> 0

Sheet JUIN 2026
A1: 44712 | C1: RECETTE | G1: CAISSE | M1: MOUVEMENT CAISSE | P1: CAISSE MOIS PREC | Q1: PAYEMENT FOURNISSEUR CAISSE | R1: MONTANT | S1: TOTAL | T1: DATE SORTIE | Y1: FOURNISSEUR | Z1: DATE | AA1: REFERENCE | AB1: COMPTE | AC1: HTVA | AD1: TVA | AE1: MONTANT | AF1: PAIEMENT | AG1: CAISSE | AH1: DATE | AI1: ECHEANCE
A2: DATE | B2: FACTURE | C2: 6 | D2: 12 | E2: 21 | F2: TOTAL | G2: CHIFF | H2: carte | I2: cadeau0 | J2: bque | K2: liquide | L2: TOT CAIS | M2: SORTIE | N2: vers ban | O2: solde cai | P2: ='MAI 2026'!P33 -> 250 | AB2: 44712
A3: 44712 | F3: =SUM(B3:E3) -> 0 | G3: =F3 -> 0 | K3: =SUM(F3-H3-J3-I3) -> 0 | L3: =SUM(F3-H3-J3-I3) -> 0 | O3: =SUM(L3-M3-N3+P2) -> 250 | X3: 1 | AE3: =SUM(AC3:AD3) -> 0 | AJ3: 0
A4: 44713 | F4: =SUM(B4:E4) -> 0 | G4: =F4 -> 0 | K4: =SUM(F4-H4-J4-I4) -> 0 | L4: =SUM(F4-H4-J4-I4) -> 0 | O4: =SUM(L4-M4-N4+O3+P4) -> 250 | X4: 2 | AE4: =SUM(AC4:AD4) -> 0 | AJ4: =AE4 -> 0
A5: 44714 | F5: =SUM(B5:E5) -> 0 | G5: =F5 -> 0 | K5: =SUM(F5-H5-J5-I5) -> 0 | L5: =SUM(F5-H5-J5-I5) -> 0 | O5: =SUM(L5-M5-N5+O4+P5) -> 250 | X5: 3 | AE5: =SUM(AC5:AD5) -> 0 | AJ5: 0
A6: 44715 | F6: =SUM(B6:E6) -> 0 | G6: =F6 -> 0 | K6: =SUM(F6-H6-J6-I6) -> 0 | L6: =SUM(F6-H6-J6-I6) -> 0 | O6: =SUM(L6-M6-N6+O5+P6) -> 250 | X6: 4 | AE6: =SUM(AC6:AD6) -> 0 | AJ6: 0
A7: 44716 | F7: =SUM(B7:E7) -> 0 | G7: =F7 -> 0 | K7: =SUM(F7-H7-J7-I7) -> 0 | L7: =SUM(F7-H7-J7-I7) -> 0 | O7: =SUM(L7-M7-N7+O6+P7) -> 250 | X7: 5 | AE7: =SUM(AC7:AD7) -> 0 | AJ7: 0
A8: 44717 | F8: =SUM(B8:E8) -> 0 | G8: =F8 -> 0 | K8: =SUM(F8-H8-J8-I8) -> 0 | L8: =SUM(F8-H8-J8-I8) -> 0 | O8: =SUM(L8-M8-N8+O7+P8) -> 250 | X8: 6 | AE8: =SUM(AC8:AD8) -> 0 | AJ8: 0
A9: 44718 | F9: =SUM(B9:E9) -> 0 | G9: =F9 -> 0 | K9: =SUM(F9-H9-J9-I9) -> 0 | L9: =SUM(F9-H9-J9-I9) -> 0 | O9: =SUM(L9-M9-N9+O8) -> 250 | X9: 7 | AE9: =SUM(AC9:AD9) -> 0 | AJ9: =AE9 -> 0
A10: 44719 | F10: =SUM(B10:E10) -> 0 | G10: =F10 -> 0 | K10: =SUM(F10-H10-J10-I10) -> 0 | L10: =SUM(F10-H10-J10-I10) -> 0 | O10: =SUM(L10-M10-N10+O9) -> 250 | X10: 8 | AE10: =SUM(AC10:AD10) -> 0 | AJ10: =AE10 -> 0
A11: 44720 | F11: =SUM(B11:E11) -> 0 | G11: =F11 -> 0 | K11: =SUM(F11-H11-J11-I11) -> 0 | L11: =SUM(F11-H11-J11-I11) -> 0 | O11: =SUM(L11-M11-N11+O10) -> 250 | X11: 9 | AE11: =SUM(AC11:AD11) -> 0 | AJ11: =AE11 -> 0
A12: 44721 | F12: =SUM(B12:E12) -> 0 | G12: =F12 -> 0 | K12: =SUM(F12-H12-J12-I12) -> 0 | L12: =SUM(F12-H12-J12-I12) -> 0 | O12: =SUM(L12-M12-N12+O11) -> 250 | X12: 10 | AE12: =SUM(AC12:AD12) -> 0 | AJ12: =AE12 -> 0
A13: 44722 | F13: =SUM(B13:E13) -> 0 | G13: =F13 -> 0 | K13: =SUM(F13-H13-J13-I13) -> 0 | L13: =SUM(F13-H13-J13-I13) -> 0 | O13: =SUM(L13-M13-N13+O12) -> 250 | X13: 11 | AE13: =SUM(AC13:AD13) -> 0 | AJ13: =AE13 -> 0
A14: 44723 | F14: =SUM(B14:E14) -> 0 | G14: =F14 -> 0 | K14: =SUM(F14-H14-J14-I14) -> 0 | L14: =SUM(F14-H14-J14-I14) -> 0 | O14: =SUM(L14-M14-N14+O13) -> 250 | X14: 12 | AE14: =SUM(AC14:AD14) -> 0 | AJ14: =AE14 -> 0
A15: 44724 | F15: =SUM(B15:E15) -> 0 | G15: =F15 -> 0 | K15: =SUM(F15-H15-J15-I15) -> 0 | L15: =SUM(F15-H15-J15-I15) -> 0 | O15: =SUM(L15-M15-N15+O14) -> 250 | X15: 13 | AE15: =SUM(AC15:AD15) -> 0 | AJ15: =AE15 -> 0
A16: 44725 | F16: =SUM(B16:E16) -> 0 | G16: =F16 -> 0 | K16: =SUM(F16-H16-J16-I16) -> 0 | L16: =SUM(F16-H16-J16-I16) -> 0 | O16: =SUM(L16-M16-N16+O15) -> 250 | X16: 14 | AE16: =SUM(AC16:AD16) -> 0 | AJ16: =AE16 -> 0
A17: 44726 | F17: =SUM(B17:E17) -> 0 | G17: =F17 -> 0 | K17: =SUM(F17-H17-J17-I17) -> 0 | L17: =SUM(F17-H17-J17-I17) -> 0 | O17: =SUM(L17-M17-N17+O16+P17) -> 250 | X17: 15 | AE17: =SUM(AC17:AD17) -> 0 | AJ17: =AE17 -> 0
A18: 44727 | C18: 878.04 | E18: 36 | F18: =SUM(B18:E18) -> 914.04 | G18: =F18 -> 914.04 | H18: 895.14 | K18: =SUM(F18-H18-J18-I18) -> 18.9 | L18: =SUM(F18-H18-J18-I18) -> 18.9 | O18: =SUM(L18-M18-N18+O17+P18) -> 268.9 | X18: 16 | AE18: =SUM(AC18:AD18) -> 0 | AJ18: =AE18 -> 0
A19: 44728 | F19: =SUM(B19:E19) -> 0 | G19: =F19 -> 0 | K19: =SUM(F19-H19-J19-I19) -> 0 | L19: =SUM(F19-H19-J19-I19) -> 0 | O19: =SUM(L19-M19-N19+O18+P19) -> 268.9 | X19: 17 | AE19: =SUM(AC19:AD19) -> 0 | AJ19: =AE19 -> 0
A20: 44729 | F20: =SUM(B20:E20) -> 0 | G20: =F20 -> 0 | K20: =SUM(F20-H20-J20-I20) -> 0 | L20: =SUM(F20-H20-J20-I20) -> 0 | O20: =SUM(L20-M20-N20+O19+P20) -> 268.9 | X20: 18 | AE20: =SUM(AC20:AD20) -> 0 | AJ20: =AE20 -> 0
A21: 44730 | F21: =SUM(B21:E21) -> 0 | G21: =F21 -> 0 | K21: =SUM(F21-H21-J21-I21) -> 0 | L21: =SUM(F21-H21-J21-I21) -> 0 | O21: =SUM(L21-M21-N21+O20) -> 268.9 | X21: 19 | AE21: =SUM(AC21:AD21) -> 0 | AJ21: =AE21 -> 0
A22: 44731 | F22: =SUM(B22:E22) -> 0 | G22: =F22 -> 0 | K22: =SUM(F22-H22-J22-I22) -> 0 | L22: =SUM(F22-H22-J22-I22) -> 0 | O22: =SUM(L22-M22-N22+O21) -> 268.9 | X22: 20 | AE22: =SUM(AC22:AD22) -> 0 | AJ22: =AE22 -> 0
A23: 44732 | F23: =SUM(B23:E23) -> 0 | G23: =F23 -> 0 | K23: =SUM(F23-H23-J23-I23) -> 0 | L23: =SUM(F23-H23-J23-I23) -> 0 | O23: =SUM(L23-M23-N23+O22) -> 268.9 | X23: 21 | AE23: =SUM(AC23:AD23) -> 0 | AJ23: =AE23 -> 0
A24: 44733 | F24: =SUM(B24:E24) -> 0 | G24: =F24 -> 0 | K24: =SUM(F24-H24-J24-I24) -> 0 | L24: =SUM(F24-H24-J24-I24) -> 0 | O24: =SUM(L24-M24-N24+O23+P24) -> 268.9 | X24: 22 | AE24: =SUM(AC24:AD24) -> 0 | AJ24: =AE24 -> 0
A25: 44734 | F25: =SUM(B25:E25) -> 0 | G25: =F25 -> 0 | K25: =SUM(F25-H25-J25-I25) -> 0 | L25: =SUM(F25-H25-J25-I25) -> 0 | O25: =SUM(L25-M25-N25+O24) -> 268.9 | X25: 26 | AE25: =SUM(AC25:AD25) -> 0 | AJ25: =AE25 -> 0
A26: 44735 | F26: =SUM(B26:E26) -> 0 | G26: =F26 -> 0 | K26: =SUM(F26-H26-J26-I26) -> 0 | L26: =SUM(F26-H26-J26-I26) -> 0 | O26: =SUM(L26-M26-N26+O25) -> 268.9 | X26: 27 | AE26: =SUM(AC26:AD26) -> 0 | AJ26: =AE26 -> 0
A27: 44736 | F27: =SUM(B27:E27) -> 0 | G27: =F27 -> 0 | K27: =SUM(F27-H27-J27-I27) -> 0 | L27: =SUM(F27-H27-J27-I27) -> 0 | O27: =SUM(L27-M27-N27+O26) -> 268.9 | X27: 28 | AE27: =SUM(AC27:AD27) -> 0 | AJ27: =AE27 -> 0
A28: 44737 | F28: =SUM(B28:E28) -> 0 | G28: =F28 -> 0 | K28: =SUM(F28-H28-J28-I28) -> 0 | L28: =SUM(F28-H28-J28-I28) -> 0 | O28: =SUM(L28-M28-N28+O27+P28) -> 268.9 | X28: 29 | AE28: =SUM(AC28:AD28) -> 0 | AJ28: =AE28 -> 0
A29: 44738 | F29: =SUM(B29:E29) -> 0 | G29: =F29 -> 0 | K29: =SUM(F29-H29-J29-I29) -> 0 | L29: =SUM(F29-H29-J29-I29) -> 0 | O29: =SUM(L29-M29-N29+O28) -> 268.9 | X29: 30 | AE29: =SUM(AC29:AD29) -> 0 | AJ29: =AE29 -> 0
A30: 44739 | F30: =SUM(B30:E30) -> 0 | G30: =F30 -> 0 | K30: =SUM(F30-H30-J30-I30) -> 0 | L30: =SUM(F30-H30-J30-I30) -> 0 | O30: =SUM(L30-M30-N30+O29+P30) -> 268.9 | AC30: TVA | AD30: =SUM(AD3:AD29) -> 0
A31: 44740 | F31: =SUM(B31:E31) -> 0 | G31: =F31 -> 0 | K31: =SUM(F31-H31-J31-I31) -> 0 | L31: =SUM(F31-H31-J31-I31) -> 0 | O31: =SUM(L31-M31-N31+O30) -> 268.9 | P31: SOLDE CAISSE
A32: 44741 | F32: =SUM(B32:E32) -> 0 | G32: =F32 -> 0 | K32: =SUM(F32-H32-J32-I32) -> 0 | L32: =SUM(F32-H32-J32-I32) -> 0 | O32: =SUM(L32-M32-N32+O31) -> 268.9 | P32: DU MOIS | AA32: MARGE | AL32: calcul de marge
F33: =SUM(B33:E33) -> 0 | G33: =F33 -> 0 | K33: =SUM(F33-H33-J33-I33) -> 0 | L33: =SUM(F33-H33-J33-I33) -> 0 | O33: =SUM(L33-M33-N33+O32) -> 268.9 | P33: =SUM(O33) -> 268.9 | X33: 1 | Y33: colruyt | Z33: 44726 | AA33: 31042601 7246 | AC33: 40.92 | AD33: 2.46 | AE33: =SUM(AC33:AD33) -> 43.38 | AF33: banotact | AJ33: 0 | AL33: =AC33 -> 40.92 | AM33: 1
B34: =SUM(B5:B33) -> 0 | C34: =SUM(C3:C33) -> 878.04 | D34: =SUM(D3:D33) -> 0 | E34: =SUM(E3:E33) -> 36 | F34: =SUM(F3:F33) -> 914.04 | H34: =SUM(H3:H33) -> 895.14 | J34: =SUM(J3:J33) -> 0 | K34: =SUM(K3:K33) -> 18.9 | L34: =SUM(L3:L33) -> 18.9 | M34: =SUM(M3:M33) -> 0 | N34: =SUM(N3:N33) -> 0 | X34: 2 | Y34: big bag | Z34: 44727 | AA34: 202/6017/33260 | AC34: 450.73 | AD34: 45.96 | AE34: =SUM(AC34:AD34) -> 496.69 | AJ34: =AE34 -> 496.69 | AL34: =AC34 -> 450.73 | AM34: 2
A35: HTVA | B35: =SUM(B3:B33) -> 0 | C35: =SUM(C34/1.06) -> 828.33962 | D35: =SUM(D34/1.12) -> 0 | E35: =SUM(E34/1.21) -> 29.752066 | F35: =SUM(B35:E35) -> 858.09169 | G35: =SUM(G34:G34) -> 0 | L35: TOTAL SORTIE | N35: =SUM(M34:N34) -> 0 | X35: 3 | Y35: bella sicilia | Z35: 44726 | AA35: 222554 | AC35: 518.14 | AD35: 50.29 | AE35: =SUM(AC35:AD35) -> 568.43 | AJ35: =AE35 -> 568.43 | AL35: =AC35 -> 518.14 | AM35: 3
A36: TVA | C36: =SUM(C34-C35) -> 49.700377 | D36: =SUM(D34-D35) -> 0 | E36: =SUM(E34-E35) -> 6.2479339 | F36: =SUM(C36:E36) -> 55.948311 | X36: 4 | Y36: colruyt | Z36: 44728 | AA36: 3104260 17428 | AC36: 168 | AD36: 19.89 | AE36: =SUM(AC36:AD36) -> 187.89 | AF36: banotact | AJ36: 0 | AL36: =AC36 -> 168 | AM36: 4
X37: 5 | AE37: =SUM(AC37:AD37) -> 0 | AJ37: =AE37 -> 0 | AL37: =AC37 -> 0 | AM37: 5
X38: 6 | AE38: =SUM(AC38:AD38) -> 0 | AJ38: 0 | AL38: =AC38 -> 0 | AM38: 6
X39: 7 | AE39: =SUM(AC39:AD39) -> 0 | AJ39: =AE39 -> 0 | AL39: =AC39 -> 0 | AM39: 7
X40: 8 | AE40: =SUM(AC40:AD40) -> 0 | AJ40: =AE40 -> 0 | AL40: =AC40 -> 0 | AM40: 8
X41: 9 | AE41: =SUM(AC41:AD41) -> 0 | AJ41: =AE41 -> 0 | AL41: =AC41 -> 0 | AM41: 9
X42: 10 | AE42: =SUM(AC42:AD42) -> 0 | AJ42: =AE42 -> 0 | AL42: =AC42 -> 0 | AM42: 10
X43: 11 | AE43: =SUM(AC43:AD43) -> 0 | AJ43: =AE43 -> 0 | AL43: =AC43 -> 0 | AM43: 11
X44: 12 | AE44: =SUM(AC44:AD44) -> 0 | AJ44: =AE44 -> 0 | AL44: =AC44 -> 0 | AM44: 12
X45: 13 | AE45: =SUM(AC45:AD45) -> 0 | AJ45: =AE45 -> 0 | AL45: =AC45 -> 0 | AM45: 13
X46: 14 | AE46: =SUM(AC46:AD46) -> 0 | AJ46: =AE46 -> 0 | AL46: =AC46 -> 0 | AM46: 14
X47: 15 | AE47: =SUM(AC47:AD47) -> 0 | AJ47: =AE47 -> 0 | AL47: =AC47 -> 0 | AM47: 15
X48: 16 | AE48: =SUM(AC48:AD48) -> 0 | AJ48: =AE48 -> 0 | AL48: =AC48 -> 0 | AM48: 16
X49: 17 | AE49: =SUM(AC49:AD49) -> 0 | AJ49: =AE49 -> 0 | AL49: =AC49 -> 0 | AM49: 17
X50: 18 | AE50: =SUM(AC50:AD50) -> 0 | AJ50: =AE50 -> 0 | AL50: =AC50 -> 0 | AM50: 18
... X62: 30 | AE62: =SUM(AC62:AD62) -> 0 | AJ62: =AE62 -> 0 | AL62: =AC62 -> 0 | AM62: 30
AC63: =SUM(AC33:AC62) -> 1177.79 | AH63: TOTAL GENE FEUILLE | AJ63: =SUM(AJ3:AJ62) -> 1065.12 | AL63: =AC63 -> 1177.79
AC64: TVA | AD64: =SUM(AD33:AD63) -> 118.6
AI66: A PÄYER
AC67: TVA | AD67: =AD30 -> 0 | AJ67: =AJ63 -> 1065.12
AC68: TVA | AD68: =AD64 -> 118.6 | AI68: mois précèdent | AJ68: ='JANV 2026'!AJ69 -> 0
AC69: TVA RECUP | AD69: =SUM(AD67:AD68) -> 118.6 | AI69: total a payer | AJ69: =SUM(AJ67:AJ68) -> 1065.12

Sheet MAI 2026
A1: 44681 | C1: RECETTE | G1: CAISSE | M1: MOUVEMENT CAISSE | P1: CAISSE MOIS PREC | Q1: PAYEMENT FOURNISSEUR CAISSE | R1: MONTANT | S1: TOTAL | T1: DATE SORTIE | Y1: FOURNISSEUR | Z1: DATE | AA1: REFERENCE | AB1: COMPTE | AC1: HTVA | AD1: TVA | AE1: MONTANT | AF1: PAIEMENT | AG1: CAISSE | AH1: DATE | AI1: ECHEANCE
A2: DATE | B2: FACTURE | C2: 6 | D2: 12 | E2: 21 | F2: TOTAL | G2: CHIFF | H2: carte | I2: cadeau0 | J2: bque | K2: liquide | L2: TOT CAIS | M2: SORTIE | N2: vers ban | O2: solde cai | P2: ='AVRIL 2026'!P33 -> 250 | AB2: 44681
A3: 44681 | F3: =SUM(B3:E3) -> 0 | G3: =F3 -> 0 | K3: =SUM(F3-H3-J3-I3) -> 0 | L3: =SUM(F3-H3-J3-I3) -> 0 | O3: =SUM(L3-M3-N3+P2) -> 250 | X3: 1 | AE3: =SUM(AC3:AD3) -> 0 | AJ3: 0
A4: 44682 | F4: =SUM(B4:E4) -> 0 | G4: =F4 -> 0 | K4: =SUM(F4-H4-J4-I4) -> 0 | L4: =SUM(F4-H4-J4-I4) -> 0 | O4: =SUM(L4-M4-N4+O3+P4) -> 250 | X4: 2 | AE4: =SUM(AC4:AD4) -> 0 | AJ4: =AE4 -> 0
A5: 44683 | F5: =SUM(B5:E5) -> 0 | G5: =F5 -> 0 | K5: =SUM(F5-H5-J5-I5) -> 0 | L5: =SUM(F5-H5-J5-I5) -> 0 | O5: =SUM(L5-M5-N5+O4+P5) -> 250 | X5: 3 | AE5: =SUM(AC5:AD5) -> 0 | AJ5: 0
A6: 44684 | F6: =SUM(B6:E6) -> 0 | G6: =F6 -> 0 | K6: =SUM(F6-H6-J6-I6) -> 0 | L6: =SUM(F6-H6-J6-I6) -> 0 | O6: =SUM(L6-M6-N6+O5+P6) -> 250 | X6: 4 | AE6: =SUM(AC6:AD6) -> 0 | AJ6: 0
A7: 44685 | F7: =SUM(B7:E7) -> 0 | G7: =F7 -> 0 | K7: =SUM(F7-H7-J7-I7) -> 0 | L7: =SUM(F7-H7-J7-I7) -> 0 | O7: =SUM(L7-M7-N7+O6+P7) -> 250 | X7: 5 | AE7: =SUM(AC7:AD7) -> 0 | AJ7: 0
A8: 44686 | F8: =SUM(B8:E8) -> 0 | G8: =F8 -> 0 | K8: =SUM(F8-H8-J8-I8) -> 0 | L8: =SUM(F8-H8-J8-I8) -> 0 | O8: =SUM(L8-M8-N8+O7+P8) -> 250 | X8: 6 | AE8: =SUM(AC8:AD8) -> 0 | AJ8: 0
A9: 44687 | F9: =SUM(B9:E9) -> 0 | G9: =F9 -> 0 | K9: =SUM(F9-H9-J9-I9) -> 0 | L9: =SUM(F9-H9-J9-I9) -> 0 | O9: =SUM(L9-M9-N9+O8) -> 250 | X9: 7 | AE9: =SUM(AC9:AD9) -> 0 | AJ9: =AE9 -> 0
A10: 44688 | F10: =SUM(B10:E10) -> 0 | G10: =F10 -> 0 | K10: =SUM(F10-H10-J10-I10) -> 0 | L10: =SUM(F10-H10-J10-I10) -> 0 | O10: =SUM(L10-M10-N10+O9) -> 250 | X10: 8 | AE10: =SUM(AC10:AD10) -> 0 | AJ10: =AE10 -> 0
A11: 44689 | F11: =SUM(B11:E11) -> 0 | G11: =F11 -> 0 | K11: =SUM(F11-H11-J11-I11) -> 0 | L11: =SUM(F11-H11-J11-I11) -> 0 | O11: =SUM(L11-M11-N11+O10) -> 250 | X11: 9 | AE11: =SUM(AC11:AD11) -> 0 | AJ11: =AE11 -> 0
A12: 44690 | F12: =SUM(B12:E12) -> 0 | G12: =F12 -> 0 | K12: =SUM(F12-H12-J12-I12) -> 0 | L12: =SUM(F12-H12-J12-I12) -> 0 | O12: =SUM(L12-M12-N12+O11) -> 250 | X12: 10 | AE12: =SUM(AC12:AD12) -> 0 | AJ12: =AE12 -> 0
A13: 44691 | F13: =SUM(B13:E13) -> 0 | G13: =F13 -> 0 | K13: =SUM(F13-H13-J13-I13) -> 0 | L13: =SUM(F13-H13-J13-I13) -> 0 | O13: =SUM(L13-M13-N13+O12) -> 250 | X13: 11 | AE13: =SUM(AC13:AD13) -> 0 | AJ13: =AE13 -> 0
A14: 44692 | F14: =SUM(B14:E14) -> 0 | G14: =F14 -> 0 | K14: =SUM(F14-H14-J14-I14) -> 0 | L14: =SUM(F14-H14-J14-I14) -> 0 | O14: =SUM(L14-M14-N14+O13) -> 250 | X14: 12 | AE14: =SUM(AC14:AD14) -> 0 | AJ14: =AE14 -> 0
A15: 44693 | F15: =SUM(B15:E15) -> 0 | G15: =F15 -> 0 | K15: =SUM(F15-H15-J15-I15) -> 0 | L15: =SUM(F15-H15-J15-I15) -> 0 | O15: =SUM(L15-M15-N15+O14) -> 250 | X15: 13 | AE15: =SUM(AC15:AD15) -> 0 | AJ15: =AE15 -> 0
A16: 44694 | F16: =SUM(B16:E16) -> 0 | G16: =F16 -> 0 | K16: =SUM(F16-H16-J16-I16) -> 0 | L16: =SUM(F16-H16-J16-I16) -> 0 | O16: =SUM(L16-M16-N16+O15) -> 250 | X16: 14 | AE16: =SUM(AC16:AD16) -> 0 | AJ16: =AE16 -> 0
A17: 44695 | F17: =SUM(B17:E17) -> 0 | G17: =F17 -> 0 | K17: =SUM(F17-H17-J17-I17) -> 0 | L17: =SUM(F17-H17-J17-I17) -> 0 | O17: =SUM(L17-M17-N17+O16+P17) -> 250 | X17: 15 | AE17: =SUM(AC17:AD17) -> 0 | AJ17: =AE17 -> 0
A18: 44696 | F18: =SUM(B18:E18) -> 0 | G18: =F18 -> 0 | K18: =SUM(F18-H18-J18-I18) -> 0 | L18: =SUM(F18-H18-J18-I18) -> 0 | O18: =SUM(L18-M18-N18+O17+P18) -> 250 | X18: 16 | AE18: =SUM(AC18:AD18) -> 0 | AJ18: =AE18 -> 0
A19: 44697 | F19: =SUM(B19:E19) -> 0 | G19: =F19 -> 0 | K19: =SUM(F19-H19-J19-I19) -> 0 | L19: =SUM(F19-H19-J19-I19) -> 0 | O19: =SUM(L19-M19-N19+O18+P19) -> 250 | X19: 17 | AE19: =SUM(AC19:AD19) -> 0 | AJ19: =AE19 -> 0
A20: 44698 | F20: =SUM(B20:E20) -> 0 | G20: =F20 -> 0 | K20: =SUM(F20-H20-J20-I20) -> 0 | L20: =SUM(F20-H20-J20-I20) -> 0 | O20: =SUM(L20-M20-N20+O19+P20) -> 250 | X20: 18 | AE20: =SUM(AC20:AD20) -> 0 | AJ20: =AE20 -> 0
A21: 44699 | F21: =SUM(B21:E21) -> 0 | G21: =F21 -> 0 | K21: =SUM(F21-H21-J21-I21) -> 0 | L21: =SUM(F21-H21-J21-I21) -> 0 | O21: =SUM(L21-M21-N21+O20) -> 250 | X21: 19 | AE21: =SUM(AC21:AD21) -> 0 | AJ21: =AE21 -> 0
A22: 44700 | F22: =SUM(B22:E22) -> 0 | G22: =F22 -> 0 | K22: =SUM(F22-H22-J22-I22) -> 0 | L22: =SUM(F22-H22-J22-I22) -> 0 | O22: =SUM(L22-M22-N22+O21) -> 250 | X22: 20 | AE22: =SUM(AC22:AD22) -> 0 | AJ22: =AE22 -> 0
A23: 44701 | F23: =SUM(B23:E23) -> 0 | G23: =F23 -> 0 | K23: =SUM(F23-H23-J23-I23) -> 0 | L23: =SUM(F23-H23-J23-I23) -> 0 | O23: =SUM(L23-M23-N23+O22) -> 250 | X23: 21 | AE23: =SUM(AC23:AD23) -> 0 | AJ23: =AE23 -> 0
A24: 44702 | F24: =SUM(B24:E24) -> 0 | G24: =F24 -> 0 | K24: =SUM(F24-H24-J24-I24) -> 0 | L24: =SUM(F24-H24-J24-I24) -> 0 | O24: =SUM(L24-M24-N24+O23+P24) -> 250 | X24: 22 | AE24: =SUM(AC24:AD24) -> 0 | AJ24: =AE24 -> 0
A25: 44703 | F25: =SUM(B25:E25) -> 0 | G25: =F25 -> 0 | K25: =SUM(F25-H25-J25-I25) -> 0 | L25: =SUM(F25-H25-J25-I25) -> 0 | O25: =SUM(L25-M25-N25+O24) -> 250 | X25: 26 | AE25: =SUM(AC25:AD25) -> 0 | AJ25: =AE25 -> 0
A26: 44704 | F26: =SUM(B26:E26) -> 0 | G26: =F26 -> 0 | K26: =SUM(F26-H26-J26-I26) -> 0 | L26: =SUM(F26-H26-J26-I26) -> 0 | O26: =SUM(L26-M26-N26+O25) -> 250 | X26: 27 | AE26: =SUM(AC26:AD26) -> 0 | AJ26: =AE26 -> 0
A27: 44705 | F27: =SUM(B27:E27) -> 0 | G27: =F27 -> 0 | K27: =SUM(F27-H27-J27-I27) -> 0 | L27: =SUM(F27-H27-J27-I27) -> 0 | O27: =SUM(L27-M27-N27+O26) -> 250 | X27: 28 | AE27: =SUM(AC27:AD27) -> 0 | AJ27: =AE27 -> 0
A28: 44706 | F28: =SUM(B28:E28) -> 0 | G28: =F28 -> 0 | K28: =SUM(F28-H28-J28-I28) -> 0 | L28: =SUM(F28-H28-J28-I28) -> 0 | O28: =SUM(L28-M28-N28+O27+P28) -> 250 | X28: 29 | AE28: =SUM(AC28:AD28) -> 0 | AJ28: =AE28 -> 0
A29: 44707 | F29: =SUM(B29:E29) -> 0 | G29: =F29 -> 0 | K29: =SUM(F29-H29-J29-I29) -> 0 | L29: =SUM(F29-H29-J29-I29) -> 0 | O29: =SUM(L29-M29-N29+O28) -> 250 | X29: 30 | AE29: =SUM(AC29:AD29) -> 0 | AJ29: =AE29 -> 0
A30: 44708 | F30: =SUM(B30:E30) -> 0 | G30: =F30 -> 0 | K30: =SUM(F30-H30-J30-I30) -> 0 | L30: =SUM(F30-H30-J30-I30) -> 0 | O30: =SUM(L30-M30-N30+O29+P30) -> 250 | AC30: TVA | AD30: =SUM(AD3:AD29) -> 0
A31: 44709 | F31: =SUM(B31:E31) -> 0 | G31: =F31 -> 0 | K31: =SUM(F31-H31-J31-I31) -> 0 | L31: =SUM(F31-H31-J31-I31) -> 0 | O31: =SUM(L31-M31-N31+O30) -> 250 | P31: SOLDE CAISSE
A32: 44710 | F32: =SUM(B32:E32) -> 0 | G32: =F32 -> 0 | K32: =SUM(F32-H32-J32-I32) -> 0 | L32: =SUM(F32-H32-J32-I32) -> 0 | O32: =SUM(L32-M32-N32+O31) -> 250 | P32: DU MOIS | AA32: MARGE | AL32: calcul de marge
A33: 44711 | F33: =SUM(B33:E33) -> 0 | G33: =F33 -> 0 | K33: =SUM(F33-H33-J33-I33) -> 0 | L33: =SUM(F33-H33-J33-I33) -> 0 | O33: =SUM(L33-M33-N33+O32) -> 250 | P33: =SUM(O33) -> 250 | X33: 1 | AE33: =SUM(AC33:AD33) -> 0 | AJ33: =AE33 -> 0 | AL33: =AC33 -> 0 | AM33: 1
B34: =SUM(B5:B33) -> 0 | C34: =SUM(C3:C33) -> 0 | D34: =SUM(D3:D33) -> 0 | E34: =SUM(E3:E33) -> 0 | F34: =SUM(F3:F33) -> 0 | H34: =SUM(H3:H33) -> 0 | J34: =SUM(J3:J33) -> 0 | K34: =SUM(K3:K33) -> 0 | L34: =SUM(L3:L33) -> 0 | M34: =SUM(M3:M33) -> 0 | N34: =SUM(N3:N33) -> 0 | X34: 2 | AE34: =SUM(AC34:AD34) -> 0 | AJ34: =AE34 -> 0 | AL34: =AC34 -> 0 | AM34: 2
A35: HTVA | B35: =SUM(B3:B33) -> 0 | C35: =SUM(C34/1.06) -> 0 | D35: =SUM(D34/1.12) -> 0 | E35: =SUM(E34/1.21) -> 0 | F35: =SUM(B35:E35) -> 0 | G35: =SUM(G34:G34) -> 0 | L35: TOTAL SORTIE | N35: =SUM(M34:N34) -> 0 | X35: 3 | AE35: =SUM(AC35:AD35) -> 0 | AJ35: =AE35 -> 0 | AL35: =AC35 -> 0 | AM35: 3
A36: TVA | C36: =SUM(C34-C35) -> 0 | D36: =SUM(D34-D35) -> 0 | E36: =SUM(E34-E35) -> 0 | F36: =SUM(C36:E36) -> 0 | X36: 4 | AE36: =SUM(AC36:AD36) -> 0 | AJ36: 0 | AL36: =AC36 -> 0 | AM36: 4
X37: 5 | AE37: =SUM(AC37:AD37) -> 0 | AJ37: =AE37 -> 0 | AL37: =AC37 -> 0 | AM37: 5
X38: 6 | AE38: =SUM(AC38:AD38) -> 0 | AJ38: 0 | AL38: =AC38 -> 0 | AM38: 6
X39: 7 | AE39: =SUM(AC39:AD39) -> 0 | AJ39: =AE39 -> 0 | AL39: =AC39 -> 0 | AM39: 7
X40: 8 | AE40: =SUM(AC40:AD40) -> 0 | AJ40: =AE40 -> 0 | AL40: =AC40 -> 0 | AM40: 8
X41: 9 | AE41: =SUM(AC41:AD41) -> 0 | AJ41: =AE41 -> 0 | AL41: =AC41 -> 0 | AM41: 9
X42: 10 | AE42: =SUM(AC42:AD42) -> 0 | AJ42: =AE42 -> 0 | AL42: =AC42 -> 0 | AM42: 10
X43: 11 | AE43: =SUM(AC43:AD43) -> 0 | AJ43: =AE43 -> 0 | AL43: =AC43 -> 0 | AM43: 11
X44: 12 | AE44: =SUM(AC44:AD44) -> 0 | AJ44: =AE44 -> 0 | AL44: =AC44 -> 0 | AM44: 12
X45: 13 | AE45: =SUM(AC45:AD45) -> 0 | AJ45: =AE45 -> 0 | AL45: =AC45 -> 0 | AM45: 13
X46: 14 | AE46: =SUM(AC46:AD46) -> 0 | AJ46: =AE46 -> 0 | AL46: =AC46 -> 0 | AM46: 14
X47: 15 | AE47: =SUM(AC47:AD47) -> 0 | AJ47: =AE47 -> 0 | AL47: =AC47 -> 0 | AM47: 15
X48: 16 | AE48: =SUM(AC48:AD48) -> 0 | AJ48: =AE48 -> 0 | AL48: =AC48 -> 0 | AM48: 16
X49: 17 | AE49: =SUM(AC49:AD49) -> 0 | AJ49: =AE49 -> 0 | AL49: =AC49 -> 0 | AM49: 17
X50: 18 | AE50: =SUM(AC50:AD50) -> 0 | AJ50: =AE50 -> 0 | AL50: =AC50 -> 0 | AM50: 18
... X62: 30 | AE62: =SUM(AC62:AD62) -> 0 | AJ62: =AE62 -> 0 | AL62: =AC62 -> 0 | AM62: 30
AC63: =SUM(AC33:AC62) -> 0 | AH63: TOTAL GENE FEUILLE | AJ63: =SUM(AJ3:AJ62) -> 0 | AL63: =AC63 -> 0
AC64: TVA | AD64: =SUM(AD33:AD63) -> 0
AI66: A PÄYER
AC67: TVA | AD67: =AD30 -> 0 | AJ67: =AJ63 -> 0
AC68: TVA | AD68: =AD64 -> 0 | AI68: mois précèdent | AJ68: ='JANV 2026'!AJ69 -> 0
AC69: TVA RECUP | AD69: =SUM(AD67:AD68) -> 0 | AI69: total a payer | AJ69: =SUM(AJ67:AJ68) -> 0

Sheet AVRIL 2026
A1: 44561 | C1: RECETTE | G1: CAISSE | M1: MOUVEMENT CAISSE | P1: CAISSE MOIS PREC | Q1: PAYEMENT FOURNISSEUR CAISSE | R1: MONTANT | S1: TOTAL | T1: DATE SORTIE | Y1: FOURNISSEUR | Z1: DATE | AA1: REFERENCE | AB1: COMPTE | AC1: HTVA | AD1: TVA | AE1: MONTANT | AF1: PAIEMENT | AG1: CAISSE | AH1: DATE | AI1: ECHEANCE
A2: DATE | B2: FACTURE | C2: 6 | D2: 12 | E2: 21 | F2: TOTAL | G2: CHIFF | H2: carte | I2: cadeau0 | J2: bque | K2: liquide | L2: TOT CAIS | M2: SORTIE | N2: vers ban | O2: solde cai | P2: ='MARS 2026'!P33 -> 250 | AB2: 44651
A3: 44651 | F3: =SUM(B3:E3) -> 0 | G3: =F3 -> 0 | K3: =SUM(F3-H3-J3-I3) -> 0 | L3: =SUM(F3-H3-J3-I3) -> 0 | O3: =SUM(L3-M3-N3+P2) -> 250 | X3: 1 | AE3: =SUM(AC3:AD3) -> 0 | AJ3: 0
A4: 44652 | F4: =SUM(B4:E4) -> 0 | G4: =F4 -> 0 | K4: =SUM(F4-H4-J4-I4) -> 0 | L4: =SUM(F4-H4-J4-I4) -> 0 | O4: =SUM(L4-M4-N4+O3+P4) -> 250 | X4: 2 | AE4: =SUM(AC4:AD4) -> 0 | AJ4: =AE4 -> 0
A5: 44653 | F5: =SUM(B5:E5) -> 0 | G5: =F5 -> 0 | K5: =SUM(F5-H5-J5-I5) -> 0 | L5: =SUM(F5-H5-J5-I5) -> 0 | O5: =SUM(L5-M5-N5+O4+P5) -> 250 | X5: 3 | AE5: =SUM(AC5:AD5) -> 0 | AJ5: 0
A6: 44654 | F6: =SUM(B6:E6) -> 0 | G6: =F6 -> 0 | K6: =SUM(F6-H6-J6-I6) -> 0 | L6: =SUM(F6-H6-J6-I6) -> 0 | O6: =SUM(L6-M6-N6+O5+P6) -> 250 | X6: 4 | AE6: =SUM(AC6:AD6) -> 0 | AJ6: 0
A7: 44655 | F7: =SUM(B7:E7) -> 0 | G7: =F7 -> 0 | K7: =SUM(F7-H7-J7-I7) -> 0 | L7: =SUM(F7-H7-J7-I7) -> 0 | O7: =SUM(L7-M7-N7+O6+P7) -> 250 | X7: 5 | AE7: =SUM(AC7:AD7) -> 0 | AJ7: 0
A8: 44656 | F8: =SUM(B8:E8) -> 0 | G8: =F8 -> 0 | K8: =SUM(F8-H8-J8-I8) -> 0 | L8: =SUM(F8-H8-J8-I8) -> 0 | O8: =SUM(L8-M8-N8+O7+P8) -> 250 | X8: 6 | AE8: =SUM(AC8:AD8) -> 0 | AJ8: 0
A9: 44657 | F9: =SUM(B9:E9) -> 0 | G9: =F9 -> 0 | K9: =SUM(F9-H9-J9-I9) -> 0 | L9: =SUM(F9-H9-J9-I9) -> 0 | O9: =SUM(L9-M9-N9+O8) -> 250 | X9: 7 | AE9: =SUM(AC9:AD9) -> 0 | AJ9: =AE9 -> 0
A10: 44658 | F10: =SUM(B10:E10) -> 0 | G10: =F10 -> 0 | K10: =SUM(F10-H10-J10-I10) -> 0 | L10: =SUM(F10-H10-J10-I10) -> 0 | O10: =SUM(L10-M10-N10+O9) -> 250 | X10: 8 | AE10: =SUM(AC10:AD10) -> 0 | AJ10: =AE10 -> 0
A11: 44659 | F11: =SUM(B11:E11) -> 0 | G11: =F11 -> 0 | K11: =SUM(F11-H11-J11-I11) -> 0 | L11: =SUM(F11-H11-J11-I11) -> 0 | O11: =SUM(L11-M11-N11+O10) -> 250 | X11: 9 | AE11: =SUM(AC11:AD11) -> 0 | AJ11: =AE11 -> 0
A12: 44660 | F12: =SUM(B12:E12) -> 0 | G12: =F12 -> 0 | K12: =SUM(F12-H12-J12-I12) -> 0 | L12: =SUM(F12-H12-J12-I12) -> 0 | O12: =SUM(L12-M12-N12+O11) -> 250 | X12: 10 | AE12: =SUM(AC12:AD12) -> 0 | AJ12: =AE12 -> 0
A13: 44661 | F13: =SUM(B13:E13) -> 0 | G13: =F13 -> 0 | K13: =SUM(F13-H13-J13-I13) -> 0 | L13: =SUM(F13-H13-J13-I13) -> 0 | O13: =SUM(L13-M13-N13+O12) -> 250 | X13: 11 | AE13: =SUM(AC13:AD13) -> 0 | AJ13: =AE13 -> 0
A14: 44662 | F14: =SUM(B14:E14) -> 0 | G14: =F14 -> 0 | K14: =SUM(F14-H14-J14-I14) -> 0 | L14: =SUM(F14-H14-J14-I14) -> 0 | O14: =SUM(L14-M14-N14+O13) -> 250 | X14: 12 | AE14: =SUM(AC14:AD14) -> 0 | AJ14: =AE14 -> 0
A15: 44663 | F15: =SUM(B15:E15) -> 0 | G15: =F15 -> 0 | K15: =SUM(F15-H15-J15-I15) -> 0 | L15: =SUM(F15-H15-J15-I15) -> 0 | O15: =SUM(L15-M15-N15+O14) -> 250 | X15: 13 | AE15: =SUM(AC15:AD15) -> 0 | AJ15: =AE15 -> 0
A16: 44664 | F16: =SUM(B16:E16) -> 0 | G16: =F16 -> 0 | K16: =SUM(F16-H16-J16-I16) -> 0 | L16: =SUM(F16-H16-J16-I16) -> 0 | O16: =SUM(L16-M16-N16+O15) -> 250 | X16: 14 | AE16: =SUM(AC16:AD16) -> 0 | AJ16: =AE16 -> 0
A17: 44665 | F17: =SUM(B17:E17) -> 0 | G17: =F17 -> 0 | K17: =SUM(F17-H17-J17-I17) -> 0 | L17: =SUM(F17-H17-J17-I17) -> 0 | O17: =SUM(L17-M17-N17+O16+P17) -> 250 | X17: 15 | AE17: =SUM(AC17:AD17) -> 0 | AJ17: =AE17 -> 0
A18: 44666 | F18: =SUM(B18:E18) -> 0 | G18: =F18 -> 0 | K18: =SUM(F18-H18-J18-I18) -> 0 | L18: =SUM(F18-H18-J18-I18) -> 0 | O18: =SUM(L18-M18-N18+O17+P18) -> 250 | X18: 16 | AE18: =SUM(AC18:AD18) -> 0 | AJ18: =AE18 -> 0
A19: 44667 | F19: =SUM(B19:E19) -> 0 | G19: =F19 -> 0 | K19: =SUM(F19-H19-J19-I19) -> 0 | L19: =SUM(F19-H19-J19-I19) -> 0 | O19: =SUM(L19-M19-N19+O18+P19) -> 250 | X19: 17 | AE19: =SUM(AC19:AD19) -> 0 | AJ19: =AE19 -> 0
A20: 44668 | F20: =SUM(B20:E20) -> 0 | G20: =F20 -> 0 | K20: =SUM(F20-H20-J20-I20) -> 0 | L20: =SUM(F20-H20-J20-I20) -> 0 | O20: =SUM(L20-M20-N20+O19+P20) -> 250 | X20: 18 | AE20: =SUM(AC20:AD20) -> 0 | AJ20: =AE20 -> 0
A21: 44669 | F21: =SUM(B21:E21) -> 0 | G21: =F21 -> 0 | K21: =SUM(F21-H21-J21-I21) -> 0 | L21: =SUM(F21-H21-J21-I21) -> 0 | O21: =SUM(L21-M21-N21+O20) -> 250 | X21: 19 | AE21: =SUM(AC21:AD21) -> 0 | AJ21: =AE21 -> 0
A22: 44670 | F22: =SUM(B22:E22) -> 0 | G22: =F22 -> 0 | K22: =SUM(F22-H22-J22-I22) -> 0 | L22: =SUM(F22-H22-J22-I22) -> 0 | O22: =SUM(L22-M22-N22+O21) -> 250 | X22: 20 | AE22: =SUM(AC22:AD22) -> 0 | AJ22: =AE22 -> 0
A23: 44671 | F23: =SUM(B23:E23) -> 0 | G23: =F23 -> 0 | K23: =SUM(F23-H23-J23-I23) -> 0 | L23: =SUM(F23-H23-J23-I23) -> 0 | O23: =SUM(L23-M23-N23+O22) -> 250 | X23: 21 | AE23: =SUM(AC23:AD23) -> 0 | AJ23: =AE23 -> 0
A24: 44672 | F24: =SUM(B24:E24) -> 0 | G24: =F24 -> 0 | K24: =SUM(F24-H24-J24-I24) -> 0 | L24: =SUM(F24-H24-J24-I24) -> 0 | O24: =SUM(L24-M24-N24+O23+P24) -> 250 | X24: 22 | AE24: =SUM(AC24:AD24) -> 0 | AJ24: =AE24 -> 0
A25: 44673 | F25: =SUM(B25:E25) -> 0 | G25: =F25 -> 0 | K25: =SUM(F25-H25-J25-I25) -> 0 | L25: =SUM(F25-H25-J25-I25) -> 0 | O25: =SUM(L25-M25-N25+O24) -> 250 | X25: 26 | AE25: =SUM(AC25:AD25) -> 0 | AJ25: =AE25 -> 0
A26: 44674 | F26: =SUM(B26:E26) -> 0 | G26: =F26 -> 0 | K26: =SUM(F26-H26-J26-I26) -> 0 | L26: =SUM(F26-H26-J26-I26) -> 0 | O26: =SUM(L26-M26-N26+O25) -> 250 | X26: 27 | AE26: =SUM(AC26:AD26) -> 0 | AJ26: =AE26 -> 0
A27: 44675 | F27: =SUM(B27:E27) -> 0 | G27: =F27 -> 0 | K27: =SUM(F27-H27-J27-I27) -> 0 | L27: =SUM(F27-H27-J27-I27) -> 0 | O27: =SUM(L27-M27-N27+O26) -> 250 | X27: 28 | AE27: =SUM(AC27:AD27) -> 0 | AJ27: =AE27 -> 0
A28: 44676 | F28: =SUM(B28:E28) -> 0 | G28: =F28 -> 0 | K28: =SUM(F28-H28-J28-I28) -> 0 | L28: =SUM(F28-H28-J28-I28) -> 0 | O28: =SUM(L28-M28-N28+O27+P28) -> 250 | X28: 29 | AE28: =SUM(AC28:AD28) -> 0 | AJ28: =AE28 -> 0
A29: 44677 | F29: =SUM(B29:E29) -> 0 | G29: =F29 -> 0 | K29: =SUM(F29-H29-J29-I29) -> 0 | L29: =SUM(F29-H29-J29-I29) -> 0 | O29: =SUM(L29-M29-N29+O28) -> 250 | X29: 30 | AE29: =SUM(AC29:AD29) -> 0 | AJ29: =AE29 -> 0
A30: 44678 | F30: =SUM(B30:E30) -> 0 | G30: =F30 -> 0 | K30: =SUM(F30-H30-J30-I30) -> 0 | L30: =SUM(F30-H30-J30-I30) -> 0 | O30: =SUM(L30-M30-N30+O29+P30) -> 250 | AC30: TVA | AD30: =SUM(AD3:AD29) -> 0
A31: 44679 | F31: =SUM(B31:E31) -> 0 | G31: =F31 -> 0 | K31: =SUM(F31-H31-J31-I31) -> 0 | L31: =SUM(F31-H31-J31-I31) -> 0 | O31: =SUM(L31-M31-N31+O30) -> 250 | P31: SOLDE CAISSE
A32: 44680 | F32: =SUM(B32:E32) -> 0 | G32: =F32 -> 0 | K32: =SUM(F32-H32-J32-I32) -> 0 | L32: =SUM(F32-H32-J32-I32) -> 0 | O32: =SUM(L32-M32-N32+O31) -> 250 | P32: DU MOIS | AA32: MARGE | AL32: calcul de marge
F33: =SUM(B33:E33) -> 0 | G33: =F33 -> 0 | K33: =SUM(F33-H33-J33-I33) -> 0 | L33: =SUM(F33-H33-J33-I33) -> 0 | O33: =SUM(L33-M33-N33+O32) -> 250 | P33: =SUM(O33) -> 250 | X33: 1 | AE33: =SUM(AC33:AD33) -> 0 | AJ33: =AE33 -> 0 | AL33: =AC33 -> 0 | AM33: 1
B34: =SUM(B5:B33) -> 0 | C34: =SUM(C3:C33) -> 0 | D34: =SUM(D3:D33) -> 0 | E34: =SUM(E3:E33) -> 0 | F34: =SUM(F3:F33) -> 0 | H34: =SUM(H3:H33) -> 0 | J34: =SUM(J3:J33) -> 0 | K34: =SUM(K3:K33) -> 0 | L34: =SUM(L3:L33) -> 0 | M34: =SUM(M3:M33) -> 0 | N34: =SUM(N3:N33) -> 0 | X34: 2 | AE34: =SUM(AC34:AD34) -> 0 | AJ34: =AE34 -> 0 | AL34: =AC34 -> 0 | AM34: 2
A35: HTVA | B35: =SUM(B3:B33) -> 0 | C35: =SUM(C34/1.06) -> 0 | D35: =SUM(D34/1.12) -> 0 | E35: =SUM(E34/1.21) -> 0 | F35: =SUM(B35:E35) -> 0 | G35: =SUM(G34:G34) -> 0 | L35: TOTAL SORTIE | N35: =SUM(M34:N34) -> 0 | X35: 3 | AE35: =SUM(AC35:AD35) -> 0 | AJ35: =AE35 -> 0 | AL35: =AC35 -> 0 | AM35: 3
A36: TVA | C36: =SUM(C34-C35) -> 0 | D36: =SUM(D34-D35) -> 0 | E36: =SUM(E34-E35) -> 0 | F36: =SUM(C36:E36) -> 0 | X36: 4 | AE36: =SUM(AC36:AD36) -> 0 | AJ36: 0 | AL36: =AC36 -> 0 | AM36: 4
X37: 5 | AE37: =SUM(AC37:AD37) -> 0 | AJ37: =AE37 -> 0 | AL37: =AC37 -> 0 | AM37: 5
X38: 6 | AE38: =SUM(AC38:AD38) -> 0 | AJ38: 0 | AL38: =AC38 -> 0 | AM38: 6
X39: 7 | AE39: =SUM(AC39:AD39) -> 0 | AJ39: =AE39 -> 0 | AL39: =AC39 -> 0 | AM39: 7
X40: 8 | AE40: =SUM(AC40:AD40) -> 0 | AJ40: =AE40 -> 0 | AL40: =AC40 -> 0 | AM40: 8
X41: 9 | AE41: =SUM(AC41:AD41) -> 0 | AJ41: =AE41 -> 0 | AL41: =AC41 -> 0 | AM41: 9
X42: 10 | AE42: =SUM(AC42:AD42) -> 0 | AJ42: =AE42 -> 0 | AL42: =AC42 -> 0 | AM42: 10
X43: 11 | AE43: =SUM(AC43:AD43) -> 0 | AJ43: =AE43 -> 0 | AL43: =AC43 -> 0 | AM43: 11
X44: 12 | AE44: =SUM(AC44:AD44) -> 0 | AJ44: =AE44 -> 0 | AL44: =AC44 -> 0 | AM44: 12
X45: 13 | AE45: =SUM(AC45:AD45) -> 0 | AJ45: =AE45 -> 0 | AL45: =AC45 -> 0 | AM45: 13
X46: 14 | AE46: =SUM(AC46:AD46) -> 0 | AJ46: =AE46 -> 0 | AL46: =AC46 -> 0 | AM46: 14
X47: 15 | AE47: =SUM(AC47:AD47) -> 0 | AJ47: =AE47 -> 0 | AL47: =AC47 -> 0 | AM47: 15
X48: 16 | AE48: =SUM(AC48:AD48) -> 0 | AJ48: =AE48 -> 0 | AL48: =AC48 -> 0 | AM48: 16
X49: 17 | AE49: =SUM(AC49:AD49) -> 0 | AJ49: =AE49 -> 0 | AL49: =AC49 -> 0 | AM49: 17
X50: 18 | AE50: =SUM(AC50:AD50) -> 0 | AJ50: =AE50 -> 0 | AL50: =AC50 -> 0 | AM50: 18
... X62: 30 | AE62: =SUM(AC62:AD62) -> 0 | AJ62: =AE62 -> 0 | AL62: =AC62 -> 0 | AM62: 30
AC63: =SUM(AC33:AC62) -> 0 | AH63: TOTAL GENE FEUILLE | AJ63: =SUM(AJ3:AJ62) -> 0 | AL63: =AC63 -> 0
AC64: TVA | AD64: =SUM(AD33:AD63) -> 0
AI66: A PÄYER
AC67: TVA | AD67: =AD30 -> 0 | AJ67: =AJ63 -> 0
AC68: TVA | AD68: =AD64 -> 0 | AI68: mois précèdent | AJ68: ='JANV 2026'!AJ69 -> 0
AC69: TVA RECUP | AD69: =SUM(AD67:AD68) -> 0 | AI69: total a payer | AJ69: =SUM(AJ67:AJ68) -> 0

Sheet MARS 2026
A1: 44561 | C1: RECETTE | G1: CAISSE | M1: MOUVEMENT CAISSE | P1: CAISSE MOIS PREC | Q1: PAYEMENT FOURNISSEUR CAISSE | R1: MONTANT | S1: TOTAL | T1: DATE SORTIE | Y1: FOURNISSEUR | Z1: DATE | AA1: REFERENCE | AB1: COMPTE | AC1: HTVA | AD1: TVA | AE1: MONTANT | AF1: PAIEMENT | AG1: CAISSE | AH1: DATE | AI1: ECHEANCE
A2: DATE | B2: FACTURE | C2: 6 | D2: 12 | E2: 21 | F2: TOTAL | G2: CHIFF | H2: carte | I2: cadeau0 | J2: bque | K2: liquide | L2: TOT CAIS | M2: SORTIE | N2: vers ban | O2: solde cai | P2: ='FEVRIER 2026'!P33 -> 250 | AB2: 46082
A3: 44620 | F3: =SUM(B3:E3) -> 0 | G3: =F3 -> 0 | K3: =SUM(F3-H3-J3-I3) -> 0 | L3: =SUM(F3-H3-J3-I3) -> 0 | O3: =SUM(L3-M3-N3+P2) -> 250 | X3: 1 | AE3: =SUM(AC3:AD3) -> 0 | AJ3: 0
A4: 44621 | F4: =SUM(B4:E4) -> 0 | G4: =F4 -> 0 | K4: =SUM(F4-H4-J4-I4) -> 0 | L4: =SUM(F4-H4-J4-I4) -> 0 | O4: =SUM(L4-M4-N4+O3+P4) -> 250 | X4: 2 | AE4: =SUM(AC4:AD4) -> 0 | AJ4: =AE4 -> 0
A5: 44622 | F5: =SUM(B5:E5) -> 0 | G5: =F5 -> 0 | K5: =SUM(F5-H5-J5-I5) -> 0 | L5: =SUM(F5-H5-J5-I5) -> 0 | O5: =SUM(L5-M5-N5+O4+P5) -> 250 | X5: 3 | AE5: =SUM(AC5:AD5) -> 0 | AJ5: 0
A6: 44623 | F6: =SUM(B6:E6) -> 0 | G6: =F6 -> 0 | K6: =SUM(F6-H6-J6-I6) -> 0 | L6: =SUM(F6-H6-J6-I6) -> 0 | O6: =SUM(L6-M6-N6+O5+P6) -> 250 | X6: 4 | AE6: =SUM(AC6:AD6) -> 0 | AJ6: 0
A7: 44624 | F7: =SUM(B7:E7) -> 0 | G7: =F7 -> 0 | K7: =SUM(F7-H7-J7-I7) -> 0 | L7: =SUM(F7-H7-J7-I7) -> 0 | O7: =SUM(L7-M7-N7+O6+P7) -> 250 | X7: 5 | AE7: =SUM(AC7:AD7) -> 0 | AJ7: 0
A8: 44625 | F8: =SUM(B8:E8) -> 0 | G8: =F8 -> 0 | K8: =SUM(F8-H8-J8-I8) -> 0 | L8: =SUM(F8-H8-J8-I8) -> 0 | O8: =SUM(L8-M8-N8+O7+P8) -> 250 | X8: 6 | AE8: =SUM(AC8:AD8) -> 0 | AJ8: 0
A9: 44626 | F9: =SUM(B9:E9) -> 0 | G9: =F9 -> 0 | K9: =SUM(F9-H9-J9-I9) -> 0 | L9: =SUM(F9-H9-J9-I9) -> 0 | O9: =SUM(L9-M9-N9+O8) -> 250 | X9: 7 | AE9: =SUM(AC9:AD9) -> 0 | AJ9: =AE9 -> 0
A10: 44627 | F10: =SUM(B10:E10) -> 0 | G10: =F10 -> 0 | K10: =SUM(F10-H10-J10-I10) -> 0 | L10: =SUM(F10-H10-J10-I10) -> 0 | O10: =SUM(L10-M10-N10+O9) -> 250 | X10: 8 | AE10: =SUM(AC10:AD10) -> 0 | AJ10: =AE10 -> 0
A11: 44628 | F11: =SUM(B11:E11) -> 0 | G11: =F11 -> 0 | K11: =SUM(F11-H11-J11-I11) -> 0 | L11: =SUM(F11-H11-J11-I11) -> 0 | O11: =SUM(L11-M11-N11+O10) -> 250 | X11: 9 | AE11: =SUM(AC11:AD11) -> 0 | AJ11: =AE11 -> 0
A12: 44629 | F12: =SUM(B12:E12) -> 0 | G12: =F12 -> 0 | K12: =SUM(F12-H12-J12-I12) -> 0 | L12: =SUM(F12-H12-J12-I12) -> 0 | O12: =SUM(L12-M12-N12+O11) -> 250 | X12: 10 | AE12: =SUM(AC12:AD12) -> 0 | AJ12: =AE12 -> 0
A13: 44630 | F13: =SUM(B13:E13) -> 0 | G13: =F13 -> 0 | K13: =SUM(F13-H13-J13-I13) -> 0 | L13: =SUM(F13-H13-J13-I13) -> 0 | O13: =SUM(L13-M13-N13+O12) -> 250 | X13: 11 | AE13: =SUM(AC13:AD13) -> 0 | AJ13: =AE13 -> 0
A14: 44631 | F14: =SUM(B14:E14) -> 0 | G14: =F14 -> 0 | K14: =SUM(F14-H14-J14-I14) -> 0 | L14: =SUM(F14-H14-J14-I14) -> 0 | O14: =SUM(L14-M14-N14+O13) -> 250 | X14: 12 | AE14: =SUM(AC14:AD14) -> 0 | AJ14: =AE14 -> 0
A15: 44632 | F15: =SUM(B15:E15) -> 0 | G15: =F15 -> 0 | K15: =SUM(F15-H15-J15-I15) -> 0 | L15: =SUM(F15-H15-J15-I15) -> 0 | O15: =SUM(L15-M15-N15+O14) -> 250 | X15: 13 | AE15: =SUM(AC15:AD15) -> 0 | AJ15: =AE15 -> 0
A16: 44633 | F16: =SUM(B16:E16) -> 0 | G16: =F16 -> 0 | K16: =SUM(F16-H16-J16-I16) -> 0 | L16: =SUM(F16-H16-J16-I16) -> 0 | O16: =SUM(L16-M16-N16+O15) -> 250 | X16: 14 | AE16: =SUM(AC16:AD16) -> 0 | AJ16: =AE16 -> 0
A17: 44634 | F17: =SUM(B17:E17) -> 0 | G17: =F17 -> 0 | K17: =SUM(F17-H17-J17-I17) -> 0 | L17: =SUM(F17-H17-J17-I17) -> 0 | O17: =SUM(L17-M17-N17+O16+P17) -> 250 | X17: 15 | AE17: =SUM(AC17:AD17) -> 0 | AJ17: =AE17 -> 0
A18: 44635 | F18: =SUM(B18:E18) -> 0 | G18: =F18 -> 0 | K18: =SUM(F18-H18-J18-I18) -> 0 | L18: =SUM(F18-H18-J18-I18) -> 0 | O18: =SUM(L18-M18-N18+O17+P18) -> 250 | X18: 16 | AE18: =SUM(AC18:AD18) -> 0 | AJ18: =AE18 -> 0
A19: 44636 | F19: =SUM(B19:E19) -> 0 | G19: =F19 -> 0 | K19: =SUM(F19-H19-J19-I19) -> 0 | L19: =SUM(F19-H19-J19-I19) -> 0 | O19: =SUM(L19-M19-N19+O18+P19) -> 250 | X19: 17 | AE19: =SUM(AC19:AD19) -> 0 | AJ19: =AE19 -> 0
A20: 44637 | F20: =SUM(B20:E20) -> 0 | G20: =F20 -> 0 | K20: =SUM(F20-H20-J20-I20) -> 0 | L20: =SUM(F20-H20-J20-I20) -> 0 | O20: =SUM(L20-M20-N20+O19+P20) -> 250 | X20: 18 | AE20: =SUM(AC20:AD20) -> 0 | AJ20: =AE20 -> 0
A21: 44638 | F21: =SUM(B21:E21) -> 0 | G21: =F21 -> 0 | K21: =SUM(F21-H21-J21-I21) -> 0 | L21: =SUM(F21-H21-J21-I21) -> 0 | O21: =SUM(L21-M21-N21+O20) -> 250 | X21: 19 | AE21: =SUM(AC21:AD21) -> 0 | AJ21: =AE21 -> 0
A22: 44639 | F22: =SUM(B22:E22) -> 0 | G22: =F22 -> 0 | K22: =SUM(F22-H22-J22-I22) -> 0 | L22: =SUM(F22-H22-J22-I22) -> 0 | O22: =SUM(L22-M22-N22+O21) -> 250 | X22: 20 | AE22: =SUM(AC22:AD22) -> 0 | AJ22: =AE22 -> 0
A23: 44640 | F23: =SUM(B23:E23) -> 0 | G23: =F23 -> 0 | K23: =SUM(F23-H23-J23-I23) -> 0 | L23: =SUM(F23-H23-J23-I23) -> 0 | O23: =SUM(L23-M23-N23+O22) -> 250 | X23: 21 | AE23: =SUM(AC23:AD23) -> 0 | AJ23: =AE23 -> 0
A24: 44641 | F24: =SUM(B24:E24) -> 0 | G24: =F24 -> 0 | K24: =SUM(F24-H24-J24-I24) -> 0 | L24: =SUM(F24-H24-J24-I24) -> 0 | O24: =SUM(L24-M24-N24+O23+P24) -> 250 | X24: 22 | AE24: =SUM(AC24:AD24) -> 0 | AJ24: =AE24 -> 0
A25: 44642 | F25: =SUM(B25:E25) -> 0 | G25: =F25 -> 0 | K25: =SUM(F25-H25-J25-I25) -> 0 | L25: =SUM(F25-H25-J25-I25) -> 0 | O25: =SUM(L25-M25-N25+O24) -> 250 | X25: 26 | AE25: =SUM(AC25:AD25) -> 0 | AJ25: =AE25 -> 0
A26: 44643 | F26: =SUM(B26:E26) -> 0 | G26: =F26 -> 0 | K26: =SUM(F26-H26-J26-I26) -> 0 | L26: =SUM(F26-H26-J26-I26) -> 0 | O26: =SUM(L26-M26-N26+O25) -> 250 | X26: 27 | AE26: =SUM(AC26:AD26) -> 0 | AJ26: =AE26 -> 0
A27: 44644 | F27: =SUM(B27:E27) -> 0 | G27: =F27 -> 0 | K27: =SUM(F27-H27-J27-I27) -> 0 | L27: =SUM(F27-H27-J27-I27) -> 0 | O27: =SUM(L27-M27-N27+O26) -> 250 | X27: 28 | AE27: =SUM(AC27:AD27) -> 0 | AJ27: =AE27 -> 0
A28: 44645 | F28: =SUM(B28:E28) -> 0 | G28: =F28 -> 0 | K28: =SUM(F28-H28-J28-I28) -> 0 | L28: =SUM(F28-H28-J28-I28) -> 0 | O28: =SUM(L28-M28-N28+O27+P28) -> 250 | X28: 29 | AE28: =SUM(AC28:AD28) -> 0 | AJ28: =AE28 -> 0
A29: 44646 | F29: =SUM(B29:E29) -> 0 | G29: =F29 -> 0 | K29: =SUM(F29-H29-J29-I29) -> 0 | L29: =SUM(F29-H29-J29-I29) -> 0 | O29: =SUM(L29-M29-N29+O28) -> 250 | X29: 30 | AE29: =SUM(AC29:AD29) -> 0 | AJ29: =AE29 -> 0
A30: 44647 | F30: =SUM(B30:E30) -> 0 | G30: =F30 -> 0 | K30: =SUM(F30-H30-J30-I30) -> 0 | L30: =SUM(F30-H30-J30-I30) -> 0 | O30: =SUM(L30-M30-N30+O29+P30) -> 250 | AC30: TVA | AD30: =SUM(AD3:AD29) -> 0
A31: 44648 | F31: =SUM(B31:E31) -> 0 | G31: =F31 -> 0 | K31: =SUM(F31-H31-J31-I31) -> 0 | L31: =SUM(F31-H31-J31-I31) -> 0 | O31: =SUM(L31-M31-N31+O30) -> 250 | P31: SOLDE CAISSE
A32: 44649 | F32: =SUM(B32:E32) -> 0 | G32: =F32 -> 0 | K32: =SUM(F32-H32-J32-I32) -> 0 | L32: =SUM(F32-H32-J32-I32) -> 0 | O32: =SUM(L32-M32-N32+O31) -> 250 | P32: DU MOIS | AA32: MARGE | AL32: calcul de marge
A33: 44650 | F33: =SUM(B33:E33) -> 0 | G33: =F33 -> 0 | K33: =SUM(F33-H33-J33-I33) -> 0 | L33: =SUM(F33-H33-J33-I33) -> 0 | O33: =SUM(L33-M33-N33+O32) -> 250 | P33: =SUM(O33) -> 250 | X33: 1 | AE33: =SUM(AC33:AD33) -> 0 | AJ33: =AE33 -> 0 | AL33: =AC33 -> 0 | AM33: 1
B34: =SUM(B5:B33) -> 0 | C34: =SUM(C3:C33) -> 0 | D34: =SUM(D3:D33) -> 0 | E34: =SUM(E3:E33) -> 0 | F34: =SUM(F3:F33) -> 0 | H34: =SUM(H3:H33) -> 0 | J34: =SUM(J3:J33) -> 0 | K34: =SUM(K3:K33) -> 0 | L34: =SUM(L3:L33) -> 0 | M34: =SUM(M3:M33) -> 0 | N34: =SUM(N3:N33) -> 0 | X34: 2 | AE34: =SUM(AC34:AD34) -> 0 | AJ34: =AE34 -> 0 | AL34: =AC34 -> 0 | AM34: 2
A35: HTVA | B35: =SUM(B3:B33) -> 0 | C35: =SUM(C34/1.06) -> 0 | D35: =SUM(D34/1.12) -> 0 | E35: =SUM(E34/1.21) -> 0 | F35: =SUM(B35:E35) -> 0 | G35: =SUM(G34:G34) -> 0 | L35: TOTAL SORTIE | N35: =SUM(M34:N34) -> 0 | X35: 3 | AE35: =SUM(AC35:AD35) -> 0 | AJ35: =AE35 -> 0 | AL35: =AC35 -> 0 | AM35: 3
A36: TVA | C36: =SUM(C34-C35) -> 0 | D36: =SUM(D34-D35) -> 0 | E36: =SUM(E34-E35) -> 0 | F36: =SUM(C36:E36) -> 0 | X36: 4 | AE36: =SUM(AC36:AD36) -> 0 | AJ36: 0 | AL36: =AC36 -> 0 | AM36: 4
X37: 5 | AE37: =SUM(AC37:AD37) -> 0 | AJ37: =AE37 -> 0 | AL37: =AC37 -> 0 | AM37: 5
X38: 6 | AE38: =SUM(AC38:AD38) -> 0 | AJ38: 0 | AL38: =AC38 -> 0 | AM38: 6
X39: 7 | AE39: =SUM(AC39:AD39) -> 0 | AJ39: =AE39 -> 0 | AL39: =AC39 -> 0 | AM39: 7
X40: 8 | AE40: =SUM(AC40:AD40) -> 0 | AJ40: =AE40 -> 0 | AL40: =AC40 -> 0 | AM40: 8
X41: 9 | AE41: =SUM(AC41:AD41) -> 0 | AJ41: =AE41 -> 0 | AL41: =AC41 -> 0 | AM41: 9
X42: 10 | AE42: =SUM(AC42:AD42) -> 0 | AJ42: =AE42 -> 0 | AL42: =AC42 -> 0 | AM42: 10
X43: 11 | AE43: =SUM(AC43:AD43) -> 0 | AJ43: =AE43 -> 0 | AL43: =AC43 -> 0 | AM43: 11
X44: 12 | AE44: =SUM(AC44:AD44) -> 0 | AJ44: =AE44 -> 0 | AL44: =AC44 -> 0 | AM44: 12
X45: 13 | AE45: =SUM(AC45:AD45) -> 0 | AJ45: =AE45 -> 0 | AL45: =AC45 -> 0 | AM45: 13
X46: 14 | AE46: =SUM(AC46:AD46) -> 0 | AJ46: =AE46 -> 0 | AL46: =AC46 -> 0 | AM46: 14
X47: 15 | AE47: =SUM(AC47:AD47) -> 0 | AJ47: =AE47 -> 0 | AL47: =AC47 -> 0 | AM47: 15
X48: 16 | AE48: =SUM(AC48:AD48) -> 0 | AJ48: =AE48 -> 0 | AL48: =AC48 -> 0 | AM48: 16
X49: 17 | AE49: =SUM(AC49:AD49) -> 0 | AJ49: =AE49 -> 0 | AL49: =AC49 -> 0 | AM49: 17
X50: 18 | AE50: =SUM(AC50:AD50) -> 0 | AJ50: =AE50 -> 0 | AL50: =AC50 -> 0 | AM50: 18
... X62: 30 | AE62: =SUM(AC62:AD62) -> 0 | AJ62: =AE62 -> 0 | AL62: =AC62 -> 0 | AM62: 30
AC63: =SUM(AC33:AC62) -> 0 | AH63: TOTAL GENE FEUILLE | AJ63: =SUM(AJ3:AJ62) -> 0 | AL63: =AC63 -> 0
AC64: TVA | AD64: =SUM(AD33:AD63) -> 0
AI66: A PÄYER
AC67: TVA | AD67: =AD30 -> 0 | AJ67: =AJ63 -> 0
AC68: TVA | AD68: =AD64 -> 0 | AI68: mois précèdent | AJ68: ='JANV 2026'!AJ69 -> 0
AC69: TVA RECUP | AD69: =SUM(AD67:AD68) -> 0 | AI69: total a payer | AJ69: =SUM(AJ67:AJ68) -> 0

Sheet FEVRIER 2026
A1: 44561 | C1: RECETTE | G1: CAISSE | M1: MOUVEMENT CAISSE | P1: CAISSE MOIS PREC | Q1: PAYEMENT FOURNISSEUR CAISSE | R1: MONTANT | S1: TOTAL | T1: DATE SORTIE | Y1: FOURNISSEUR | Z1: DATE | AA1: REFERENCE | AB1: COMPTE | AC1: HTVA | AD1: TVA | AE1: MONTANT | AF1: PAIEMENT | AG1: CAISSE | AH1: DATE | AI1: ECHEANCE
A2: DATE | B2: FACTURE | C2: 6 | D2: 12 | E2: 21 | F2: TOTAL | G2: CHIFF | H2: carte | I2: cadeau0 | J2: bque | K2: liquide | L2: TOT CAIS | M2: SORTIE | N2: vers ban | O2: solde cai | P2: ='JANV 2026'!P33 -> 250 | AB2: 44592
A3: 44592 | F3: =SUM(B3:E3) -> 0 | G3: =F3 -> 0 | K3: =SUM(F3-H3-J3-I3) -> 0 | L3: =SUM(F3-H3-J3-I3) -> 0 | O3: =SUM(L3-M3-N3+P2) -> 250 | X3: 1 | AE3: =SUM(AC3:AD3) -> 0 | AJ3: 0
A4: 44593 | F4: =SUM(B4:E4) -> 0 | G4: =F4 -> 0 | K4: =SUM(F4-H4-J4-I4) -> 0 | L4: =SUM(F4-H4-J4-I4) -> 0 | O4: =SUM(L4-M4-N4+O3+P4) -> 250 | X4: 2 | AE4: =SUM(AC4:AD4) -> 0 | AJ4: =AE4 -> 0
A5: 44594 | F5: =SUM(B5:E5) -> 0 | G5: =F5 -> 0 | K5: =SUM(F5-H5-J5-I5) -> 0 | L5: =SUM(F5-H5-J5-I5) -> 0 | O5: =SUM(L5-M5-N5+O4+P5) -> 250 | X5: 3 | AE5: =SUM(AC5:AD5) -> 0 | AJ5: 0
A6: 44595 | F6: =SUM(B6:E6) -> 0 | G6: =F6 -> 0 | K6: =SUM(F6-H6-J6-I6) -> 0 | L6: =SUM(F6-H6-J6-I6) -> 0 | O6: =SUM(L6-M6-N6+O5+P6) -> 250 | X6: 4 | AE6: =SUM(AC6:AD6) -> 0 | AJ6: 0
A7: 44596 | F7: =SUM(B7:E7) -> 0 | G7: =F7 -> 0 | K7: =SUM(F7-H7-J7-I7) -> 0 | L7: =SUM(F7-H7-J7-I7) -> 0 | O7: =SUM(L7-M7-N7+O6+P7) -> 250 | X7: 5 | AE7: =SUM(AC7:AD7) -> 0 | AJ7: 0
A8: 44597 | F8: =SUM(B8:E8) -> 0 | G8: =F8 -> 0 | K8: =SUM(F8-H8-J8-I8) -> 0 | L8: =SUM(F8-H8-J8-I8) -> 0 | O8: =SUM(L8-M8-N8+O7+P8) -> 250 | X8: 6 | AE8: =SUM(AC8:AD8) -> 0 | AJ8: 0
A9: 44598 | F9: =SUM(B9:E9) -> 0 | G9: =F9 -> 0 | K9: =SUM(F9-H9-J9-I9) -> 0 | L9: =SUM(F9-H9-J9-I9) -> 0 | O9: =SUM(L9-M9-N9+O8) -> 250 | X9: 7 | AE9: =SUM(AC9:AD9) -> 0 | AJ9: =AE9 -> 0
A10: 44599 | F10: =SUM(B10:E10) -> 0 | G10: =F10 -> 0 | K10: =SUM(F10-H10-J10-I10) -> 0 | L10: =SUM(F10-H10-J10-I10) -> 0 | O10: =SUM(L10-M10-N10+O9) -> 250 | X10: 8 | AE10: =SUM(AC10:AD10) -> 0 | AJ10: =AE10 -> 0
A11: 44600 | F11: =SUM(B11:E11) -> 0 | G11: =F11 -> 0 | K11: =SUM(F11-H11-J11-I11) -> 0 | L11: =SUM(F11-H11-J11-I11) -> 0 | O11: =SUM(L11-M11-N11+O10) -> 250 | X11: 9 | AE11: =SUM(AC11:AD11) -> 0 | AJ11: =AE11 -> 0
A12: 44601 | F12: =SUM(B12:E12) -> 0 | G12: =F12 -> 0 | K12: =SUM(F12-H12-J12-I12) -> 0 | L12: =SUM(F12-H12-J12-I12) -> 0 | O12: =SUM(L12-M12-N12+O11) -> 250 | X12: 10 | AE12: =SUM(AC12:AD12) -> 0 | AJ12: =AE12 -> 0
A13: 44602 | F13: =SUM(B13:E13) -> 0 | G13: =F13 -> 0 | K13: =SUM(F13-H13-J13-I13) -> 0 | L13: =SUM(F13-H13-J13-I13) -> 0 | O13: =SUM(L13-M13-N13+O12) -> 250 | X13: 11 | AE13: =SUM(AC13:AD13) -> 0 | AJ13: =AE13 -> 0
A14: 44603 | F14: =SUM(B14:E14) -> 0 | G14: =F14 -> 0 | K14: =SUM(F14-H14-J14-I14) -> 0 | L14: =SUM(F14-H14-J14-I14) -> 0 | O14: =SUM(L14-M14-N14+O13) -> 250 | X14: 12 | AE14: =SUM(AC14:AD14) -> 0 | AJ14: =AE14 -> 0
A15: 44604 | F15: =SUM(B15:E15) -> 0 | G15: =F15 -> 0 | K15: =SUM(F15-H15-J15-I15) -> 0 | L15: =SUM(F15-H15-J15-I15) -> 0 | O15: =SUM(L15-M15-N15+O14) -> 250 | X15: 13 | AE15: =SUM(AC15:AD15) -> 0 | AJ15: =AE15 -> 0
A16: 44605 | F16: =SUM(B16:E16) -> 0 | G16: =F16 -> 0 | K16: =SUM(F16-H16-J16-I16) -> 0 | L16: =SUM(F16-H16-J16-I16) -> 0 | O16: =SUM(L16-M16-N16+O15) -> 250 | X16: 14 | AE16: =SUM(AC16:AD16) -> 0 | AJ16: =AE16 -> 0
A17: 44606 | F17: =SUM(B17:E17) -> 0 | G17: =F17 -> 0 | K17: =SUM(F17-H17-J17-I17) -> 0 | L17: =SUM(F17-H17-J17-I17) -> 0 | O17: =SUM(L17-M17-N17+O16+P17) -> 250 | X17: 15 | AE17: =SUM(AC17:AD17) -> 0 | AJ17: =AE17 -> 0
A18: 44607 | F18: =SUM(B18:E18) -> 0 | G18: =F18 -> 0 | K18: =SUM(F18-H18-J18-I18) -> 0 | L18: =SUM(F18-H18-J18-I18) -> 0 | O18: =SUM(L18-M18-N18+O17+P18) -> 250 | X18: 16 | AE18: =SUM(AC18:AD18) -> 0 | AJ18: =AE18 -> 0
A19: 44608 | F19: =SUM(B19:E19) -> 0 | G19: =F19 -> 0 | K19: =SUM(F19-H19-J19-I19) -> 0 | L19: =SUM(F19-H19-J19-I19) -> 0 | O19: =SUM(L19-M19-N19+O18+P19) -> 250 | X19: 17 | AE19: =SUM(AC19:AD19) -> 0 | AJ19: =AE19 -> 0
A20: 44609 | F20: =SUM(B20:E20) -> 0 | G20: =F20 -> 0 | K20: =SUM(F20-H20-J20-I20) -> 0 | L20: =SUM(F20-H20-J20-I20) -> 0 | O20: =SUM(L20-M20-N20+O19+P20) -> 250 | X20: 18 | AE20: =SUM(AC20:AD20) -> 0 | AJ20: =AE20 -> 0
A21: 44610 | F21: =SUM(B21:E21) -> 0 | G21: =F21 -> 0 | K21: =SUM(F21-H21-J21-I21) -> 0 | L21: =SUM(F21-H21-J21-I21) -> 0 | O21: =SUM(L21-M21-N21+O20) -> 250 | X21: 19 | AE21: =SUM(AC21:AD21) -> 0 | AJ21: =AE21 -> 0
A22: 44611 | F22: =SUM(B22:E22) -> 0 | G22: =F22 -> 0 | K22: =SUM(F22-H22-J22-I22) -> 0 | L22: =SUM(F22-H22-J22-I22) -> 0 | O22: =SUM(L22-M22-N22+O21) -> 250 | X22: 20 | AE22: =SUM(AC22:AD22) -> 0 | AJ22: =AE22 -> 0
A23: 44612 | F23: =SUM(B23:E23) -> 0 | G23: =F23 -> 0 | K23: =SUM(F23-H23-J23-I23) -> 0 | L23: =SUM(F23-H23-J23-I23) -> 0 | O23: =SUM(L23-M23-N23+O22) -> 250 | X23: 21 | AE23: =SUM(AC23:AD23) -> 0 | AJ23: =AE23 -> 0
A24: 44613 | F24: =SUM(B24:E24) -> 0 | G24: =F24 -> 0 | K24: =SUM(F24-H24-J24-I24) -> 0 | L24: =SUM(F24-H24-J24-I24) -> 0 | O24: =SUM(L24-M24-N24+O23+P24) -> 250 | X24: 22 | AE24: =SUM(AC24:AD24) -> 0 | AJ24: =AE24 -> 0
A25: 44614 | F25: =SUM(B25:E25) -> 0 | G25: =F25 -> 0 | K25: =SUM(F25-H25-J25-I25) -> 0 | L25: =SUM(F25-H25-J25-I25) -> 0 | O25: =SUM(L25-M25-N25+O24) -> 250 | X25: 26 | AE25: =SUM(AC25:AD25) -> 0 | AJ25: =AE25 -> 0
A26: 44615 | F26: =SUM(B26:E26) -> 0 | G26: =F26 -> 0 | K26: =SUM(F26-H26-J26-I26) -> 0 | L26: =SUM(F26-H26-J26-I26) -> 0 | O26: =SUM(L26-M26-N26+O25) -> 250 | X26: 27 | AE26: =SUM(AC26:AD26) -> 0 | AJ26: =AE26 -> 0
A27: 44616 | F27: =SUM(B27:E27) -> 0 | G27: =F27 -> 0 | K27: =SUM(F27-H27-J27-I27) -> 0 | L27: =SUM(F27-H27-J27-I27) -> 0 | O27: =SUM(L27-M27-N27+O26) -> 250 | X27: 28 | AE27: =SUM(AC27:AD27) -> 0 | AJ27: =AE27 -> 0
A28: 44617 | F28: =SUM(B28:E28) -> 0 | G28: =F28 -> 0 | K28: =SUM(F28-H28-J28-I28) -> 0 | L28: =SUM(F28-H28-J28-I28) -> 0 | O28: =SUM(L28-M28-N28+O27+P28) -> 250 | X28: 29 | AE28: =SUM(AC28:AD28) -> 0 | AJ28: =AE28 -> 0
A29: 44618 | F29: =SUM(B29:E29) -> 0 | G29: =F29 -> 0 | K29: =SUM(F29-H29-J29-I29) -> 0 | L29: =SUM(F29-H29-J29-I29) -> 0 | O29: =SUM(L29-M29-N29+O28) -> 250 | X29: 30 | AE29: =SUM(AC29:AD29) -> 0 | AJ29: =AE29 -> 0
A30: 44619 | F30: =SUM(B30:E30) -> 0 | G30: =F30 -> 0 | K30: =SUM(F30-H30-J30-I30) -> 0 | L30: =SUM(F30-H30-J30-I30) -> 0 | O30: =SUM(L30-M30-N30+O29+P30) -> 250 | AC30: TVA | AD30: =SUM(AD3:AD29) -> 0
F31: =SUM(B31:E31) -> 0 | G31: =F31 -> 0 | K31: =SUM(F31-H31-J31-I31) -> 0 | L31: =SUM(F31-H31-J31-I31) -> 0 | O31: =SUM(L31-M31-N31+O30) -> 250 | P31: SOLDE CAISSE
F32: =SUM(B32:E32) -> 0 | G32: =F32 -> 0 | K32: =SUM(F32-H32-J32-I32) -> 0 | L32: =SUM(F32-H32-J32-I32) -> 0 | O32: =SUM(L32-M32-N32+O31) -> 250 | P32: DU MOIS | AA32: MARGE
F33: =SUM(B33:E33) -> 0 | G33: =F33 -> 0 | K33: =SUM(F33-H33-J33-I33) -> 0 | L33: =SUM(F33-H33-J33-I33) -> 0 | O33: =SUM(L33-M33-N33+O32) -> 250 | P33: =SUM(O33) -> 250 | X33: 1 | AE33: =SUM(AC33:AD33) -> 0 | AJ33: =AE33 -> 0 | AL33: calcul de marge
B34: =SUM(B5:B33) -> 0 | C34: =SUM(C3:C33) -> 0 | D34: =SUM(D3:D33) -> 0 | E34: =SUM(E3:E33) -> 0 | F34: =SUM(F3:F33) -> 0 | H34: =SUM(H3:H33) -> 0 | J34: =SUM(J3:J33) -> 0 | K34: =SUM(K3:K33) -> 0 | L34: =SUM(L3:L33) -> 0 | M34: =SUM(M3:M33) -> 0 | N34: =SUM(N3:N33) -> 0 | X34: 2 | AE34: =SUM(AC34:AD34) -> 0 | AJ34: =AE34 -> 0 | AL34: =AC33 -> 0 | AM34: 1
A35: HTVA | B35: =SUM(B3:B33) -> 0 | C35: =SUM(C34/1.06) -> 0 | D35: =SUM(D34/1.12) -> 0 | E35: =SUM(E34/1.21) -> 0 | F35: =SUM(B35:E35) -> 0 | G35: =SUM(G34:G34) -> 0 | L35: TOTAL SORTIE | N35: =SUM(M34:N34) -> 0 | X35: 3 | AE35: =SUM(AC35:AD35) -> 0 | AJ35: =AE35 -> 0 | AL35: =AC34 -> 0 | AM35: 2
A36: TVA | C36: =SUM(C34-C35) -> 0 | D36: =SUM(D34-D35) -> 0 | E36: =SUM(E34-E35) -> 0 | F36: =SUM(C36:E36) -> 0 | X36: 4 | AE36: =SUM(AC36:AD36) -> 0 | AJ36: 0 | AL36: =AC35 -> 0 | AM36: 3
X37: 5 | AE37: =SUM(AC37:AD37) -> 0 | AJ37: =AE37 -> 0 | AL37: =AC36 -> 0 | AM37: 4
X38: 6 | AE38: =SUM(AC38:AD38) -> 0 | AJ38: 0 | AL38: =AC37 -> 0 | AM38: 5
X39: 7 | AE39: =SUM(AC39:AD39) -> 0 | AJ39: =AE39 -> 0 | AL39: =AC38 -> 0 | AM39: 6
X40: 8 | AE40: =SUM(AC40:AD40) -> 0 | AJ40: =AE40 -> 0 | AL40: =AC39 -> 0 | AM40: 7
X41: 9 | AE41: =SUM(AC41:AD41) -> 0 | AJ41: =AE41 -> 0 | AL41: =AC40 -> 0 | AM41: 8
X42: 10 | AE42: =SUM(AC42:AD42) -> 0 | AJ42: =AE42 -> 0 | AL42: =AC41 -> 0 | AM42: 9
X43: 11 | AE43: =SUM(AC43:AD43) -> 0 | AJ43: =AE43 -> 0 | AL43: =AC42 -> 0 | AM43: 10
X44: 12 | AE44: =SUM(AC44:AD44) -> 0 | AJ44: =AE44 -> 0 | AL44: =AC43 -> 0 | AM44: 11
X45: 13 | AE45: =SUM(AC45:AD45) -> 0 | AJ45: =AE45 -> 0 | AL45: =AC44 -> 0 | AM45: 12
X46: 14 | AE46: =SUM(AC46:AD46) -> 0 | AJ46: =AE46 -> 0 | AL46: =AC45 -> 0 | AM46: 13
X47: 15 | AE47: =SUM(AC47:AD47) -> 0 | AJ47: =AE47 -> 0 | AL47: =AC46 -> 0 | AM47: 14
X48: 16 | AE48: =SUM(AC48:AD48) -> 0 | AJ48: =AE48 -> 0 | AL48: =AC47 -> 0 | AM48: 15
X49: 17 | AE49: =SUM(AC49:AD49) -> 0 | AJ49: =AE49 -> 0 | AL49: =AC48 -> 0 | AM49: 16
X50: 18 | AE50: =SUM(AC50:AD50) -> 0 | AJ50: =AE50 -> 0 | AL50: =AC49 -> 0 | AM50: 17
... X62: 30 | AE62: =SUM(AC62:AD62) -> 0 | AJ62: =AE62 -> 0 | AL62: =AC61 -> 0 | AM62: 29
AC63: =SUM(AC33:AC62) -> 0 | AH63: TOTAL GENE FEUILLE | AJ63: =SUM(AJ3:AJ62) -> 0 | AL63: =AC62 -> 0 | AM63: 30
AC64: TVA | AD64: =SUM(AD33:AD63) -> 0 | AL64: =AC63 -> 0
AI66: A PÄYER
AC67: TVA | AD67: =AD30 -> 0 | AJ67: =AJ63 -> 0
AC68: TVA | AD68: =AD64 -> 0 | AI68: mois précèdent | AJ68: ='JANV 2026'!AJ69 -> 0
AC69: TVA RECUP | AD69: =SUM(AD67:AD68) -> 0 | AI69: total a payer | AJ69: =SUM(AJ67:AJ68) -> 0

Sheet JANV 2026
A1: 44561 | C1: RECETTE | G1: CAISSE | M1: MOUVEMENT CAISSE | P1: CAISSE MOIS PREC | Q1: PAYEMENT FOURNISSEUR CAISSE | R1: MONTANT | S1: TOTAL | T1: DATE SORTIE | Y1: FOURNISSEUR | Z1: DATE | AA1: REFERENCE | AB1: COMPTE | AC1: HTVA | AD1: TVA | AE1: MONTANT | AF1: PAIEMENT | AG1: CAISSE | AH1: DATE | AI1: ECHEANCE
A2: DATE | B2: FACTURE | C2: 6 | D2: 12 | E2: 21 | F2: TOTAL | G2: CHIFF | H2: carte | I2: cadeau0 | J2: bque | K2: liquide | L2: TOT CAIS | M2: SORTIE | N2: vers ban | O2: solde cai | P2: 250 | AB2: 44561
A3: 44561 | F3: =SUM(B3:E3) -> 0 | G3: =F3 -> 0 | K3: =SUM(F3-H3-J3-I3) -> 0 | L3: =SUM(F3-H3-J3-I3) -> 0 | O3: =SUM(L3-M3-N3+P2) -> 250 | X3: 1 | AE3: =SUM(AC3:AD3) -> 0 | AJ3: 0
A4: 44562 | F4: =SUM(B4:E4) -> 0 | G4: =F4 -> 0 | K4: =SUM(F4-H4-J4-I4) -> 0 | L4: =SUM(F4-H4-J4-I4) -> 0 | O4: =SUM(L4-M4-N4+O3+P4) -> 250 | X4: 2 | AE4: =SUM(AC4:AD4) -> 0 | AJ4: =AE4 -> 0
A5: 44563 | F5: =SUM(B5:E5) -> 0 | G5: =F5 -> 0 | K5: =SUM(F5-H5-J5-I5) -> 0 | L5: =SUM(F5-H5-J5-I5) -> 0 | O5: =SUM(L5-M5-N5+O4+P5) -> 250 | X5: 3 | AE5: =SUM(AC5:AD5) -> 0 | AJ5: 0
A6: 44564 | F6: =SUM(B6:E6) -> 0 | G6: =F6 -> 0 | K6: =SUM(F6-H6-J6-I6) -> 0 | L6: =SUM(F6-H6-J6-I6) -> 0 | O6: =SUM(L6-M6-N6+O5+P6) -> 250 | X6: 4 | AE6: =SUM(AC6:AD6) -> 0 | AJ6: 0
A7: 44565 | F7: =SUM(B7:E7) -> 0 | G7: =F7 -> 0 | K7: =SUM(F7-H7-J7-I7) -> 0 | L7: =SUM(F7-H7-J7-I7) -> 0 | O7: =SUM(L7-M7-N7+O6+P7) -> 250 | X7: 5 | AE7: =SUM(AC7:AD7) -> 0 | AJ7: 0
A8: 44566 | F8: =SUM(B8:E8) -> 0 | G8: =F8 -> 0 | K8: =SUM(F8-H8-J8-I8) -> 0 | L8: =SUM(F8-H8-J8-I8) -> 0 | O8: =SUM(L8-M8-N8+O7+P8) -> 250 | X8: 6 | AE8: =SUM(AC8:AD8) -> 0 | AJ8: 0
A9: 44567 | F9: =SUM(B9:E9) -> 0 | G9: =F9 -> 0 | K9: =SUM(F9-H9-J9-I9) -> 0 | L9: =SUM(F9-H9-J9-I9) -> 0 | O9: =SUM(L9-M9-N9+O8) -> 250 | X9: 7 | AE9: =SUM(AC9:AD9) -> 0 | AJ9: =AE9 -> 0
A10: 44568 | F10: =SUM(B10:E10) -> 0 | G10: =F10 -> 0 | K10: =SUM(F10-H10-J10-I10) -> 0 | L10: =SUM(F10-H10-J10-I10) -> 0 | O10: =SUM(L10-M10-N10+O9) -> 250 | X10: 8 | AE10: =SUM(AC10:AD10) -> 0 | AJ10: =AE10 -> 0
A11: 44569 | F11: =SUM(B11:E11) -> 0 | G11: =F11 -> 0 | K11: =SUM(F11-H11-J11-I11) -> 0 | L11: =SUM(F11-H11-J11-I11) -> 0 | O11: =SUM(L11-M11-N11+O10) -> 250 | X11: 9 | AE11: =SUM(AC11:AD11) -> 0 | AJ11: =AE11 -> 0
A12: 44570 | F12: =SUM(B12:E12) -> 0 | G12: =F12 -> 0 | K12: =SUM(F12-H12-J12-I12) -> 0 | L12: =SUM(F12-H12-J12-I12) -> 0 | O12: =SUM(L12-M12-N12+O11) -> 250 | X12: 10 | AE12: =SUM(AC12:AD12) -> 0 | AJ12: =AE12 -> 0
A13: 44571 | F13: =SUM(B13:E13) -> 0 | G13: =F13 -> 0 | K13: =SUM(F13-H13-J13-I13) -> 0 | L13: =SUM(F13-H13-J13-I13) -> 0 | O13: =SUM(L13-M13-N13+O12) -> 250 | X13: 11 | AE13: =SUM(AC13:AD13) -> 0 | AJ13: =AE13 -> 0
A14: 44572 | F14: =SUM(B14:E14) -> 0 | G14: =F14 -> 0 | K14: =SUM(F14-H14-J14-I14) -> 0 | L14: =SUM(F14-H14-J14-I14) -> 0 | O14: =SUM(L14-M14-N14+O13) -> 250 | X14: 12 | AE14: =SUM(AC14:AD14) -> 0 | AJ14: =AE14 -> 0
A15: 44573 | F15: =SUM(B15:E15) -> 0 | G15: =F15 -> 0 | K15: =SUM(F15-H15-J15-I15) -> 0 | L15: =SUM(F15-H15-J15-I15) -> 0 | O15: =SUM(L15-M15-N15+O14) -> 250 | X15: 13 | AE15: =SUM(AC15:AD15) -> 0 | AJ15: =AE15 -> 0
A16: 44574 | F16: =SUM(B16:E16) -> 0 | G16: =F16 -> 0 | K16: =SUM(F16-H16-J16-I16) -> 0 | L16: =SUM(F16-H16-J16-I16) -> 0 | O16: =SUM(L16-M16-N16+O15) -> 250 | X16: 14 | AE16: =SUM(AC16:AD16) -> 0 | AJ16: =AE16 -> 0
A17: 44575 | F17: =SUM(B17:E17) -> 0 | G17: =F17 -> 0 | K17: =SUM(F17-H17-J17-I17) -> 0 | L17: =SUM(F17-H17-J17-I17) -> 0 | O17: =SUM(L17-M17-N17+O16+P17) -> 250 | X17: 15 | AE17: =SUM(AC17:AD17) -> 0 | AJ17: =AE17 -> 0
A18: 44576 | F18: =SUM(B18:E18) -> 0 | G18: =F18 -> 0 | K18: =SUM(F18-H18-J18-I18) -> 0 | L18: =SUM(F18-H18-J18-I18) -> 0 | O18: =SUM(L18-M18-N18+O17+P18) -> 250 | X18: 16 | AE18: =SUM(AC18:AD18) -> 0 | AJ18: =AE18 -> 0
A19: 44577 | F19: =SUM(B19:E19) -> 0 | G19: =F19 -> 0 | K19: =SUM(F19-H19-J19-I19) -> 0 | L19: =SUM(F19-H19-J19-I19) -> 0 | O19: =SUM(L19-M19-N19+O18+P19) -> 250 | X19: 17 | AE19: =SUM(AC19:AD19) -> 0 | AJ19: =AE19 -> 0
A20: 44578 | F20: =SUM(B20:E20) -> 0 | G20: =F20 -> 0 | K20: =SUM(F20-H20-J20-I20) -> 0 | L20: =SUM(F20-H20-J20-I20) -> 0 | O20: =SUM(L20-M20-N20+O19+P20) -> 250 | X20: 18 | AE20: =SUM(AC20:AD20) -> 0 | AJ20: =AE20 -> 0
A21: 44579 | F21: =SUM(B21:E21) -> 0 | G21: =F21 -> 0 | K21: =SUM(F21-H21-J21-I21) -> 0 | L21: =SUM(F21-H21-J21-I21) -> 0 | O21: =SUM(L21-M21-N21+O20) -> 250 | X21: 19 | AE21: =SUM(AC21:AD21) -> 0 | AJ21: =AE21 -> 0
A22: 44580 | F22: =SUM(B22:E22) -> 0 | G22: =F22 -> 0 | K22: =SUM(F22-H22-J22-I22) -> 0 | L22: =SUM(F22-H22-J22-I22) -> 0 | O22: =SUM(L22-M22-N22+O21) -> 250 | X22: 20 | AE22: =SUM(AC22:AD22) -> 0 | AJ22: =AE22 -> 0
A23: 44581 | F23: =SUM(B23:E23) -> 0 | G23: =F23 -> 0 | K23: =SUM(F23-H23-J23-I23) -> 0 | L23: =SUM(F23-H23-J23-I23) -> 0 | O23: =SUM(L23-M23-N23+O22) -> 250 | X23: 21 | AE23: =SUM(AC23:AD23) -> 0 | AJ23: =AE23 -> 0
A24: 44582 | F24: =SUM(B24:E24) -> 0 | G24: =F24 -> 0 | K24: =SUM(F24-H24-J24-I24) -> 0 | L24: =SUM(F24-H24-J24-I24) -> 0 | O24: =SUM(L24-M24-N24+O23+P24) -> 250 | X24: 22 | AE24: =SUM(AC24:AD24) -> 0 | AJ24: =AE24 -> 0
A25: 44583 | F25: =SUM(B25:E25) -> 0 | G25: =F25 -> 0 | K25: =SUM(F25-H25-J25-I25) -> 0 | L25: =SUM(F25-H25-J25-I25) -> 0 | O25: =SUM(L25-M25-N25+O24) -> 250 | X25: 26 | AE25: =SUM(AC25:AD25) -> 0 | AJ25: =AE25 -> 0
A26: 44584 | F26: =SUM(B26:E26) -> 0 | G26: =F26 -> 0 | K26: =SUM(F26-H26-J26-I26) -> 0 | L26: =SUM(F26-H26-J26-I26) -> 0 | O26: =SUM(L26-M26-N26+O25) -> 250 | X26: 27 | AE26: =SUM(AC26:AD26) -> 0 | AJ26: =AE26 -> 0
A27: 44585 | F27: =SUM(B27:E27) -> 0 | G27: =F27 -> 0 | K27: =SUM(F27-H27-J27-I27) -> 0 | L27: =SUM(F27-H27-J27-I27) -> 0 | O27: =SUM(L27-M27-N27+O26) -> 250 | X27: 28 | AE27: =SUM(AC27:AD27) -> 0 | AJ27: =AE27 -> 0
A28: 44586 | F28: =SUM(B28:E28) -> 0 | G28: =F28 -> 0 | K28: =SUM(F28-H28-J28-I28) -> 0 | L28: =SUM(F28-H28-J28-I28) -> 0 | O28: =SUM(L28-M28-N28+O27+P28) -> 250 | X28: 29 | AE28: =SUM(AC28:AD28) -> 0 | AJ28: =AE28 -> 0
A29: 44587 | F29: =SUM(B29:E29) -> 0 | G29: =F29 -> 0 | K29: =SUM(F29-H29-J29-I29) -> 0 | L29: =SUM(F29-H29-J29-I29) -> 0 | O29: =SUM(L29-M29-N29+O28) -> 250 | X29: 30 | AE29: =SUM(AC29:AD29) -> 0 | AJ29: =AE29 -> 0
A30: 44588 | F30: =SUM(B30:E30) -> 0 | G30: =F30 -> 0 | K30: =SUM(F30-H30-J30-I30) -> 0 | L30: =SUM(F30-H30-J30-I30) -> 0 | O30: =SUM(L30-M30-N30+O29+P30) -> 250 | AC30: TVA | AD30: =SUM(AD3:AD29) -> 0
A31: 44589 | F31: =SUM(B31:E31) -> 0 | G31: =F31 -> 0 | K31: =SUM(F31-H31-J31-I31) -> 0 | L31: =SUM(F31-H31-J31-I31) -> 0 | O31: =SUM(L31-M31-N31+O30) -> 250 | P31: SOLDE CAISSE
A32: 44590 | F32: =SUM(B32:E32) -> 0 | G32: =F32 -> 0 | K32: =SUM(F32-H32-J32-I32) -> 0 | L32: =SUM(F32-H32-J32-I32) -> 0 | O32: =SUM(L32-M32-N32+O31) -> 250 | P32: DU MOIS | AA32: MARGE
A33: 44591 | F33: =SUM(B33:E33) -> 0 | G33: =F33 -> 0 | K33: =SUM(F33-H33-J33-I33) -> 0 | L33: =SUM(F33-H33-J33-I33) -> 0 | O33: =SUM(L33-M33-N33+O32) -> 250 | P33: =SUM(O33) -> 250 | X33: 1 | AE33: =SUM(AC33:AD33) -> 0 | AJ33: =AE33 -> 0 | AL33: calcul de marge
B34: =SUM(B5:B33) -> 0 | C34: =SUM(C3:C33) -> 0 | D34: =SUM(D3:D33) -> 0 | E34: =SUM(E3:E33) -> 0 | F34: =SUM(F3:F33) -> 0 | H34: =SUM(H3:H33) -> 0 | J34: =SUM(J3:J33) -> 0 | K34: =SUM(K3:K33) -> 0 | L34: =SUM(L3:L33) -> 0 | M34: =SUM(M3:M33) -> 0 | N34: =SUM(N3:N33) -> 0 | X34: 2 | AE34: =SUM(AC34:AD34) -> 0 | AJ34: =AE34 -> 0 | AL34: =AC33 -> 0 | AM34: 1
A35: HTVA | B35: =SUM(B3:B33) -> 0 | C35: =SUM(C34/1.06) -> 0 | D35: =SUM(D34/1.12) -> 0 | E35: =SUM(E34/1.21) -> 0 | F35: =SUM(B35:E35) -> 0 | G35: =SUM(G34:G34) -> 0 | L35: TOTAL SORTIE | N35: =SUM(M34:N34) -> 0 | X35: 3 | AE35: =SUM(AC35:AD35) -> 0 | AJ35: =AE35 -> 0 | AL35: =AC34 -> 0 | AM35: 2
A36: TVA | C36: =SUM(C34-C35) -> 0 | D36: =SUM(D34-D35) -> 0 | E36: =SUM(E34-E35) -> 0 | F36: =SUM(C36:E36) -> 0 | X36: 4 | AE36: =SUM(AC36:AD36) -> 0 | AJ36: 0 | AL36: =AC35 -> 0 | AM36: 3
X37: 5 | AE37: =SUM(AC37:AD37) -> 0 | AJ37: =AE37 -> 0 | AL37: =AC36 -> 0 | AM37: 4
X38: 6 | AE38: =SUM(AC38:AD38) -> 0 | AJ38: 0 | AL38: =AC37 -> 0 | AM38: 5
X39: 7 | AE39: =SUM(AC39:AD39) -> 0 | AJ39: =AE39 -> 0 | AL39: =AC38 -> 0 | AM39: 6
X40: 8 | AE40: =SUM(AC40:AD40) -> 0 | AJ40: =AE40 -> 0 | AL40: =AC39 -> 0 | AM40: 7
X41: 9 | AE41: =SUM(AC41:AD41) -> 0 | AJ41: =AE41 -> 0 | AL41: =AC40 -> 0 | AM41: 8
X42: 10 | AE42: =SUM(AC42:AD42) -> 0 | AJ42: =AE42 -> 0 | AL42: =AC41 -> 0 | AM42: 9
X43: 11 | AE43: =SUM(AC43:AD43) -> 0 | AJ43: =AE43 -> 0 | AL43: =AC42 -> 0 | AM43: 10
X44: 12 | AE44: =SUM(AC44:AD44) -> 0 | AJ44: =AE44 -> 0 | AL44: =AC43 -> 0 | AM44: 11
X45: 13 | AE45: =SUM(AC45:AD45) -> 0 | AJ45: =AE45 -> 0 | AL45: =AC44 -> 0 | AM45: 12
X46: 14 | AE46: =SUM(AC46:AD46) -> 0 | AJ46: =AE46 -> 0 | AL46: =AC45 -> 0 | AM46: 13
X47: 15 | AE47: =SUM(AC47:AD47) -> 0 | AJ47: =AE47 -> 0 | AL47: =AC46 -> 0 | AM47: 14
X48: 16 | AE48: =SUM(AC48:AD48) -> 0 | AJ48: =AE48 -> 0 | AL48: =AC47 -> 0 | AM48: 15
X49: 17 | AE49: =SUM(AC49:AD49) -> 0 | AJ49: =AE49 -> 0 | AL49: =AC48 -> 0 | AM49: 16
X50: 18 | AE50: =SUM(AC50:AD50) -> 0 | AJ50: =AE50 -> 0 | AL50: =AC49 -> 0 | AM50: 17
... X62: 30 | AE62: =SUM(AC62:AD62) -> 0 | AJ62: =AE62 -> 0 | AL62: =AC61 -> 0 | AM62: 29
AC63: =SUM(AC33:AC62) -> 0 | AH63: TOTAL GENERALE FEUILLE | AJ63: =SUM(AJ3:AJ62) -> 0 | AL63: =AC62 -> 0 | AM63: 30
AC64: TVA | AD64: =SUM(AD33:AD63) -> 0 | AL64: =AC63 -> 0
AI66: A PÄYER
AC67: TVA | AD67: =AD30 -> 0 | AI67: MOIS EN COURS | AJ67: =AJ63 -> 0
AC68: TVA | AD68: =AD64 -> 0 | AI68: mois précèdent | AJ68: ='[1]avril 2026'!AL73 -> 0
AC69: TVA RECUP | AD69: =SUM(AD67:AD68) -> 0 | AI69: total a payer | AJ69: =SUM(AJ67:AJ68) -> 0

Sheet tva onss
C1: TVA | J1: ONSS
J2: 1 er trim. | O2: 075/6525/07152 | P2: TVA
C3: TVA 1 TRIM | D3: A PAYER | E3: A RECUP | F3: RESTE A PAYER | J3: ONSS PAYER | K3: acompte | O3: 033/1462/57996 | P3: ONSS
C4: 46023 | D4: ='JANV 2026'!F36 -> 0 | E4: ='JANV 2026'!AD69 -> 0 | F4: =SUM(D4-E4) -> 0
C5: 46054 | D5: ='FEVRIER 2026'!F36 -> 0 | E5: ='FEVRIER 2026'!AD69 -> 0 | F5: =SUM(D5-E5) -> 0
C6: 46082 | D6: ='MARS 2026'!F36 -> 0 | E6: ='MARS 2026'!AD69 -> 0 | F6: =SUM(D6-E6) -> 0
D8: =SUM(D4:D7) -> 0 | E8: =SUM(E4:E6) -> 0 | F8: =SUM(F4:F7) -> 0
J10: TOT onss payé | K10: =SUM(K4:K9) -> 0
C11: TVA PAYER | F11: acompte
D12: solde 4 em trim. 2025 | F12: 0 | G12: solde | J12: ONSS a payer | L12: =SUM(K12-K10) -> 0 | M12: solde a payer
F18: =SUM(F11:F17) -> 0
C22: RESTE | D22: =F8 -> 0 | E22: =F18 -> 0 | F22: =SUM(D22-E22) -> 0
J26: 2 er trim.
C27: TVA 2 TRIM | D27: A PAYER | E27: A REMB | F27: RESTE A PAYER | J27: ONSS PAYER | K27: acompte
C28: 46113 | D28: ='AVRIL 2026'!F36 -> 0 | E28: ='AVRIL 2026'!AD69 -> 0 | F28: =SUM(D28-E28) -> 0
C29: 46143 | D29: ='MAI 2026'!F36 -> 0 | E29: ='MAI 2026'!AD69 -> 0 | F29: =SUM(D29-E29) -> 0
C30: 46174 | D30: ='JUIN 2026'!F36 -> 55.948311 | E30: ='JUIN 2026'!AD69 -> 118.6 | F30: =SUM(D30-E30) -> -62.651689
D32: =SUM(D28:D31) -> 55.948311 | E32: =SUM(E28:E30) -> 118.6 | F32: =SUM(F28:F31) -> -62.651689
J34: TOT onss payé | K34: =SUM(K28:K33) -> 0
C35: TVA PAYER | F35: acompte
J36: ONSS a payer | L36: =SUM(K36-K34) -> 0 | M36: solde a payer
F44: =SUM(F35:F42) -> 0
C46: RESTE | D46: =F32 -> -62.651689 | E46: =F44 -> 0 | F46: =SUM(D46-E46) -> -62.651689
J60: 3 er trim. | O60: 075/6525/07152 | P60: TVA
C61: TVA 3 TRIM | D61: A PAYER | E61: A REMB | F61: RESTE A PAYER | J61: ONSS PAYER | K61: acompte | O61: 033/1462/57996 | P61: ONSS
C62: 46204 | D62: ='JUILLET 2026'!F36 -> 0 | E62: ='JUILLET 2026'!AD69 -> 0 | F62: =SUM(D62-E62) -> 0
C63: 46235 | D63: ='AOUT 2026'!F36 -> 0 | E63: ='AOUT 2026'!AD69 -> 0 | F63: =SUM(D63-E63) -> 0
C64: 46266 | D64: ='SEPT 2026'!F36 -> 0 | E64: ='SEPT 2026'!AD69 -> 0 | F64: =SUM(D64-E64) -> 0
D66: =SUM(D62:D65) -> 0 | E66: =SUM(E62:E64) -> 0 | F66: =SUM(F62:F65) -> 0
J68: TOT onss payé | K68: =SUM(K62:K67) -> 0
C69: TVA PAYER | F69: acompte
J70: ONSS a payer | L70: =SUM(K70-K68) -> 0 | M70: solde a payer
F76: =SUM(F69:F75) -> 0
C80: RESTE | D80: =F66 -> 0 | E80: =F76 -> 0 | F80: =SUM(D80-E80) -> 0
J84: 4 er trim.
C85: TVA 4 TRIM | D85: A PAYER | E85: A REMB | F85: RESTE A PAYER | J85: ONSS PAYER | K85: acompte
C86: 46296 | D86: ='OCT 2026'!F36 -> 0 | E86: ='OCT 2026'!AD69 -> 0 | F86: =SUM(D86-E86) -> 0
C87: 46327 | D87: ='NOV 2026'!F36 -> 0 | E87: ='NOV 2026'!AD69 -> 0 | F87: =SUM(D87-E87) -> 0
C88: 46357 | D88: ='DEC 2026'!F36 -> 0 | E88: ='DEC 2026'!AD69 -> 0 | F88: =SUM(D88-E88) -> 0
D90: =SUM(D86:D89) -> 0 | E90: =SUM(E86:E88) -> 0 | F90: =SUM(F86:F89) -> 0
J92: TOT onss payé | K92: =SUM(K86:K91) -> 0
C93: TVA PAYER
J94: ONSS a payer | L94: =SUM(K94-K92) -> 0 | M94: solde a payer
F100: =SUM(F93:F99) -> 0
C104: RESTE | D104: =F90 -> 0 | E104: =F100 -> 0 | F104: =SUM(D104-E104) -> 0

Sheet marge
A1: 2026 | B1: JANVIER | C1: FEVRIER | D1: MARS | E1: AVRIL | F1: MAI | G1: JUIN | H1: JUILLET | I1: AOÛT | J1: SEPTEMBRE | K1: OCTOBRE | L1: NOVEMBRE | M1: DÉCEMBRE
A4: 1 | B4: ='JANV 2026'!AL34 -> 0 | C4: ='FEVRIER 2026'!AL34 -> 0 | D4: ='MARS 2026'!AL33 -> 0 | E4: ='AVRIL 2026'!AL33 -> 0 | F4: ='MAI 2026'!AL33 -> 0 | G4: ='JUIN 2026'!AL33 -> 40.92 | H4: ='JUILLET 2026'!AL33 -> 0 | I4: ='AOUT 2026'!AL33 -> 0 | J4: ='SEPT 2026'!AL33 -> 0 | K4: ='OCT 2026'!AL33 -> 0 | L4: ='NOV 2026'!AL33 -> 0 | M4: ='DEC 2026'!AL33 -> 0 | Q4: 1
A5: 2 | B5: ='JANV 2026'!AL35 -> 0 | C5: ='FEVRIER 2026'!AL35 -> 0 | D5: ='MARS 2026'!AL34 -> 0 | E5: ='AVRIL 2026'!AL34 -> 0 | F5: ='MAI 2026'!AL34 -> 0 | G5: ='JUIN 2026'!AL34 -> 450.73 | H5: ='JUILLET 2026'!AL34 -> 0 | I5: ='AOUT 2026'!AL34 -> 0 | J5: ='SEPT 2026'!AL34 -> 0 | K5: ='OCT 2026'!AL34 -> 0 | L5: ='NOV 2026'!AL34 -> 0 | M5: ='DEC 2026'!AL34 -> 0 | Q5: 2
A6: 3 | B6: ='JANV 2026'!AL36 -> 0 | C6: ='FEVRIER 2026'!AL36 -> 0 | D6: ='MARS 2026'!AL35 -> 0 | E6: ='AVRIL 2026'!AL35 -> 0 | F6: ='MAI 2026'!AL35 -> 0 | G6: ='JUIN 2026'!AL35 -> 518.14 | H6: ='JUILLET 2026'!AL35 -> 0 | I6: ='AOUT 2026'!AL35 -> 0 | J6: ='SEPT 2026'!AL35 -> 0 | K6: ='OCT 2026'!AL35 -> 0 | L6: ='NOV 2026'!AL35 -> 0 | M6: ='DEC 2026'!AL35 -> 0 | Q6: 3
A7: 4 | B7: ='JANV 2026'!AL37 -> 0 | C7: ='FEVRIER 2026'!AL37 -> 0 | D7: ='MARS 2026'!AL36 -> 0 | E7: ='AVRIL 2026'!AL36 -> 0 | F7: ='MAI 2026'!AL36 -> 0 | G7: ='JUIN 2026'!AL36 -> 168 | H7: ='JUILLET 2026'!AL36 -> 0 | I7: ='AOUT 2026'!AL36 -> 0 | J7: ='SEPT 2026'!AL36 -> 0 | K7: ='OCT 2026'!AL36 -> 0 | L7: ='NOV 2026'!AL36 -> 0 | M7: ='DEC 2026'!AL36 -> 0 | Q7: 4
A8: 5 | B8: ='JANV 2026'!AL38 -> 0 | C8: ='FEVRIER 2026'!AL38 -> 0 | D8: ='MARS 2026'!AL37 -> 0 | E8: ='AVRIL 2026'!AL37 -> 0 | F8: ='MAI 2026'!AL37 -> 0 | G8: ='JUIN 2026'!AL37 -> 0 | H8: ='JUILLET 2026'!AL37 -> 0 | I8: ='AOUT 2026'!AL37 -> 0 | J8: ='SEPT 2026'!AL37 -> 0 | K8: ='OCT 2026'!AL37 -> 0 | L8: ='NOV 2026'!AL37 -> 0 | M8: ='DEC 2026'!AL37 -> 0 | Q8: 5
A9: 6 | B9: ='JANV 2026'!AL39 -> 0 | C9: ='FEVRIER 2026'!AL39 -> 0 | D9: ='MARS 2026'!AL38 -> 0 | E9: ='AVRIL 2026'!AL38 -> 0 | F9: ='MAI 2026'!AL38 -> 0 | G9: ='JUIN 2026'!AL38 -> 0 | H9: ='JUILLET 2026'!AL38 -> 0 | I9: ='AOUT 2026'!AL38 -> 0 | J9: ='SEPT 2026'!AL38 -> 0 | K9: ='OCT 2026'!AL38 -> 0 | L9: ='NOV 2026'!AL38 -> 0 | M9: ='DEC 2026'!AL38 -> 0 | Q9: 6
A10: 7 | B10: ='JANV 2026'!AL40 -> 0 | C10: ='FEVRIER 2026'!AL40 -> 0 | D10: ='MARS 2026'!AL39 -> 0 | E10: ='AVRIL 2026'!AL39 -> 0 | F10: ='MAI 2026'!AL39 -> 0 | G10: ='JUIN 2026'!AL39 -> 0 | H10: ='JUILLET 2026'!AL39 -> 0 | I10: ='AOUT 2026'!AL39 -> 0 | J10: ='SEPT 2026'!AL39 -> 0 | K10: ='OCT 2026'!AL39 -> 0 | L10: ='NOV 2026'!AL39 -> 0 | M10: ='DEC 2026'!AL39 -> 0 | Q10: 7
A11: 8 | B11: ='JANV 2026'!AL41 -> 0 | C11: ='FEVRIER 2026'!AL41 -> 0 | D11: ='MARS 2026'!AL40 -> 0 | E11: ='AVRIL 2026'!AL40 -> 0 | F11: ='MAI 2026'!AL40 -> 0 | G11: ='JUIN 2026'!AL40 -> 0 | H11: ='JUILLET 2026'!AL40 -> 0 | I11: ='AOUT 2026'!AL40 -> 0 | J11: ='SEPT 2026'!AL40 -> 0 | K11: ='OCT 2026'!AL40 -> 0 | L11: ='NOV 2026'!AL40 -> 0 | M11: ='DEC 2026'!AL40 -> 0 | Q11: 8
A12: 9 | B12: ='JANV 2026'!AL42 -> 0 | C12: ='FEVRIER 2026'!AL42 -> 0 | D12: ='MARS 2026'!AL41 -> 0 | E12: ='AVRIL 2026'!AL41 -> 0 | F12: ='MAI 2026'!AL41 -> 0 | G12: ='JUIN 2026'!AL41 -> 0 | H12: ='JUILLET 2026'!AL41 -> 0 | I12: ='AOUT 2026'!AL41 -> 0 | J12: ='SEPT 2026'!AL41 -> 0 | K12: ='OCT 2026'!AL41 -> 0 | L12: ='NOV 2026'!AL41 -> 0 | M12: ='DEC 2026'!AL41 -> 0 | Q12: 9
A13: 10 | B13: ='JANV 2026'!AL43 -> 0 | C13: ='FEVRIER 2026'!AL43 -> 0 | D13: ='MARS 2026'!AL42 -> 0 | E13: ='AVRIL 2026'!AL42 -> 0 | F13: ='MAI 2026'!AL42 -> 0 | G13: ='JUIN 2026'!AL42 -> 0 | H13: ='JUILLET 2026'!AL42 -> 0 | I13: ='AOUT 2026'!AL42 -> 0 | J13: ='SEPT 2026'!AL42 -> 0 | K13: ='OCT 2026'!AL42 -> 0 | L13: ='NOV 2026'!AL42 -> 0 | M13: ='DEC 2026'!AL42 -> 0 | Q13: 10
A14: 11 | B14: ='JANV 2026'!AL44 -> 0 | C14: ='FEVRIER 2026'!AL44 -> 0 | D14: ='MARS 2026'!AL43 -> 0 | E14: ='AVRIL 2026'!AL43 -> 0 | F14: ='MAI 2026'!AL43 -> 0 | G14: ='JUIN 2026'!AL43 -> 0 | H14: ='JUILLET 2026'!AL43 -> 0 | I14: ='AOUT 2026'!AL43 -> 0 | J14: ='SEPT 2026'!AL43 -> 0 | K14: ='OCT 2026'!AL43 -> 0 | L14: ='NOV 2026'!AL43 -> 0 | M14: ='DEC 2026'!AL43 -> 0 | Q14: 11
A15: 12 | B15: ='JANV 2026'!AL45 -> 0 | C15: ='FEVRIER 2026'!AL45 -> 0 | D15: ='MARS 2026'!AL44 -> 0 | E15: ='AVRIL 2026'!AL44 -> 0 | F15: ='MAI 2026'!AL44 -> 0 | G15: ='JUIN 2026'!AL44 -> 0 | H15: ='JUILLET 2026'!AL44 -> 0 | I15: ='AOUT 2026'!AL44 -> 0 | J15: ='SEPT 2026'!AL44 -> 0 | K15: ='OCT 2026'!AL44 -> 0 | L15: ='NOV 2026'!AL44 -> 0 | M15: ='DEC 2026'!AL44 -> 0 | Q15: 12
... A23: 20 | B23: ='JANV 2026'!AL53 -> 0 | C23: ='FEVRIER 2026'!AL53 -> 0 | D23: ='MARS 2026'!AL52 -> 0 | E23: ='AVRIL 2026'!AL52 -> 0 | F23: ='MAI 2026'!AL52 -> 0 | G23: ='JUIN 2026'!AL52 -> 0 | H23: ='JUILLET 2026'!AL52 -> 0 | I23: ='AOUT 2026'!AL52 -> 0 | J23: ='SEPT 2026'!AL52 -> 0 | K23: ='OCT 2026'!AL52 -> 0 | L23: ='NOV 2026'!AL52 -> 0 | M23: ='DEC 2026'!AL52 -> 0 | Q23: 20
A24: Z | B24: ='JANV 2026'!AL54 -> 0 | C24: ='FEVRIER 2026'!AL54 -> 0 | D24: ='MARS 2026'!AL53 -> 0 | E24: ='AVRIL 2026'!AL53 -> 0 | F24: ='MAI 2026'!AL53 -> 0 | G24: ='JUIN 2026'!AL53 -> 0 | H24: ='JUILLET 2026'!AL53 -> 0 | I24: ='AOUT 2026'!AL53 -> 0 | J24: ='SEPT 2026'!AL53 -> 0 | K24: ='OCT 2026'!AL53 -> 0 | L24: ='NOV 2026'!AL53 -> 0 | M24: ='DEC 2026'!AL53 -> 0 | Q24: 21
A25: 22 | B25: ='JANV 2026'!AL55 -> 0 | C25: ='FEVRIER 2026'!AL55 -> 0 | D25: ='MARS 2026'!AL54 -> 0 | E25: ='AVRIL 2026'!AL54 -> 0 | F25: ='MAI 2026'!AL54 -> 0 | G25: ='JUIN 2026'!AL54 -> 0 | H25: ='JUILLET 2026'!AL54 -> 0 | I25: ='AOUT 2026'!AL54 -> 0 | J25: ='SEPT 2026'!AL54 -> 0 | K25: ='OCT 2026'!AL54 -> 0 | L25: ='NOV 2026'!AL54 -> 0 | M25: ='DEC 2026'!AL54 -> 0 | Q25: 22
A26: 23 | B26: ='JANV 2026'!AL56 -> 0 | C26: ='FEVRIER 2026'!AL56 -> 0 | D26: ='MARS 2026'!AL55 -> 0 | E26: ='AVRIL 2026'!AL55 -> 0 | F26: ='MAI 2026'!AL55 -> 0 | G26: ='JUIN 2026'!AL55 -> 0 | H26: ='JUILLET 2026'!AL55 -> 0 | I26: ='AOUT 2026'!AL55 -> 0 | J26: ='SEPT 2026'!AL55 -> 0 | K26: ='OCT 2026'!AL55 -> 0 | L26: ='NOV 2026'!AL55 -> 0 | M26: ='DEC 2026'!AL55 -> 0 | Q26: 23
A27: 24 | B27: ='JANV 2026'!AL57 -> 0 | C27: ='FEVRIER 2026'!AL57 -> 0 | D27: ='MARS 2026'!AL56 -> 0 | E27: ='AVRIL 2026'!AL56 -> 0 | F27: ='MAI 2026'!AL56 -> 0 | G27: ='JUIN 2026'!AL56 -> 0 | H27: ='JUILLET 2026'!AL56 -> 0 | I27: ='AOUT 2026'!AL56 -> 0 | J27: ='SEPT 2026'!AL56 -> 0 | K27: ='OCT 2026'!AL56 -> 0 | L27: ='NOV 2026'!AL56 -> 0 | M27: ='DEC 2026'!AL56 -> 0 | Q27: 24
A28: 25 | B28: ='JANV 2026'!AL58 -> 0 | C28: ='FEVRIER 2026'!AL58 -> 0 | D28: ='MARS 2026'!AL57 -> 0 | E28: ='AVRIL 2026'!AL57 -> 0 | F28: ='MAI 2026'!AL57 -> 0 | G28: ='JUIN 2026'!AL57 -> 0 | H28: ='JUILLET 2026'!AL57 -> 0 | I28: ='AOUT 2026'!AL57 -> 0 | J28: ='SEPT 2026'!AL57 -> 0 | K28: ='OCT 2026'!AL57 -> 0 | L28: ='NOV 2026'!AL57 -> 0 | M28: ='DEC 2026'!AL57 -> 0 | Q28: 25
A29: 26 | B29: ='JANV 2026'!AL59 -> 0 | C29: ='FEVRIER 2026'!AL59 -> 0 | D29: ='MARS 2026'!AL58 -> 0 | E29: ='AVRIL 2026'!AL58 -> 0 | F29: ='MAI 2026'!AL58 -> 0 | G29: ='JUIN 2026'!AL58 -> 0 | H29: ='JUILLET 2026'!AL58 -> 0 | I29: ='AOUT 2026'!AL58 -> 0 | J29: ='SEPT 2026'!AL58 -> 0 | K29: ='OCT 2026'!AL58 -> 0 | L29: ='NOV 2026'!AL58 -> 0 | M29: ='DEC 2026'!AL58 -> 0 | Q29: 26
A30: 27 | B30: ='JANV 2026'!AL60 -> 0 | C30: ='FEVRIER 2026'!AL60 -> 0 | D30: ='MARS 2026'!AL59 -> 0 | E30: ='AVRIL 2026'!AL59 -> 0 | F30: ='MAI 2026'!AL59 -> 0 | G30: ='JUIN 2026'!AL59 -> 0 | H30: ='JUILLET 2026'!AL59 -> 0 | I30: ='AOUT 2026'!AL59 -> 0 | J30: ='SEPT 2026'!AL59 -> 0 | K30: ='OCT 2026'!AL59 -> 0 | L30: ='NOV 2026'!AL59 -> 0 | M30: ='DEC 2026'!AL59 -> 0 | Q30: 27
A31: 28 | B31: ='JANV 2026'!AL61 -> 0 | C31: ='FEVRIER 2026'!AL61 -> 0 | D31: ='MARS 2026'!AL60 -> 0 | E31: ='AVRIL 2026'!AL60 -> 0 | F31: ='MAI 2026'!AL60 -> 0 | G31: ='JUIN 2026'!AL60 -> 0 | H31: ='JUILLET 2026'!AL60 -> 0 | I31: ='AOUT 2026'!AL60 -> 0 | J31: ='SEPT 2026'!AL60 -> 0 | K31: ='OCT 2026'!AL60 -> 0 | L31: ='NOV 2026'!AL60 -> 0 | M31: ='DEC 2026'!AL60 -> 0 | Q31: 28
A32: 29 | B32: ='JANV 2026'!AL62 -> 0 | C32: ='FEVRIER 2026'!AL62 -> 0 | D32: ='MARS 2026'!AL61 -> 0 | E32: ='AVRIL 2026'!AL61 -> 0 | F32: ='MAI 2026'!AL61 -> 0 | G32: ='JUIN 2026'!AL61 -> 0 | H32: ='JUILLET 2026'!AL61 -> 0 | I32: ='AOUT 2026'!AL61 -> 0 | J32: ='SEPT 2026'!AL61 -> 0 | K32: ='OCT 2026'!AL61 -> 0 | L32: ='NOV 2026'!AL61 -> 0 | M32: ='DEC 2026'!AL61 -> 0 | Q32: 29
A33: 30 | B33: ='JANV 2026'!AL63 -> 0 | C33: ='FEVRIER 2026'!AL63 -> 0 | D33: ='MARS 2026'!AL62 -> 0 | E33: ='AVRIL 2026'!AL62 -> 0 | F33: ='MAI 2026'!AL62 -> 0 | G33: ='JUIN 2026'!AL62 -> 0 | H33: ='JUILLET 2026'!AL62 -> 0 | I33: ='AOUT 2026'!AL62 -> 0 | J33: ='SEPT 2026'!AL62 -> 0 | K33: ='OCT 2026'!AL62 -> 0 | L33: ='NOV 2026'!AL62 -> 0 | M33: ='DEC 2026'!AL62 -> 0 | Q33: 30
A34: 31 | Q34: 31
A35: 32 | Q35: 32
A36: 33 | Q36: 33
A37: 34 | Q37: 34
A38: 35 | Q38: 35
A39: 36 | Q39: 36
A40: 37 | Q40: 37
A41: 38 | Q41: 38
A42: 39 | Q42: 39
A43: 40 | Q43: 40
A44: 41 | Q44: 41
A45: 42 | Q45: 42
P58: STOCK
B59: =SUM(B4:B58) -> 0 | C59: =SUM(C4:C58) -> 0 | D59: =SUM(D4:D58) -> 0 | E59: =SUM(E4:E58) -> 0 | F59: =SUM(F4:F58) -> 0 | G59: =SUM(G4:G58) -> 1177.79 | H59: =SUM(H4:H58) -> 0 | I59: =SUM(I4:I58) -> 0 | ... M59: =SUM(M4:M58) -> 0 | O59: =SUM(B59:M59) -> 1177.79 | P59: =W67 -> 0 | Q59: =SUM(O59-P59) -> 1177.79
B60: ='JANV 2026'!F35 -> 0 | C60: ='FEVRIER 2026'!F35 -> 0 | D60: ='MARS 2026'!F35 -> 0 | E60: ='AVRIL 2026'!F35 -> 0 | F60: ='MAI 2026'!F35 -> 0 | G60: ='JUIN 2026'!F35 -> 858.09169 | H60: ='JUILLET 2026'!F35 -> 0 | I60: ='AOUT 2026'!F35 -> 0 | J60: ='SEPT 2026'!F35 -> 0 | K60: ='OCT 2026'!F35 -> 0 | L60: ='NOV 2026'!F35 -> 0 | M60: ='DEC 2026'!F35 -> 0 | O60: =SUM(B60:N60) -> 858.09169 | Q60: =O60 -> 858.09169
B61: =SUM(B60/B59) -> #DIV/0! | C61: =SUM(C60/C59) -> #DIV/0! | D61: =SUM(D60/D59) -> #DIV/0! | E61: =SUM(E60/E59) -> #DIV/0! | F61: =SUM(F60/F59) -> #DIV/0! | G61: =SUM(G60/G59) -> 0.72856085 | H61: =SUM(H60/H59) -> #DIV/0! | I61: =SUM(I60/I59) -> #DIV/0! | ... M61: =SUM(M60/M59) -> #DIV/0! | O61: =SUM(O60/O59) -> 0.72856085 | Q61: =SUM(Q60/Q59) -> 0.72856085
B65: PIZZA OFFERT | N65: =O68 -> 3000 | O65: =O59 -> 1177.79 | P65: STOCK
B66: =B59 -> 0 | C66: =C59 -> 0 | D66: =D59 -> 0 | E66: =E59 -> 0 | F66: =F59 -> 0 | G66: =G59 -> 1177.79 | H66: =H59 -> 0 | I66: =I59 -> 0 | ... M66: =M59 -> 0 | O66: =SUM(O65-N65) -> -1822.21 | P66: =W67 -> 0 | Q66: =SUM(O66-P66) -> -1822.21
B67: =B60 -> 0 | C67: =C60 -> 0 | D67: =D60 -> 0 | E67: =E60 -> 0 | F67: =F60 -> 0 | G67: =G60 -> 858.09169 | H67: =H60 -> 0 | I67: =I60 -> 0 | ... M67: =M60 -> 0 | O67: =SUM(B67:N67) -> 858.09169 | Q67: =O67 -> 858.09169
B68: 400 | C68: 800 | D68: 800 | E68: 1000 | O68: =SUM(B68:M68) -> 3000
B69: =SUM(B67:B68) -> 400 | C69: =SUM(C67:C68) -> 800 | D69: =SUM(D67:D68) -> 800 | E69: =SUM(E67:E68) -> 1000 | F69: =SUM(F67:F68) -> 0 | G69: =SUM(G67:G68) -> 858.09169 | H69: =SUM(H67:H68) -> 0 | I69: =SUM(I67:I68) -> 0 | ... O69: =SUM(O67:O68) -> 3858.0917 | Q69: =O69 -> 3858.0917
B70: =SUM(B69/B66) -> #DIV/0! | C70: =SUM(C69/C66) -> #DIV/0! | D70: =SUM(D69/D66) -> #DIV/0! | E70: =SUM(E69/E66) -> #DIV/0! | F70: =SUM(F69/F66) -> #DIV/0! | G70: =SUM(G69/G66) -> 0.72856085 | H70: =SUM(H69/H66) -> #DIV/0! | I70: =SUM(I69/I66) -> #DIV/0! | ... M70: =SUM(M69/M66) -> #DIV/0! | O70: =SUM(O69/O66) -> -2.1172596 | Q70: =SUM(Q69/Q66) -> -2.1172596
